Workbook

Sheet C1P
H3: =SUM(D15:G15) -> 37909 | I3: =SUM(H15:K15) -> 38717
A5: Producto Interno Bruto (PIB) | CF5: =SUM(CF15:CI15) -> 63888.121
A7: Series encadenadas de volumen con año de referencia 2015 | I7: Índice
A8: Datos originales | I8: Tasa de crecimiento anual
A9: Miles de millones de pesos | I9: Tasa de crecimiento año corrido
A10: 2005 - 2025pr cuarto trimestre
H11: =SUM(D15:G15) -> 37909
A12: Clasificación Cuentas Nacionales | B12: Secciones CIIU Rev. 4 A.C. 12 agrupaciones | C12: Concepto | D12: 2005 | H12: 2006 | L12: 2007 | P12: 2008 | T12: 2009 | X12: 2010 | AB12: 2011 | AF12: 2012 | AJ12: 2013 | AN12: 2014 | AR12: 2015 | AV12: 2016 | AZ12: 2017 | BD12: 2018 | BH12: 2019 | BL12: 2020 | BP12: 2021 | BT12: 2022 | BX12: 2023 | BY12: 2023pr | CB12: 2024p | CC12: 2023pr | CF12: 2025pr | CG12: 2023pr
D13: I | E13: II | F13: III | G13: IV | H13: I | I13: II | J13: III | K13: IV | L13: I | M13: II | N13: III | O13: IV | P13: I | Q13: II | R13: III | S13: IV | T13: I | U13: II | V13: III | W13: IV | X13: I | Y13: II | Z13: III | AA13: IV | AB13: I | AC13: II | AD13: III | AE13: IV | AF13: I | AG13: II | AH13: III | AI13: IV | AJ13: I | AK13: II | AL13: III | AM13: IV | AN13: I | AO13: II | AP13: III | AQ13: IV | AR13: I | AS13: II | AT13: III | AU13: IV | AV13: I | AW13: II | AX13: III | AY13: IV | AZ13: I | BA13: II | BB13: III | BC13: IV | BD13: I | BE13: II | BF13: III | BG13: IV | BH13: I | BI13: II | BJ13: III | BK13: IV | BL13: I | BM13: II | BN13: III | BO13: IV | BP13: I | BQ13: II | BR13: III | BS13: IV | BT13: I | BU13: II | BV13: III | BW13: IV | BX13: I | BY13: II | BZ13: III | CA13: IV | CB13: I | CC13: II | CD13: III | CE13: IV | CF13: I | CG13: II | CH13: III | CI13: IV
B15: A | C15: Agricultura, ganadería, caza, silvicultura y pesca | D15: 8790.3092 | E15: 9235.9265 | F15: 10131.952 | G15: 9750.8127 | H15: 8923.1481 | I15: 9216.8047 | J15: 10502.225 | K15: 10074.822 | L15: 9277.8062 | M15: 9552.3759 | N15: 11016.705 | O15: 10392.113 | P15: 9494.4998 | Q15: 9574.5342 | R15: 10898.67 | S15: 9947.2955 | T15: 9201.6384 | U15: 9303.5289 | V15: 11099.46 | W15: 10217.373 | X15: 9170.0768 | Y15: 9530.0457 | Z15: 10815.285 | AA15: 10427.593 | AB15: 9793.664 | AC15: 9701.6391 | AD15: 10878.875 | AE15: 10331.822 | AF15: 9960.5478 | AG15: 10218.776 | AH15: 11143.14 | AI15: 10402.536 | AJ15: 10305.601 | AK15: 11359.853 | AL15: 11956.095 | AM15: 11213.45 | AN15: 11097.83 | AO15: 11269.929 | AP15: 12185.836 | AQ15: 11586.405 | AR15: 11447.884 | AS15: 11579.526 | AT15: 13022.909 | AU15: 12073.681 | AV15: 11376.929 | AW15: 11692.178 | AX15: 13220.071 | AY15: 13151.821 | AZ15: 12648.93 | BA15: 12427.807 | BB15: 14008.503 | BC15: 13112.759 | BD15: 12764.937 | BE15: 12913.669 | BF15: 14140.695 | BG15: 13210.699 | BH15: 12947.978 | BI15: 13064.055 | BJ15: 14642.832 | BK15: 13816.135 | BL15: 13676.434 | BM15: 12926.396 | BN15: 14751.586 | BO15: 14184.584 | BP15: 14227.403 | BQ15: 13762.484 | BR15: 15219.863 | BS15: 14758.251 | BT15: 14019.812 | BU15: 14052.89 | BV15: 15095.528 | BW15: 14273.771 | BX15: 14137.414 | BY15: 13847.922 | BZ15: 15306.853 | CA15: 15096.811 | CB15: 14544.976 | CC15: 14876.726 | CD15: 16622.435 | CE15: 15922.863 | CF15: 15468.067 | CG15: 15430.091 | CH15: 17134.602 | CI15: 15855.361
B16: B | C16: Explotación de minas y canteras | D16: 6592.3892 | E16: 6869.3947 | F16: 6834.0478 | G16: 7134.1683 | H16: 6865.1489 | I16: 6797.3004 | J16: 7082.3134 | K16: 7314.2373 | L16: 6722.2691 | M16: 6878.8022 | N16: 7124.0003 | O16: 7708.9284 | P16: 7463.2658 | Q16: 7589.8046 | R16: 7913.3793 | S16: 8134.5503 | T16: 8054.5977 | U16: 8417.0066 | V16: 8698.6562 | W16: 9488.7395 | X16: 9243.1811 | Y16: 9722.948 | Z16: 9487.7341 | AA16: 9973.1368 | AB16: 10169.974 | AC16: 10924.63 | AD16: 11205.7 | AE16: 11673.696 | AF16: 11328.974 | AG16: 11547.73 | AH16: 11437.228 | AI16: 12021.068 | AJ16: 11666.955 | AK16: 12100.884 | AL16: 12193.107 | AM16: 12833.054 | AN16: 12147.824 | AO16: 11648.281 | AP16: 11904.877 | AQ16: 12435.018 | AR16: 11822.424 | AS16: 11981.225 | AT16: 11604.12 | AU16: 12219.231 | AV16: 11686.431 | AW16: 11380.396 | AX16: 11476.119 | AY16: 11710.054 | AZ16: 10729.042 | BA16: 10852.107 | BB16: 10732.087 | BC16: 11278.764 | BD16: 10228.693 | BE16: 10506.302 | BF16: 10740.397 | BG16: 11392.607 | BH16: 10714.291 | BI16: 10558.258 | BJ16: 10773.46 | BK16: 11646.991 | BL16: 10372.59 | BM16: 8353.0282 | BN16: 8813.815 | BO16: 9516.5669 | BP16: 8916.1366 | BQ16: 8788.8475 | BR16: 9025.3914 | BS16: 10249.625 | BT16: 9106.7119 | BU16: 9076.7185 | BV16: 9664.3824 | BW16: 9670.1872 | BX16: 9404.7982 | BY16: 9382.9909 | BZ16: 9868.8485 | CA16: 9824.3624 | CB16: 9334.0928 | CC16: 9205.0128 | CD16: 9315.8093 | CE16: 9313.0851 | CF16: 8800.01 | CG16: 8260.8344 | CH16: 8764.5722 | CI16: 9042.8604
B17: C | C17: Industrias manufactureras | D17: 17589.141 | E17: 19231.589 | F17: 20020.828 | G17: 20410.442 | H17: 18696.145 | I17: 19896.254 | J17: 21916.025 | K17: 22376.576 | L17: 20585.558 | M17: 21585.35 | N17: 23114.862 | O17: 24034.23 | P17: 21455.898 | Q17: 22279.229 | R17: 23089.636 | S17: 22814.237 | T17: 20534.213 | U17: 20829.399 | V17: 22290.69 | W17: 22699.698 | X17: 20599.938 | Y17: 21568.781 | Z17: 22505.659 | AA17: 23305.622 | AB17: 21875.783 | AC17: 22592.285 | AD17: 24227.686 | AE17: 24200.245 | AF17: 22554.935 | AG17: 22856.841 | AH17: 24219.153 | AI17: 24036.071 | AJ17: 21586.527 | AK17: 23707.988 | AL17: 24754.432 | AM17: 25032.053 | AN17: 23069.198 | AO17: 23912.265 | AP17: 25352.407 | AQ17: 25495.13 | AR17: 23229.668 | AS17: 24148.232 | AT17: 25925.717 | AU17: 26485.382 | AV17: 24236.419 | AW17: 25602.738 | AX17: 26290.843 | AY17: 26876 | AZ17: 24391.063 | BA17: 24436.141 | BB17: 26003.398 | BC17: 26304.397 | BD17: 23834.359 | BE17: 25367.316 | BF17: 26513.098 | BG17: 26912.228 | BH17: 24377.308 | BI17: 25331.828 | BJ17: 26876.768 | BK17: 27274.095 | BL17: 24082.005 | BM17: 18387.012 | BN17: 24804.771 | BO17: 26980.211 | BP17: 25251.992 | BQ17: 24095.48 | BR17: 28505.911 | BS17: 29212.617 | BT17: 27301.263 | BU17: 28402.716 | BV17: 30101.686 | BW17: 29996.336 | BX17: 28122.632 | BY17: 27987.521 | BZ17: 28867.953 | CA17: 28946.894 | CB17: 26568.445 | CC17: 27416.931 | CD17: 28217.097 | CE17: 28800.528 | CF17: 26947.14 | CG17: 27631.096 | CH17: 29383.819 | CI17: 29094.506
B18: D + E | C18: Suministro de electricidad, gas, vapor y aire acondicionado; Distribución de agua; evacuación y tratamiento de aguas residuales, gestión de desechos y actividades de saneamiento ambiental | D18: 4569.4659 | E18: 4654.2027 | F18: 4723.8287 | G18: 4737.5027 | H18: 4806.4049 | I18: 4866.9413 | J18: 4954.7764 | K18: 5050.8773 | L18: 5116.3782 | M18: 5061.9166 | N18: 5125.0681 | O18: 5207.637 | P18: 5034.5067 | Q18: 5105.0712 | R18: 5200.1237 | S18: 5279.2984 | T18: 5058.2893 | U18: 5149.9549 | V18: 5358.795 | W18: 5545.9608 | X18: 5477.8293 | Y18: 5447.405 | Z18: 5517.4241 | AA18: 5492.3415 | AB18: 5611.66 | AC18: 5583.229 | AD18: 5701.7854 | AE18: 5711.3256 | AF18: 5734.2276 | AG18: 5709.7382 | AH18: 5841.8436 | AI18: 5808.1907 | AJ18: 5847.2276 | AK18: 5978.505 | AL18: 6062.4855 | AM18: 6061.7819 | AN18: 6109.9747 | AO18: 6198.7077 | AP18: 6289.244 | AQ18: 6175.0736 | AR18: 6069.884 | AS18: 6065.2999 | AT18: 6266.4382 | AU18: 6197.3779 | AV18: 6137.1828 | AW18: 6011.9198 | AX18: 6214.7722 | AY18: 6233.1252 | AZ18: 6168.4074 | BA18: 6200.6571 | BB18: 6462.2663 | BC18: 6475.6693 | BD18: 6294.5868 | BE18: 6370.4434 | BF18: 6655.0361 | BG18: 6631.9337 | BH18: 6491.7604 | BI18: 6540.1256 | BJ18: 6819.5981 | BK18: 6754.5158 | BL18: 6612.8675 | BM18: 5923.1188 | BN18: 6431.8586 | BO18: 6619.1551 | BP18: 6522.1206 | BQ18: 6483.7845 | BR18: 6987.0198 | BS18: 7086.0751 | BT18: 6904.8012 | BU18: 6973.4849 | BV18: 7205.5573 | BW18: 7243.1566 | BX18: 7069.128 | BY18: 7148.6124 | BZ18: 7473.9116 | CA18: 7529.348 | CB18: 7462.8136 | CC18: 7363.8831 | CD18: 7572.2763 | CE18: 7549.0271 | CF18: 7363.7066 | CG18: 7430.3135 | CH18: 7728.2987 | CI18: 7767.2836
B19: F | C19: Construcción | D19: 7664.2016 | E19: 6279.2183 | F19: 7076.3523 | G19: 8788.2278 | H19: 8116.8906 | I19: 6978.6757 | J19: 8327.2679 | K19: 10004.166 | L19: 8636.1703 | M19: 8330.4976 | N19: 8744.1252 | O19: 10036.207 | P19: 8762.6427 | Q19: 9786.3606 | R19: 10723.559 | S19: 10016.438 | T19: 8473.3176 | U19: 10614.757 | V19: 10347.871 | W19: 10880.054 | X19: 8909.8084 | Y19: 9646.8102 | Z19: 9941.597 | AA19: 11549.784 | AB19: 9096.0198 | AC19: 10513.935 | AD19: 11102.807 | AE19: 11823.238 | AF19: 10710.469 | AG19: 12076.412 | AH19: 10256.528 | AI19: 12007.59 | AJ19: 10894.653 | AK19: 12755.641 | AL19: 13063.174 | AM19: 13417.533 | AN19: 12469.589 | AO19: 13578.946 | AP19: 14398.541 | AQ19: 14154.924 | AR19: 13195.72 | AS19: 14903.054 | AT19: 14659.67 | AU19: 15283.556 | AV19: 14339.67 | AW19: 15286.252 | AX19: 15325.918 | AY19: 15173.16 | AZ19: 13715.937 | BA19: 15117.399 | BB19: 15003.007 | BC19: 15070.658 | BD19: 13571.103 | BE19: 14121.17 | BF19: 15326.309 | BG19: 15137.418 | BH19: 13598.259 | BI19: 13877.765 | BJ19: 14015.097 | BK19: 14401.879 | BL19: 11086.692 | BM19: 7838.7481 | BN19: 9796.7456 | BO19: 10636.814 | BP19: 10305.013 | BQ19: 9706.9536 | BR19: 9771.9111 | BS19: 11255.122 | BT19: 10827.442 | BU19: 10621.912 | BV19: 11169.294 | BW19: 11146.352 | BX19: 10630.611 | BY19: 10483.337 | BZ19: 10337.714 | CA19: 10960.339 | CB19: 10571.505 | CC19: 10494.32 | CD19: 10549.124 | CE19: 10833.051 | CF19: 10253.109 | CG19: 10119.096 | CH19: 10350.991 | CI19: 10549.857
B20: G + H + I | C20: Comercio al por mayor y al por menor; reparación de vehículos automotores y motocicletas; Transporte y almacenamiento; Alojamiento y servicios de comida | D20: 19640.391 | E20: 20946.162 | F20: 21324.236 | G20: 23516.211 | H20: 20786.839 | I20: 22218.285 | J20: 23316.259 | K20: 25604.617 | L20: 22680.962 | M20: 24012.078 | N20: 24969.726 | O20: 27680.234 | P20: 24083.328 | Q20: 24987.794 | R20: 25526.739 | S20: 27748.138 | T20: 23694.795 | U20: 24819.381 | V20: 25578.988 | W20: 28091.837 | X20: 24763.731 | Y20: 25986.494 | Z20: 26939.107 | AA20: 29957.668 | AB20: 26384.518 | AC20: 28029.435 | AD20: 28993.041 | AE20: 31656.006 | AF20: 28030.095 | AG20: 29187.252 | AH20: 29745.273 | AI20: 32490.38 | AJ20: 28781.369 | AK20: 30659.919 | AL20: 31290.788 | AM20: 34416.925 | AN20: 30361.573 | AO20: 31948.679 | AP20: 32734.375 | AQ20: 36018.373 | AR20: 31452.895 | AS20: 32855.095 | AT20: 33856.424 | AU20: 37264.586 | AV20: 32577.695 | AW20: 33669.427 | AX20: 34592.1 | AY20: 38226.779 | AZ20: 32976.282 | BA20: 34438.58 | BB20: 35788.653 | BC20: 38448.484 | BD20: 34235.812 | BE20: 35461.931 | BF20: 36420.056 | BG20: 39320.202 | BH20: 34982.89 | BI20: 36658.561 | BJ20: 38239.194 | BK20: 41009.355 | BL20: 36054.615 | BM20: 24740.586 | BN20: 30547.514 | BO20: 38892.285 | BP20: 35506.805 | BQ20: 34612.928 | BR20: 40031.075 | BS20: 46664.193 | BT20: 40847.977 | BU20: 42630.469 | BV20: 44588.873 | BW20: 47383.681 | BX20: 40482.128 | BY20: 40764.79 | BZ20: 41939.34 | CA20: 45880.742 | CB20: 40088.07 | CC20: 40740.826 | CD20: 42379.817 | CE20: 47942.286 | CF20: 41566.057 | CG20: 43106.4 | CH20: 44774.812 | CI20: 49574.508
B21: J | C21: Información y comunicaciones | D21: 2844.2886 | E21: 3064.9642 | F21: 2948.8702 | G21: 3871.877 | H21: 3373.8843 | I21: 3685.3631 | J21: 3482.4948 | K21: 4087.2579 | L21: 3792.7595 | M21: 3979.1224 | N21: 4361.3481 | O21: 4627.77 | P21: 4074.979 | Q21: 4182.6272 | R21: 4378.088 | S21: 4484.3057 | T21: 3842.6323 | U21: 3820.6827 | V21: 3713.0051 | W21: 4292.6799 | X21: 4063.0914 | Y21: 4461.016 | Z21: 4610.2349 | AA21: 5121.6577 | AB21: 4714.9302 | AC21: 4827.3913 | AD21: 5076.5355 | AE21: 5534.143 | AF21: 4855.8277 | AG21: 4875.427 | AH21: 4995.196 | AI21: 5688.5493 | AJ21: 5170.0999 | AK21: 5318.0308 | AL21: 5590.6069 | AM21: 6139.2624 | AN21: 5645.9837 | AO21: 5808.6139 | AP21: 5733.7076 | AQ21: 6465.6948 | AR21: 5667.8964 | AS21: 5762.5458 | AT21: 5972.0252 | AU21: 6558.5325 | AV21: 5686.9792 | AW21: 5811.0582 | AX21: 5921.5831 | AY21: 6384.3795 | AZ21: 5608.7036 | BA21: 5814.2199 | BB21: 5749.9205 | BC21: 6585.156 | BD21: 5651.2779 | BE21: 5971.2315 | BF21: 6146.0438 | BG21: 6826.4467 | BH21: 5839.0838 | BI21: 6136.1388 | BJ21: 6068.1294 | BK21: 6777.648 | BL21: 5873.0649 | BM21: 5773.356 | BN21: 5938.6877 | BO21: 6547.8914 | BP21: 6070.5757 | BQ21: 6453.3384 | BR21: 6784.3066 | BS21: 7901.7793 | BT21: 7335.7056 | BU21: 7528.2755 | BV21: 7644.5357 | BW21: 8055.4831 | BX21: 7515.6431 | BY21: 7597.515 | BZ21: 7557.3479 | CA21: 8363.494 | CB21: 7342.7285 | CC21: 7512.7271 | CD21: 7677.2645 | CE21: 8436.28 | CF21: 7375.3696 | CG21: 7731.4708 | CH21: 7823.9085 | CI21: 8338.2861
B22: K | C22: Actividades financieras y de seguros | D22: 3810.3818 | E22: 3800.1953 | F22: 3925.3989 | G22: 3888.024 | H22: 4202.7529 | I22: 3953.9212 | J22: 4048.895 | K22: 4234.4309 | L22: 4561.1293 | M22: 4599.9342 | N22: 4586.0106 | O22: 4954.9259 | P22: 5099.862 | Q22: 4877.9752 | R22: 5070.4059 | S22: 5549.7569 | T22: 5462.1108 | U22: 5157.4931 | V22: 5279.5132 | W22: 5415.8828 | X22: 5296.2107 | Y22: 5447.6775 | Z22: 5642.0479 | AA22: 5926.0639 | AB22: 6003.9846 | AC22: 6043.1246 | AD22: 6166.0615 | AE22: 6540.8292 | AF22: 6524.2746 | AG22: 6607.6521 | AH22: 6590.487 | AI22: 6903.5863 | AJ22: 7169.6678 | AK22: 7182.5977 | AL22: 7081.2146 | AM22: 7726.5199 | AN22: 7829.6591 | AO22: 7926.7305 | AP22: 8038.7947 | AQ22: 8343.8158 | AR22: 8693.2543 | AS22: 8621.381 | AT22: 8717.425 | AU22: 8663.9396 | AV22: 8891.1996 | AW22: 8745.9069 | AX22: 8923.4288 | AY22: 9165.4647 | AZ22: 9102.9347 | BA22: 9390.0797 | BB22: 9325.5308 | BC22: 9832.4547 | BD22: 9434.2971 | BE22: 9787.3618 | BF22: 9745.8787 | BG22: 10089.462 | BH22: 10069.694 | BI22: 10277.41 | BJ22: 10575.71 | BK22: 10582.186 | BL22: 10308.053 | BM22: 10402.776 | BN22: 10799.374 | BO22: 10922.796 | BP22: 10826.578 | BQ22: 10747.939 | BR22: 11041.781 | BS22: 11386.702 | BT22: 10486.922 | BU22: 11971.907 | BV22: 12091.992 | BW22: 12389.179 | BX22: 12989.231 | BY22: 12542.214 | BZ22: 12398.603 | CA22: 13204.951 | CB22: 12703.545 | CC22: 12815.961 | CD22: 13024.378 | CE22: 13140.116 | CF22: 13120.146 | CG22: 13175.098 | CH22: 13591.239 | CI22: 13225.859
B23: L | C23: Actividades inmobiliarias | D23: 12401.89 | E23: 12505.838 | F23: 12581.406 | G23: 12743.867 | H23: 12835.292 | I23: 12986.941 | J23: 13131.315 | K23: 13311.451 | L23: 13380.504 | M23: 13496.911 | N23: 13600.448 | O23: 13747.137 | P23: 13726.531 | Q23: 13859.252 | R23: 13986.592 | S23: 14158.625 | T23: 14228.179 | U23: 14385.003 | V23: 14523.249 | W23: 14729.569 | X23: 14779.178 | Y23: 14910.885 | Z23: 15046.183 | AA23: 15195.754 | AB23: 15205.731 | AC23: 15323.855 | AD23: 15453.995 | AE23: 15644.418 | AF23: 15666.453 | AG23: 15799.927 | AH23: 15962.479 | AI23: 16150.141 | AJ23: 16166.466 | AK23: 16322.597 | AL23: 16465.748 | AM23: 16670.19 | AN23: 16689.594 | AO23: 16818.508 | AP23: 16975.09 | AQ23: 17180.808 | AR23: 17186.368 | AS23: 17335.378 | AT23: 17504.971 | AU23: 17798.283 | AV23: 17772.654 | AW23: 17992.276 | AX23: 18139.395 | AY23: 18384.676 | AZ23: 18350.569 | BA23: 18499.075 | BB23: 18672.652 | BC23: 18972.703 | BD23: 18957.811 | BE23: 19225.038 | BF23: 19503.435 | BG23: 19762.716 | BH23: 19787.092 | BI23: 19945.321 | BJ23: 20054.546 | BK23: 20177.041 | BL23: 20178.06 | BM23: 20077.666 | BN23: 20327.08 | BO23: 20535.195 | BP23: 20564.352 | BQ23: 20725.468 | BR23: 20845.947 | BS23: 21007.233 | BT23: 21033.94 | BU23: 21154.666 | BV23: 21277.515 | BW23: 21376.88 | BX23: 21413.302 | BY23: 21535.002 | BZ23: 21650.711 | CA23: 21813.985 | CB23: 21859.527 | CC23: 22024.482 | CD23: 22130.745 | CE23: 22307.246 | CF23: 22294.963 | CG23: 22461.557 | CH23: 22586.541 | CI23: 22730.744
B24: M + N | C24: Actividades profesionales, científicas y técnicas; Actividades de servicios administrativos y de apoyo | D24: 8402.0467 | E24: 8655.4516 | F24: 8856.4296 | G24: 10143.072 | H24: 8999.3431 | I24: 9239.7882 | J24: 9514.4231 | K24: 10838.446 | L24: 9631.1004 | M24: 9851.5071 | N24: 10218.567 | O24: 11544.825 | P24: 10102.937 | Q24: 10245.351 | R24: 10523.532 | S24: 11928.18 | T24: 10374.737 | U24: 10640.268 | V24: 10829.496 | W24: 12153.5 | X24: 10612.298 | Y24: 10917.585 | Z24: 11144.774 | AA24: 12679.342 | AB24: 11223.772 | AC24: 11601.396 | AD24: 12023.357 | AE24: 13719.476 | AF24: 11913.935 | AG24: 12224.618 | AH24: 12503.465 | AI24: 14264.982 | AJ24: 12258.593 | AK24: 12779.855 | AL24: 13241.204 | AM24: 15313.348 | AN24: 13328.007 | AO24: 13817.407 | AP24: 14191.572 | AQ24: 16163.013 | AR24: 13599.603 | AS24: 13844.779 | AT24: 14336.372 | AU24: 15611.246 | AV24: 13178.921 | AW24: 13527.314 | AX24: 13825.219 | AY24: 15463.546 | AZ24: 13214.524 | BA24: 13763.548 | BB24: 14114.122 | BC24: 15717.807 | BD24: 13658.468 | BE24: 14355.241 | BF24: 14694.811 | BG24: 16357.48 | BH24: 14195.182 | BI24: 14941.176 | BJ24: 15230.074 | BK24: 16735.568 | BL24: 14365.937 | BM24: 13079.188 | BN24: 13982.755 | BO24: 16136.119 | BP24: 14521.193 | BQ24: 14945.735 | BR24: 15796.752 | BS24: 17903.32 | BT24: 15770.851 | BU24: 16887.861 | BV24: 16935.938 | BW24: 18537.35 | BX24: 16313.72 | BY24: 17130.495 | BZ24: 17115.185 | CA24: 18877.599 | CB24: 16246.072 | CC24: 17065.705 | CD24: 17030.614 | CE24: 18803.608 | CF24: 16435.695 | CG24: 17331.799 | CH24: 17229.349 | CI24: 19076.803
B25: O + P + Q | C25: Administración pública y defensa; planes de seguridad social de afiliación obligatoria; Educación; Actividades de atención de la salud humana y de servicios sociales | D25: 17323.157 | E25: 17123.79 | F25: 17441.522 | G25: 19293.531 | H25: 17962.104 | I25: 17682.049 | J25: 18320.527 | K25: 20504.321 | L25: 18578.296 | M25: 18342.234 | N25: 19172.742 | O25: 21420.728 | P25: 19293.585 | Q25: 19092.906 | R25: 19329.088 | S25: 21451.421 | T25: 19581.38 | U25: 19586.838 | V25: 20084.098 | W25: 22328.684 | X25: 20565.505 | Y25: 20464.51 | Z25: 20788.83 | AA25: 23543.155 | AB25: 21746.413 | AC25: 21509.709 | AD25: 21968.947 | AE25: 25039.931 | AF25: 22844.961 | AG25: 22690.911 | AH25: 23288.938 | AI25: 26458.19 | AJ25: 23741.823 | AK25: 24107.805 | AL25: 24673.471 | AM25: 28007.902 | AN25: 25318.739 | AO25: 25166.905 | AP25: 26129.321 | AQ25: 29793.035 | AR25: 26821.055 | AS25: 27080.491 | AT25: 28737.271 | AU25: 29438.183 | AV25: 27319 | AW25: 28326.971 | AX25: 28963.345 | AY25: 31588.685 | AZ25: 28195.339 | BA25: 29338.96 | BB25: 29880.42 | BC25: 32807.28 | BD25: 29321.273 | BE25: 30904.023 | BF25: 31330.751 | BG25: 34359.953 | BH25: 30720.95 | BI25: 32627.214 | BJ25: 33015.831 | BK25: 35969.006 | BL25: 31068.918 | BM25: 31821.613 | BN25: 32417.007 | BO25: 37434.462 | BP25: 33193.705 | BQ25: 35088.196 | BR25: 35833.306 | BS25: 39858.793 | BT25: 34337.153 | BU25: 37060.605 | BV25: 35441.405 | BW25: 38749.837 | BX25: 34488.205 | BY25: 38875.121 | BZ25: 38036.565 | CA25: 41372.109 | CB25: 36481.815 | CC25: 40564.422 | CD25: 38604.022 | CE25: 43329.741 | CF25: 37800.812 | CG25: 41235.697 | CH25: 41662.98 | CI25: 45416.907
B26: R + S + T | C26: Actividades artísticas, de entretenimiento y recreación y otras actividades de servicios; Actividades de los hogares individuales en calidad de empleadores; actividades no diferenciadas de los hogares individuales como productores de bienes y servicios para uso propio | D26: 3062.3467 | E26: 3086.6502 | F26: 3230.2451 | G26: 3396.758 | H26: 3227.5616 | I26: 3289.4725 | J26: 3396.6279 | K26: 3510.338 | L26: 3400.4915 | M26: 3434.68 | N26: 3535.0164 | O26: 3764.812 | P26: 3531.8089 | Q26: 3539.6989 | R26: 3662.2171 | S26: 3824.2751 | T26: 3580.6588 | U26: 3626.0585 | V26: 3733.475 | W26: 3956.8077 | X26: 3712.3652 | Y26: 3688.6975 | Z26: 3833.5657 | AA26: 4024.3716 | AB26: 3852.8437 | AC26: 3939.0594 | AD26: 4150.9522 | AE26: 4245.1448 | AF26: 3989.2292 | AG26: 3998.5042 | AH26: 4348.4977 | AI26: 4340.7688 | AJ26: 4190.118 | AK26: 4246.1099 | AL26: 4531.9183 | AM26: 4749.8539 | AN26: 4442.555 | AO26: 4293.2336 | AP26: 4651.0877 | AQ26: 4823.1236 | AR26: 4539.4797 | AS26: 4496.6079 | AT26: 4848.5142 | AU26: 5097.3982 | AV26: 4811.6792 | AW26: 4805.5432 | AX26: 5107.5146 | AY26: 5309.263 | AZ26: 4954.6159 | BA26: 4894.9117 | BB26: 5191.2952 | BC26: 5415.1772 | BD26: 4833.623 | BE26: 5006.4008 | BF26: 5309.3039 | BG26: 5775.6723 | BH26: 5431.1567 | BI26: 5766.8764 | BJ26: 6013.0322 | BK26: 6441.9347 | BL26: 5635.939 | BM26: 3809.3984 | BN26: 5345.5629 | BO26: 6074.0998 | BP26: 6168.9947 | BQ26: 6736.1924 | BR26: 7153.1327 | BS26: 7989.6802 | BT26: 8042.7311 | BU26: 8340.2724 | BV26: 8980.3246 | BW26: 10568.672 | BX26: 9260.1955 | BY26: 9452.4622 | BZ26: 9928.354 | CA26: 11019.988 | CB26: 9831.645 | CC26: 10481.125 | CD26: 11064.665 | CE26: 11532.565 | CF26: 11363.528 | CG26: 11290.01 | CH26: 11638.34 | CI26: 12863.459
A27: B.1b | C27: Valor agregado bruto | D27: 111789.94 | E27: 115152.44 | F27: 118810.66 | G27: 126941.96 | H27: 118008.18 | I27: 120449.4 | J27: 127605.65 | K27: 135926.77 | L27: 125486.91 | M27: 128480.24 | N27: 135324.7 | O27: 144364.16 | P27: 131462.23 | Q27: 134338.88 | R27: 139797.04 | S27: 144564.85 | T27: 131692.99 | U27: 135619.68 | V27: 141259.09 | W27: 149381.24 | X27: 136962.7 | Y27: 141727.64 | Z27: 146460.78 | AA27: 156981.87 | AB27: 145905.14 | AC27: 150842.53 | AD27: 157551.37 | AE27: 166352.96 | AF27: 154648.87 | AG27: 158182.84 | AH27: 161013.73 | AI27: 170730.55 | AJ27: 158395.23 | AK27: 166948.62 | AL27: 171561.32 | AM27: 181920.82 | AN27: 168936.11 | AO27: 172331.83 | AP27: 178821.9 | AQ27: 188641.16 | AR27: 173726.18 | AS27: 178673.6 | AT27: 185451.82 | AU27: 192691.39 | AV27: 178014.88 | AW27: 182852.11 | AX27: 188000.32 | AY27: 197666.69 | AZ27: 180127.58 | BA27: 185272.23 | BB27: 191235.85 | BC27: 200239.34 | BD27: 182983.72 | BE27: 190157.25 | BF27: 196700.65 | BG27: 206066.37 | BH27: 189395.25 | BI27: 195906.44 | BJ27: 202482.3 | BK27: 211930 | BL27: 189639.81 | BM27: 163258.88 | BN27: 183882.66 | BO27: 204587.65 | BP27: 192289.73 | BQ27: 192325.5 | BR27: 207382.42 | BS27: 225751.35 | BT27: 206170.42 | BU27: 214522.88 | BV27: 220414.01 | BW27: 229104.69 | BX27: 211695.28 | BY27: 215981.05 | BZ27: 220969.14 | CA27: 232186.53 | CB27: 212938.45 | CC27: 219935.49 | CD27: 224560.36 | CE27: 237495.7 | CF27: 218543.41 | CG27: 224497.67 | CH27: 232840.97 | CI27: 242850.38
A28: D.21-D.31 | C28: Impuestos menos subvenciones sobre los productos | D28: 9461.1759 | E28: 10489.427 | F28: 10524.587 | G28: 12049.81 | H28: 10898.716 | I28: 11818.069 | J28: 11590.958 | K28: 13319.257 | L28: 12039.845 | M28: 12851.973 | N28: 13302.309 | O28: 14618.873 | P28: 13141.885 | Q28: 13740.322 | R28: 13766.813 | S28: 14851.981 | T28: 13107.436 | U28: 13478.292 | V28: 13149.921 | W28: 14879.351 | X28: 13457.875 | Y28: 14277.474 | Z28: 14196.064 | AA28: 16074.587 | AB28: 14757.135 | AC28: 15763.246 | AD28: 15818.037 | AE28: 17662.581 | AF28: 15874.963 | AG28: 16496.007 | AH28: 16251.426 | AI28: 18250.604 | AJ28: 16181.034 | AK28: 17093.4 | AL28: 16774.014 | AM28: 19046.552 | AN28: 17153.629 | AO28: 18044.411 | AP28: 17784.418 | AQ28: 19916.543 | AR28: 17637.047 | AS28: 18187.96 | AT28: 18181.901 | AU28: 20142.092 | AV28: 17892.884 | AW28: 18186.892 | AX28: 18805.261 | AY28: 20069.963 | AZ28: 17867.662 | BA28: 18309.314 | BB28: 19059.824 | BC28: 20536.2 | BD28: 18283.141 | BE28: 19028.383 | BF28: 19656.676 | BG28: 21119.8 | BH28: 18867.206 | BI28: 19710.93 | BJ28: 20636.811 | BK28: 22274.053 | BL28: 19339.304 | BM28: 16331.817 | BN28: 18971.359 | BO28: 21847.52 | BP28: 19816.985 | BQ28: 20359.037 | BR28: 22551.372 | BS28: 25912.607 | BT28: 23203.517 | BU28: 24569.512 | BV28: 26617.005 | BW28: 28469.967 | BX28: 24117.599 | BY28: 24044.634 | BZ28: 24890.796 | CA28: 27220.972 | CB28: 23595.205 | CC28: 23899.489 | CD28: 25243.377 | CE28: 28036.93 | CF28: 24110.161 | CG28: 24491.472 | CH28: 25934.277 | CI28: 28731.272
A29: B.1b | C29: Producto Interno Bruto | D29: 121117.73 | E29: 125559.34 | F29: 129223.31 | G29: 138952.62 | H29: 128839.68 | I29: 132242.91 | J29: 139114.41 | K29: 149238 | L29: 137488.52 | M29: 141316.5 | N29: 148649.97 | O29: 159002.02 | P29: 144602.69 | Q29: 148078.93 | R29: 153584.53 | S29: 159446.84 | T29: 144812.49 | U29: 149108.6 | V29: 154402.16 | W29: 164292.74 | X29: 150431.72 | Y29: 156004.2 | Z29: 160651.52 | AA29: 173063.55 | AB29: 160659.88 | AC29: 166585.33 | AD29: 173372.36 | AE29: 184010.44 | AF29: 170516.61 | AG29: 174658.12 | AH29: 177268.45 | AI29: 188971.82 | AJ29: 174578.04 | AK29: 184043.02 | AL29: 188345.14 | AM29: 200972.79 | AN29: 186100.22 | AO29: 190347.09 | AP29: 196605.87 | AQ29: 208535.82 | AR29: 191363.28 | AS29: 196861.4 | AT29: 203635.77 | AU29: 212831.55 | AV29: 195907.74 | AW29: 201038.99 | AX29: 206805.58 | AY29: 217736.68 | AZ29: 198002.9 | BA29: 203591.84 | BB29: 210300.68 | BC29: 220760.57 | BD29: 201268.45 | BE29: 209187.55 | BF29: 216359.03 | BG29: 227192.98 | BH29: 208263.59 | BI29: 215620.27 | BJ29: 223124.46 | BK29: 234215.69 | BL29: 208984.37 | BM29: 179587.95 | BN29: 202864.17 | BO29: 226463.51 | BP29: 212118.51 | BQ29: 212672.15 | BR29: 229893.55 | BS29: 251558.79 | BT29: 229311 | BU29: 239013.85 | BV29: 246908.06 | BW29: 257422.1 | BX29: 235748.94 | BY29: 239983.68 | BZ29: 245804.91 | CA29: 259305.47 | CB29: 236500.46 | CC29: 243822.84 | CD29: 249751.85 | CE29: 265414.85 | CF29: 242632.98 | CG29: 248985.66 | CH29: 258737.57 | CI29: 271434.71
A31: Fuente: DANE, PIB_T
A32: prpreliminar
A33: pprovisional
A34: Actualizado el 16 de febrero de 2026
A39: Producto Interno Bruto (PIB)
A41: Tasa de crecimiento anual (%)
A42: Base 2015
A43: 2006 - 2025pr cuarto trimestre
A45: Clasificación Cuentas Nacionales | B45: Secciones CIIU Rev. 4 A.C. 12 agrupaciones | C45: Concepto | H45: 2006 | L45: 2007 | P45: 2008 | T45: 2009 | X45: 2010 | AB45: 2011 | AF45: 2012 | AJ45: 2013 | AN45: 2014 | AR45: 2015 | AV45: 2016 | AZ45: 2017 | BD45: 2018 | BH45: 2019 | BL45: 2020 | BP45: 2021 | BT45: 2022 | BX45: 2023 | BY45: 2023pr | CB45: 2024p | CC45: 2023pr | CF45: 2025pr | CG45: 2023pr
H46: I | I46: II | J46: III | K46: IV | L46: I | M46: II | N46: III | O46: IV | P46: I | Q46: II | R46: III | S46: IV | T46: I | U46: II | V46: III | W46: IV | X46: I | Y46: II | Z46: III | AA46: IV | AB46: I | AC46: II | AD46: III | AE46: IV | AF46: I | AG46: II | AH46: III | AI46: IV | AJ46: I | AK46: II | AL46: III | AM46: IV | AN46: I | AO46: II | AP46: III | AQ46: IV | AR46: I | AS46: II | AT46: III | AU46: IV | AV46: I | AW46: II | AX46: III | AY46: IV | AZ46: I | BA46: II | BB46: III | BC46: IV | BD46: I | BE46: II | BF46: III | BG46: IV | BH46: I | BI46: II | BJ46: III | BK46: IV | BL46: I | BM46: II | BN46: III | BO46: IV | BP46: I | BQ46: II | BR46: III | BS46: IV | BT46: I | BU46: II | BV46: III | BW46: IV | BX46: I | BY46: II | BZ46: III | CA46: IV | CB46: I | CC46: II | CD46: III | CE46: IV | CF46: I | CG46: II | CH46: III | CI46: IV
B48: A | C48: Agricultura, ganadería, caza, silvicultura y pesca | H48: 1.5111974 | I48: -0.20703641 | J48: 3.65451 | K48: 3.3228986 | L48: 3.9745853 | M48: 3.6408622 | N48: 4.8987757 | O48: 3.1493386 | P48: 2.3356123 | Q48: 0.23196598 | R48: -1.0714161 | S48: -4.2803336 | T48: -3.084537 | U48: -2.8304797 | V48: 1.8423266 | W48: 2.7150847 | X48: -0.34300037 | Y48: 2.4347402 | Z48: -2.560258 | AA48: 2.057473 | AB48: 6.8002401 | AC48: 1.8005525 | AD48: 0.58796269 | AE48: -0.91843394 | AF48: 1.7039971 | AG48: 5.3304103 | AH48: 2.4291601 | AI48: 0.6844271 | AJ48: 3.4642009 | AK48: 11.166476 | AL48: 7.2955695 | AM48: 7.7953485 | AN48: 7.6873635 | AO48: -0.79159647 | AP48: 1.9215319 | AQ48: 3.3259613 | AR48: 3.1542569 | AS48: 2.7471012 | AT48: 6.8692315 | AU48: 4.2055867 | AV48: -0.61981064 | AW48: 0.97285977 | AX48: 1.5139667 | AY48: 8.9296722 | AZ48: 11.180531 | BA48: 6.2916322 | BB48: 5.9639012 | BC48: -0.29700746 | BD48: 0.91712616 | BE48: 3.9094741 | BF48: 0.94365531 | BG48: 0.74690207 | BH48: 1.4339385 | BI48: 1.1645482 | BJ48: 3.5510067 | BK48: 4.5829196 | BL48: 5.626021 | BM48: -1.053723 | BN48: 0.74270785 | BO48: 2.666806 | BP48: 4.0286004 | BQ48: 6.4680648 | BR48: 3.1744183 | BS48: 4.044295 | BT48: -1.4590949 | BU48: 2.1101292 | BV48: -0.81692761 | BW48: -3.2827712 | BX48: 0.83882936 | BY48: -1.4585479 | BZ48: 1.3999223 | CA48: 5.7661018 | CB48: 2.8828639 | CC48: 7.4293046 | CD48: 8.5947228 | CE48: 5.4716966 | CF48: 6.3464589 | CG48: 3.7196677 | CH48: 3.0811817 | CI48: -0.42393249
B49: B | C49: Explotación de minas y canteras | H49: 4.1374937 | I49: -1.0495008 | J49: 3.6327764 | K49: 2.5240362 | L49: -2.0812333 | M49: 1.199032 | N49: 0.58860499 | O49: 5.3962032 | P49: 11.023014 | Q49: 10.336137 | R49: 11.080558 | S49: 5.5211554 | T49: 7.9232326 | U49: 10.898858 | V49: 9.9234079 | W49: 16.647376 | X49: 14.756583 | Y49: 15.515508 | Z49: 9.0712623 | AA49: 5.10497 | AB49: 10.026771 | AC49: 12.359237 | AD49: 18.107231 | AE49: 17.051398 | AF49: 11.396295 | AG49: 5.7036252 | AH49: 2.0661622 | AI49: 2.9756802 | AJ49: 2.9833365 | AK49: 4.7901494 | AL49: 6.6089359 | AM49: 6.754691 | AN49: 4.1216319 | AO49: -3.7402478 | AP49: -2.3638789 | AQ49: -3.1016439 | AR49: -2.6786693 | AS49: 2.8583168 | AT49: -2.5263357 | AU49: -1.7353217 | AV49: -1.1503003 | AW49: -5.0147535 | AX49: -1.1030635 | AY49: -4.1670126 | AZ49: -8.1923138 | BA49: -4.6420994 | BB49: -6.4833042 | BC49: -3.6830737 | BD49: -4.6634958 | BE49: -3.1865238 | BF49: 0.077433358 | BG49: 1.0093585 | BH49: 4.7474036 | BI49: 0.49452468 | BJ49: 0.30783126 | BK49: 2.2328874 | BL49: -3.1892062 | BM49: -20.886307 | BN49: -18.189558 | BO49: -18.291628 | BP49: -14.041367 | BQ49: 5.2175005 | BR49: 2.4005088 | BS49: 7.7029638 | BT49: 2.1374201 | BU49: 3.2754125 | BV49: 7.0799258 | BW49: -5.6532541 | BX49: 3.2732596 | BY49: 3.3742635 | BZ49: 2.1156669 | CA49: 1.5943346 | CB49: -0.75180085 | CC49: -1.8968161 | CD49: -5.6038883 | CE49: -5.2041781 | CF49: -5.7218505 | CG49: -10.25722 | CH49: -5.9172214 | CI49: -2.9015589
B50: C | C50: Industrias manufactureras | H50: 6.2936781 | I50: 3.4561099 | J50: 9.4661283 | K50: 9.6329809 | L50: 10.105894 | M50: 8.4895195 | N50: 5.4701375 | O50: 7.4079891 | P50: 4.2279149 | Q50: 3.2145844 | R50: -0.10913065 | S50: -5.0760675 | T50: -4.2957179 | U50: -6.5075434 | V50: -3.4601933 | W50: -0.50204878 | X50: 0.32007523 | Y50: 3.549703 | Z50: 0.96438877 | AA50: 2.6693058 | AB50: 6.1934431 | AC50: 4.745306 | AD50: 7.6515293 | AE50: 3.8386567 | AF50: 3.1045826 | AG50: 1.1710007 | AH50: -0.03522096 | AI50: -0.67839956 | AJ50: -4.2935532 | AK50: 3.7238177 | AL50: 2.2101462 | AM50: 4.1436986 | AN50: 6.8685047 | AO50: 0.86163723 | AP50: 2.4156264 | AQ50: 1.8499359 | AR50: 0.69560251 | AS50: 0.98680543 | AT50: 2.2613669 | AU50: 3.8840814 | AV50: 4.3339018 | AW50: 6.0232363 | AX50: 1.4083519 | AY50: 1.4748458 | AZ50: 0.63806316 | BA50: -4.556529 | BB50: -1.0933261 | BC50: -2.1268152 | BD50: -2.2824114 | BE50: 3.8106462 | BF50: 1.9601262 | BG50: 2.3107546 | BH50: 2.2780126 | BI50: -0.13989596 | BJ50: 1.3716648 | BK50: 1.3446206 | BL50: -1.2113841 | BM50: -27.415376 | BN50: -7.7092496 | BO50: -1.0775201 | BP50: 4.8583415 | BQ50: 31.046195 | BR50: 14.92108 | BS50: 8.2742365 | BT50: 8.1152849 | BU50: 17.8757 | BV50: 5.5980488 | BW50: 2.6828079 | BX50: 3.0085414 | BY50: -1.461815 | BZ50: -4.0985517 | CA50: -3.4985656 | CB50: -5.5264666 | CC50: -2.0387297 | CD50: -2.254597 | CE50: -0.50563703 | CF50: 1.4253568 | CG50: 0.78114362 | CH50: 4.1348084 | CI50: 1.0207392
B51: D + E | C51: Suministro de electricidad, gas, vapor y aire acondicionado; Distribución de agua; evacuación y tratamiento de aguas residuales, gestión de desechos y actividades de saneamiento ambiental | H51: 5.185267 | I51: 4.5708935 | J51: 4.8889951 | K51: 6.6147634 | L51: 6.4491727 | M51: 4.0061157 | N51: 3.4369189 | O51: 3.1036132 | P51: -1.6001848 | Q51: 0.85253291 | R51: 1.4644805 | S51: 1.3760824 | T51: 0.47239073 | U51: 0.8792002 | V51: 3.0512985 | W51: 5.0510947 | X51: 8.2941089 | Y51: 5.7757799 | Z51: 2.9601644 | AA51: -0.96681583 | AB51: 2.4431337 | AC51: 2.4933697 | AD51: 3.341438 | AE51: 3.9870801 | AF51: 2.1841586 | AG51: 2.2658802 | AH51: 2.4563905 | AI51: 1.6960169 | AJ51: 1.9706243 | AK51: 4.7071646 | AL51: 3.776923 | AM51: 4.3660965 | AN51: 4.4935317 | AO51: 3.6832399 | AP51: 3.7403555 | AQ51: 1.8689518 | AR51: -0.65615047 | AS51: -2.1521869 | AT51: -0.36261622 | AU51: 0.36119766 | AV51: 1.1087325 | AW51: -0.88008976 | AX51: -0.82448732 | AY51: 0.57681318 | AZ51: 0.50877746 | BA51: 3.1393835 | BB51: 3.9823514 | BC51: 3.891212 | BD51: 2.0455755 | BE51: 2.738199 | BF51: 2.983006 | BG51: 2.4131012 | BH51: 3.1324312 | BI51: 2.6635852 | BJ51: 2.4727452 | BK51: 1.8483618 | BL51: 1.8655506 | BM51: -9.434173 | BN51: -5.6856657 | BO51: -2.004004 | BP51: -1.3722776 | BQ51: 9.4657173 | BR51: 8.6314275 | BS51: 7.0540726 | BT51: 5.8674252 | BU51: 7.5526942 | BV51: 3.127764 | BW51: 2.2167638 | BX51: 2.3798917 | BY51: 2.5113337 | BZ51: 3.7242688 | CA51: 3.9511973 | CB51: 5.5690833 | CC51: 3.011363 | CD51: 1.3161067 | CE51: 0.26136467 | CF51: -1.3280109 | CG51: 0.902112 | CH51: 2.060443 | CI51: 2.8911871
B52: F | C52: Construcción | H52: 5.9065393 | I52: 11.139242 | J52: 17.677406 | K52: 13.835987 | L52: 6.3975191 | M52: 19.370751 | N52: 5.0059316 | O52: 0.32027772 | P52: 1.4644507 | Q52: 17.476303 | R52: 22.6373 | S52: -0.19697997 | T52: -3.3018022 | U52: 8.4648077 | V52: -3.5033849 | W52: 8.6219882 | X52: 5.1513572 | Y52: -9.1188798 | Z52: -3.9261652 | AA52: 6.1555819 | AB52: 2.0899596 | AC52: 8.9887192 | AD52: 11.680316 | AE52: 2.3676114 | AF52: 17.748966 | AG52: 14.861016 | AH52: -7.6222076 | AI52: 1.5592345 | AJ52: 1.7196591 | AK52: 5.6244203 | AL52: 27.364483 | AM52: 11.742093 | AN52: 14.456045 | AO52: 6.4544434 | AP52: 10.222384 | AQ52: 5.4957255 | AR52: 5.8232148 | AS52: 9.751185 | AT52: 1.8135789 | AU52: 7.9734234 | AV52: 8.6691029 | AW52: 2.5712686 | AX52: 4.5447654 | AY52: -0.72231693 | AZ52: -4.3497052 | BA52: -1.1046101 | BB52: -2.1069632 | BC52: -0.67554608 | BD52: -1.0559548 | BE52: -6.5899482 | BF52: 2.1549209 | BG52: 0.44297933 | BH52: 0.20010138 | BI52: -1.7236849 | BJ52: -8.5553016 | BK52: -4.8590816 | BL52: -18.469766 | BM52: -43.515775 | BN52: -30.098626 | BO52: -26.14287 | BP52: -7.0506074 | BQ52: 23.832957 | BR52: -0.25349761 | BS52: 5.8129074 | BT52: 5.0696598 | BU52: 9.4258027 | BV52: 14.299997 | BW52: -0.96640829 | BX52: -1.8178933 | BY52: -1.3046156 | BZ52: -7.4452357 | CA52: -1.6688264 | CB52: -0.55599651 | CC52: 0.1047684 | CD52: 2.0450372 | CE52: -1.1613464 | CF52: -3.0118312 | CG52: -3.5754957 | CH52: -1.8781897 | CI52: -2.6141715
B53: G + H + I | C53: Comercio al por mayor y al por menor; reparación de vehículos automotores y motocicletas; Transporte y almacenamiento; Alojamiento y servicios de comida | H53: 5.8371951 | I53: 6.0733004 | J53: 9.3415923 | K53: 8.8807059 | L53: 9.1121239 | M53: 8.0734984 | N53: 7.0914752 | O53: 8.1064202 | P53: 6.1830129 | Q53: 4.0634389 | R53: 2.2307543 | S53: 0.24531541 | T53: -1.6132897 | U53: -0.67398265 | V53: 0.20468102 | W53: 1.2386376 | X53: 4.5112692 | Y53: 4.7024274 | Z53: 5.3173304 | AA53: 6.6418988 | AB53: 6.5450059 | AC53: 7.8615484 | AD53: 7.6243582 | AE53: 5.6691247 | AF53: 6.2369019 | AG53: 4.130719 | AH53: 2.5945274 | AI53: 2.6357524 | AJ53: 2.6802401 | AK53: 5.0455811 | AL53: 5.1958329 | AM53: 5.9295859 | AN53: 5.4903742 | AO53: 4.2034041 | AP53: 4.6134556 | AQ53: 4.6530836 | AR53: 3.5944178 | AS53: 2.8371018 | AT53: 3.4277391 | AU53: 3.4599361 | AV53: 3.5761409 | AW53: 2.4785536 | AX53: 2.1729297 | AY53: 2.5820566 | AZ53: 1.2234979 | BA53: 2.2844285 | BB53: 3.4590375 | BC53: 0.57997278 | BD53: 3.8195004 | BE53: 2.9715224 | BF53: 1.7642538 | BG53: 2.2672361 | BH53: 2.1821549 | BI53: 3.3744091 | BJ53: 4.9948784 | BK53: 4.2958921 | BL53: 3.0635694 | BM53: -32.510755 | BN53: -20.11465 | BO53: -5.1624079 | BP53: -1.5193909 | BQ53: 39.903427 | BR53: 31.045279 | BS53: 19.983161 | BT53: 15.042673 | BU53: 23.163429 | BV53: 11.38565 | BW53: 1.5418425 | BX53: -0.89563649 | BY53: -4.3763984 | BZ53: -5.9421385 | CA53: -3.1718491 | CB53: -0.97341137 | CC53: -0.058785282 | CD53: 1.0502718 | CE53: 4.4932671 | CF53: 3.68685 | CG53: 5.8063964 | CH53: 5.6512625 | CI53: 3.4045555
B54: J | C54: Información y comunicaciones | H54: 18.619618 | I54: 20.241634 | J54: 18.095898 | K54: 5.5627012 | L54: 12.415222 | M54: 7.9709747 | N54: 25.236315 | O54: 13.22432 | P54: 7.4410065 | Q54: 5.1143142 | R54: 0.38382547 | S54: -3.1000735 | T54: -5.7017895 | U54: -8.6535203 | V54: -15.191173 | W54: -4.2732557 | X54: 5.7371898 | Y54: 16.759655 | Z54: 24.164519 | AA54: 19.311429 | AB54: 16.042928 | AC54: 8.2128217 | AD54: 10.114464 | AE54: 8.0537465 | AF54: 2.9883274 | AG54: 0.99506497 | AH54: -1.6022644 | AI54: 2.7900668 | AJ54: 6.472062 | AK54: 9.0782579 | AL54: 11.91967 | AM54: 7.9231643 | AN54: 9.2045383 | AO54: 9.2249023 | AP54: 2.5596633 | AQ54: 5.317126 | AR54: 0.38811082 | AS54: -0.7930997 | AT54: 4.1564317 | AU54: 1.4358517 | AV54: 0.33668166 | AW54: 0.84185641 | AX54: -0.84463958 | AY54: -2.655366 | AZ54: -1.376399 | BA54: 0.054407466 | BB54: -2.8989311 | BC54: 3.1448082 | BD54: 0.75907569 | BE54: 2.7004765 | BF54: 6.8891963 | BG54: 3.6641614 | BH54: 3.3232456 | BI54: 2.7616968 | BJ54: -1.2677164 | BK54: -0.71484849 | BL54: 0.5819601 | BM54: -5.912232 | BN54: -2.1331407 | BO54: -3.3899169 | BP54: 3.3629924 | BQ54: 11.777939 | BR54: 14.239155 | BS54: 20.676701 | BT54: 20.840362 | BU54: 16.65707 | BV54: 12.679691 | BW54: 1.9451795 | BX54: 2.452899 | BY54: 0.91972589 | BZ54: -1.1405253 | CA54: 3.8236182 | CB54: -2.3007293 | CC54: -1.1159964 | CD54: 1.5867547 | CE54: 0.87028245 | CF54: 0.44453722 | CG54: 2.9116421 | CH54: 1.9101085 | CI54: -1.1615771
B55: K | C55: Actividades financieras y de seguros | H55: 10.297423 | I55: 4.0452103 | J55: 3.1460765 | K55: 8.9095881 | L55: 8.527183 | M55: 16.338541 | N55: 13.265734 | O55: 17.015153 | P55: 11.811387 | Q55: 6.0444571 | R55: 10.562455 | S55: 12.004841 | T55: 7.1031107 | U55: 5.7302031 | V55: 4.1240741 | W55: -2.4122504 | X55: -3.0372893 | Y55: 5.6264621 | Z55: 6.8668204 | AA55: 9.4200897 | AB55: 13.363779 | AC55: 10.930293 | AD55: 9.2876489 | AE55: 10.373924 | AF55: 8.6657461 | AG55: 9.3416481 | AH55: 6.8832503 | AI55: 5.5460408 | AJ55: 9.892183 | AK55: 8.701209 | AL55: 7.4459995 | AM55: 11.920378 | AN55: 9.2053253 | AO55: 10.360218 | AP55: 13.522823 | AQ55: 7.9893137 | AR55: 11.029794 | AS55: 8.7633936 | AT55: 8.4419408 | AU55: 3.8366602 | AV55: 2.2769985 | AW55: 1.4443836 | AX55: 2.3631267 | AY55: 5.7886497 | AZ55: 2.3814009 | BA55: 7.365421 | BB55: 4.5061382 | BC55: 7.2772087 | BD55: 3.6401709 | BE55: 4.23087 | BF55: 4.5074955 | BG55: 2.6138708 | BH55: 6.7349646 | BI55: 5.0069508 | BJ55: 8.5146901 | BK55: 4.8835472 | BL55: 2.3671005 | BM55: 1.2198241 | BN55: 2.1148808 | BO55: 3.2187134 | BP55: 5.0302886 | BQ55: 3.3179862 | BR55: 2.2446393 | BS55: 4.2471313 | BT55: -3.1372439 | BU55: 11.387929 | BV55: 9.5112522 | BW55: 8.8039271 | BX55: 23.861235 | BY55: 4.7637154 | BZ55: 2.5356505 | CA55: 6.5845579 | CB55: -2.1994073 | CC55: 2.1826011 | CD55: 5.0471378 | CE55: -0.49098991 | CF55: 3.2794044 | CG55: 2.8022609 | CH55: 4.3523119 | CI55: 0.65252779
B56: L | C56: Actividades inmobiliarias | H56: 3.4946505 | I56: 3.8470312 | J56: 4.3708139 | K56: 4.4537817 | L56: 4.2477526 | M56: 3.9267863 | N56: 3.5726274 | O56: 3.2730177 | P56: 2.5860565 | Q56: 2.6846236 | R56: 2.8391993 | S56: 2.9932599 | T56: 3.6545857 | U56: 3.7935057 | V56: 3.8369354 | W56: 4.0324831 | X56: 3.872587 | Y56: 3.6557624 | Z56: 3.6006698 | AA56: 3.1649645 | AB56: 2.8861808 | AC56: 2.7695881 | AD56: 2.7104034 | AE56: 2.9525606 | AF56: 3.0299187 | AG56: 3.1067399 | AH56: 3.2903061 | AI56: 3.2326074 | AJ56: 3.1916155 | AK56: 3.3080492 | AL56: 3.1528224 | AM56: 3.2200902 | AN56: 3.2358826 | AO56: 3.0381907 | AP56: 3.0933461 | AQ56: 3.0630604 | AR56: 2.9765504 | AS56: 3.0732203 | AT56: 3.1215218 | AU56: 3.5939806 | AV56: 3.4113426 | AW56: 3.7893456 | AX56: 3.6242461 | AY56: 3.2946633 | AZ56: 3.2517123 | BA56: 2.8167623 | BB56: 2.9397772 | BC56: 3.1984628 | BD56: 3.3091181 | BE56: 3.9243219 | BF56: 4.4491935 | BG56: 4.1639417 | BH56: 4.3743504 | BI56: 3.7465847 | BJ56: 2.8257117 | BK56: 2.0965019 | BL56: 1.9758705 | BM56: 0.66354067 | BN56: 1.3589642 | BO56: 1.7750534 | BP56: 1.9144201 | BQ56: 3.226482 | BR56: 2.5525898 | BS56: 2.2986777 | BT56: 2.2835024 | BU56: 2.0708711 | BV56: 2.0702726 | BW56: 1.7596171 | BX56: 1.8035733 | BY56: 1.7978831 | BZ56: 1.753946 | CA56: 2.0447568 | CB56: 2.083867 | CC56: 2.2729473 | CD56: 2.2171779 | CE56: 2.2612157 | CF56: 1.991974 | CG56: 1.9845003 | CH56: 2.0595561 | CI56: 1.8984765
B57: M + N | C57: Actividades profesionales, científicas y técnicas; Actividades de servicios administrativos y de apoyo | H57: 7.1089389 | I57: 6.7510811 | J57: 7.4295577 | K57: 6.85565 | L57: 7.0200382 | M57: 6.6204857 | N57: 7.4008098 | O57: 6.5173503 | P57: 4.8990959 | Q57: 3.9978019 | R57: 2.9844129 | S57: 3.3205801 | T57: 2.6902998 | U57: 3.8545983 | V57: 2.9074265 | W57: 1.888969 | X57: 2.2898056 | Y57: 2.6063022 | Z57: 2.911296 | AA57: 4.3266754 | AB57: 5.7619351 | AC57: 6.2633822 | AD57: 7.8833626 | AE57: 8.2033687 | AF57: 6.1491191 | AG57: 5.3719578 | AH57: 3.9931291 | AI57: 3.9761481 | AJ57: 2.8928996 | AK57: 4.5419591 | AL57: 5.9002757 | AM57: 7.3492259 | AN57: 8.7237951 | AO57: 8.1186574 | AP57: 7.1773536 | AQ57: 5.548524 | AR57: 2.0377799 | AS57: 0.1980975 | AT57: 1.0203193 | AU57: -3.4137618 | AV57: -3.09334 | AW57: -2.2930296 | AX57: -3.5654285 | AY57: -0.9461133 | AZ57: 0.27015069 | BA57: 1.7463414 | BB57: 2.0896822 | BC57: 1.6442595 | BD57: 3.3595174 | BE57: 4.2989904 | BF57: 4.1142419 | BG57: 4.069735 | BH57: 3.9295292 | BI57: 4.0816786 | BJ57: 3.6425326 | BK57: 2.31141 | BL57: 1.2029103 | BM57: -12.462122 | BN57: -8.1898409 | BO57: -3.5818852 | BP57: 1.0807252 | BQ57: 14.271119 | BR57: 12.973096 | BS57: 10.951833 | BT57: 8.6057534 | BU57: 12.994517 | BV57: 7.211521 | BW57: 3.5414088 | BX57: 3.4422298 | BY57: 1.436739 | BZ57: 1.0583853 | CA57: 1.8354786 | CB57: -0.41466838 | CC57: -0.37821755 | CD57: -0.49412806 | CE57: -0.39194968 | CF57: 1.1671912 | CG57: 1.5592351 | CH57: 1.1669242 | CI57: 1.4528823
B58: O + P + Q | C58: Administración pública y defensa; planes de seguridad social de afiliación obligatoria; Educación; Actividades de atención de la salud humana y de servicios sociales | H58: 3.6884002 | I58: 3.2601333 | J58: 5.039722 | K58: 6.275627 | L58: 3.4305124 | M58: 3.7336497 | N58: 4.651696 | O58: 4.4693353 | P58: 3.8501329 | Q58: 4.0925855 | R58: 0.81546083 | S58: 0.14328686 | T58: 1.4916598 | U58: 2.5869908 | V58: 3.9060844 | W58: 4.0895339 | X58: 5.0258205 | Y58: 4.4809305 | Z58: 3.5089017 | AA58: 5.4390628 | AB58: 5.742181 | AC58: 5.1073736 | AD58: 5.6766869 | AE58: 6.3575833 | AF58: 5.0516249 | AG58: 5.4914808 | AH58: 6.0084434 | AI58: 5.6639913 | AJ58: 3.9258644 | AK58: 6.2443225 | AL58: 5.9450228 | AM58: 5.8572089 | AN58: 6.6419332 | AO58: 4.393184 | AP58: 5.9004671 | AQ58: 6.3736789 | AR58: 5.9336127 | AS58: 7.6035799 | AT58: 9.980935 | AU58: -1.1910574 | AV58: 1.8565462 | AW58: 4.6028712 | AX58: 0.78668939 | AY58: 7.3051436 | AZ58: 3.2077997 | BA58: 3.5725309 | BB58: 3.1663326 | BC58: 3.8576966 | BD58: 3.9933331 | BE58: 5.334418 | BF58: 4.8537825 | BG58: 4.732708 | BH58: 4.7735894 | BI58: 5.5759431 | BJ58: 5.3783576 | BK58: 4.6829292 | BL58: 1.1326758 | BM58: -2.4691086 | BN58: -1.8137468 | BO58: 4.0742194 | BP58: 6.8389476 | BQ58: 10.265298 | BR58: 10.538599 | BS58: 6.4762015 | BT58: 3.4447726 | BU58: 5.62129 | BV58: -1.0936768 | BW58: -2.7822126 | BX58: 0.43990745 | BY58: 4.896076 | BZ58: 7.3223958 | CA58: 6.7671845 | CB58: 5.7805567 | CC58: 4.3454569 | CD58: 1.4918727 | CE58: 4.7317651 | CF58: 3.6154904 | CG58: 1.6548369 | CH58: 7.9239354 | CI58: 4.8169371
B59: R + S + T | C59: Actividades artísticas, de entretenimiento y recreación y otras actividades de servicios; Actividades de los hogares individuales en calidad de empleadores; actividades no diferenciadas de los hogares individuales como productores de bienes y servicios para uso propio | H59: 5.3950416 | I59: 6.5709513 | J59: 5.1507793 | K59: 3.343778 | L59: 5.3579122 | M59: 4.4143121 | N59: 4.0742915 | O59: 7.2492729 | P59: 3.8617163 | Q59: 3.0576034 | R59: 3.5983055 | S59: 1.5794435 | T59: 1.383143 | U59: 2.4397429 | V59: 1.9457582 | W59: 3.4655611 | X59: 3.678271 | Y59: 1.7274688 | Z59: 2.6809006 | AA59: 1.707535 | AB59: 3.7840696 | AC59: 6.7872691 | AD59: 8.2791454 | AE59: 5.4859052 | AF59: 3.5398669 | AG59: 1.5091134 | AH59: 4.7590411 | AI59: 2.2525514 | AJ59: 5.0357789 | AK59: 6.1924565 | AL59: 4.2180217 | AM59: 9.4242527 | AN59: 6.0245814 | AO59: 1.1098101 | AP59: 2.6295578 | AQ59: 1.5425688 | AR59: 2.181733 | AS59: 4.7370874 | AT59: 4.2447382 | AU59: 5.6866588 | AV59: 5.99627 | AW59: 6.8704085 | AX59: 5.3418509 | AY59: 4.1563324 | AZ59: 2.9706214 | BA59: 1.8596972 | BB59: 1.6403386 | BC59: 1.9948935 | BD59: -2.4420251 | BE59: 2.2776525 | BF59: 2.2732047 | BG59: 6.6571251 | BH59: 12.362025 | BI59: 15.190067 | BJ59: 13.254625 | BK59: 11.535668 | BL59: 3.7705103 | BM59: -33.943471 | BN59: -11.100379 | BO59: -5.7100068 | BP59: 9.458152 | BQ59: 76.830873 | BR59: 33.814397 | BS59: 31.536862 | BT59: 30.373449 | BU59: 23.812859 | BV59: 25.54394 | BW59: 32.279036 | BX59: 15.13745 | BY59: 13.335173 | BZ59: 10.556739 | CA59: 4.2703232 | CB59: 6.1710309 | CC59: 10.882486 | CD59: 11.445114 | CE59: 4.6513318 | CF59: 15.581151 | CG59: 7.7175391 | CH59: 5.1847439 | CI59: 11.540316
A60: B.1b | C60: Valor agregado bruto | H60: 5.56244 | I60: 4.5999511 | J60: 7.40253 | K60: 7.0778811 | L60: 6.337461 | M60: 6.6673964 | N60: 6.0491406 | O60: 6.2073082 | P60: 4.7617094 | Q60: 4.5599538 | R60: 3.3049028 | S60: 0.1390158 | T60: 0.17553246 | U60: 0.95341135 | V60: 1.0458323 | W60: 3.3316511 | X60: 4.0015153 | Y60: 4.5037417 | Z60: 3.6823803 | AA60: 5.0880738 | AB60: 6.5291047 | AC60: 6.4312732 | AD60: 7.5723918 | AE60: 5.9695335 | AF60: 5.992753 | AG60: 4.866207 | AH60: 2.1976062 | AI60: 2.6315113 | AJ60: 2.4224931 | AK60: 5.541546 | AL60: 6.5507442 | AM60: 6.5543448 | AN60: 6.6547927 | AO60: 3.224473 | AP60: 4.2320586 | AQ60: 3.6940997 | AR60: 2.8354347 | AS60: 3.6799765 | AT60: 3.7075566 | AU60: 2.1470568 | AV60: 2.4686567 | AW60: 2.3386287 | AX60: 1.3742068 | AY60: 2.5820008 | AZ60: 1.1868087 | BA60: 1.3235385 | BB60: 1.7210255 | BC60: 1.3015103 | BD60: 1.58562 | BE60: 2.636672 | BF60: 2.8576252 | BG60: 2.9100357 | BH60: 3.5038833 | BI60: 3.0233861 | BJ60: 2.9393139 | BK60: 2.8455037 | BL60: 0.12912182 | BM60: -16.664872 | BN60: -9.1858122 | BO60: -3.4645159 | BP60: 1.3973481 | BQ60: 17.804002 | BR60: 12.779757 | BS60: 10.344563 | BT60: 7.2186328 | BU60: 11.54157 | BV60: 6.2838458 | BW60: 1.4854118 | BX60: 2.6797542 | BY60: 0.67972409 | BZ60: 0.25186039 | CA60: 1.3451668 | CB60: 0.5872451 | CC60: 1.8309203 | CD60: 1.6252117 | CE60: 2.2865981 | CF60: 2.6321967 | CG60: 2.0743304 | CH60: 3.6874762 | CI60: 2.2546402
A61: D.21-D.31 | C61: Impuestos menos subvenciones sobre los productos | H61: 15.194095 | I61: 12.666489 | J61: 10.13219 | K61: 10.534994 | L61: 10.470311 | M61: 8.7485002 | N61: 14.764532 | O61: 9.7574211 | P61: 9.1532671 | Q61: 6.9121614 | R61: 3.4919037 | S61: 1.5945681 | T61: -0.26213163 | U61: -1.9070128 | V61: -4.4810076 | W61: 0.18428963 | X61: 2.673592 | Y61: 5.9293987 | Z61: 7.9555071 | AA61: 8.0328507 | AB61: 9.6542758 | AC61: 10.406412 | AD61: 11.425512 | AE61: 9.8789093 | AF61: 7.5748321 | AG61: 4.6485384 | AH61: 2.7398394 | AI61: 3.3291986 | AJ61: 1.9280067 | AK61: 3.6214422 | AL61: 3.2156428 | AM61: 4.3612172 | AN61: 6.0107081 | AO61: 5.5636113 | AP61: 6.0236271 | AQ61: 4.5677081 | AR61: 2.8181716 | AS61: 0.79553419 | AT61: 2.2350066 | AU61: 1.1324703 | AV61: 1.4505671 | AW61: -0.0058741202 | AX61: 3.4284643 | AY61: -0.35809982 | AZ61: -0.14096541 | BA61: 0.67313613 | BB61: 1.3536803 | BC61: 2.3230592 | BD61: 2.3253164 | BE61: 3.9273359 | BF61: 3.1314677 | BG61: 2.8418102 | BH61: 3.1945521 | BI61: 3.5869947 | BJ61: 4.986272 | BK61: 5.4652654 | BL61: 2.502217 | BM61: -17.143344 | BN61: -8.0702999 | BO61: -1.9149341 | BP61: 2.4699992 | BQ61: 24.658736 | BR61: 18.87062 | BS61: 18.606628 | BT61: 17.089036 | BU61: 20.681112 | BV61: 18.028318 | BW61: 9.8691732 | BX61: 3.9394115 | BY61: -2.1362986 | BZ61: -6.4853618 | CA61: -4.387061 | CB61: -2.1660272 | CC61: -0.60364892 | CD61: 1.4165113 | CE61: 2.9975343 | CF61: 2.182459 | CG61: 2.4769695 | CH61: 2.7369581 | CI61: 2.4765272
A62: B.1b | C62: Producto Interno Bruto | H62: 6.3755741 | I62: 5.323039 | J62: 7.654265 | K62: 7.4020784 | L62: 6.7128664 | M62: 6.8613055 | N62: 6.8544721 | O62: 6.5425803 | P62: 5.1743787 | Q62: 4.7853126 | R62: 3.3195886 | S62: 0.27975742 | T62: 0.14508701 | U62: 0.69535103 | V62: 0.53236473 | W62: 3.039196 | X62: 3.8803502 | Y62: 4.6245494 | Z62: 4.0474546 | AA62: 5.3385254 | AB62: 6.7991977 | AC62: 6.7825905 | AD62: 7.9182778 | AE62: 6.3253583 | AF62: 6.1351561 | AG62: 4.846037 | AH62: 2.247241 | AI62: 2.6962516 | AJ62: 2.3818401 | AK62: 5.3733024 | AL62: 6.2485426 | AM62: 6.3506629 | AN62: 6.6000143 | AO62: 3.4253216 | AP62: 4.3859522 | AQ62: 3.7632113 | AR62: 2.8280769 | AS62: 3.4223328 | AT62: 3.5756298 | AU62: 2.05995 | AV62: 2.3747844 | AW62: 2.1220985 | AX62: 1.5566087 | AY62: 2.3047006 | AZ62: 1.0694632 | BA62: 1.2698276 | BB62: 1.6900414 | BC62: 1.3887831 | BD62: 1.6492417 | BE62: 2.7484906 | BF62: 2.8808028 | BG62: 2.9137462 | BH62: 3.4755274 | BI62: 3.075098 | BJ62: 3.1269436 | BK62: 3.0910783 | BL62: 0.34608976 | BM62: -16.711007 | BN62: -9.080262 | BO62: -3.3098452 | BP62: 1.4997004 | BQ62: 18.422284 | BR62: 13.323882 | BS62: 11.081378 | BT62: 8.1051367 | BU62: 12.386057 | BV62: 7.4010353 | BW62: 2.3307905 | BX62: 2.8075119 | BY62: 0.40576595 | BZ62: -0.44678468 | CA62: 0.73162986 | CB62: 0.31878093 | CC62: 1.5997579 | CD62: 1.605721 | CE62: 2.3560545 | CF62: 2.593029 | CG62: 2.1174491 | CH62: 3.5978602 | CI62: 2.2680951
A64: Fuente: DANE, PIB_T
A65: prpreliminar
A66: pprovisional
A67: Actualizado el 16 de febrero de 2026
A72: Producto Interno Bruto (PIB)
A74: Tasa de crecimiento año corrido (%)
A75: Base 2015
A76: 2006 - 2025pr cuarto trimestre
A78: Clasificación Cuentas Nacionales | B78: Secciones CIIU Rev. 4 A.C. 12 agrupaciones | C78: Concepto | H78: 2006 | L78: 2007 | P78: 2008 | T78: 2009 | X78: 2010 | AB78: 2011 | AF78: 2012 | AJ78: 2013 | AN78: 2014 | AR78: 2015 | AV78: 2016 | AZ78: 2017 | BD78: 2018 | BH78: 2019 | BL78: 2020 | BP78: 2021 | BT78: 2022 | BX78: 2023 | BY78: 2023pr | CB78: 2024p | CC78: 2023pr | CF78: 2025pr | CG78: 2023pr
H79: I | I79: II | J79: III | K79: IV | L79: I | M79: II | N79: III | O79: IV | P79: I | Q79: II | R79: III | S79: IV | T79: I | U79: II | V79: III | W79: IV | X79: I | Y79: II | Z79: III | AA79: IV | AB79: I | AC79: II | AD79: III | AE79: IV | AF79: I | AG79: II | AH79: III | AI79: IV | AJ79: I | AK79: II | AL79: III | AM79: IV | AN79: I | AO79: II | AP79: III | AQ79: IV | AR79: I | AS79: II | AT79: III | AU79: IV | AV79: I | AW79: II | AX79: III | AY79: IV | AZ79: I | BA79: II | BB79: III | BC79: IV | BD79: I | BE79: II | BF79: III | BG79: IV | BH79: I | BI79: II | BJ79: III | BK79: IV | BL79: I | BM79: II | BN79: III | BO79: IV | BP79: I | BQ79: II | BR79: III | BS79: IV | BT79: I | BU79: II | BV79: III | BW79: IV | BX79: I | BY79: II | BZ79: III | CA79: IV | CB79: I | CC79: II | CD79: III | CE79: IV | CF79: I | CG79: II | CH79: III | CI79: IV
B81: A | C81: Agricultura, ganadería, caza, silvicultura y pesca | H81: 1.5111974 | I81: 0.6308427 | J81: 1.7188265 | K81: 2.13142 | L81: 3.9745853 | M81: 3.8050226 | N81: 4.2060689 | O81: 3.9310897 | P81: 2.3356123 | Q81: 1.2684521 | R81: 0.40478956 | S81: -0.805189 | T81: -3.084537 | U81: -2.9569752 | V81: -1.2115626 | W81: -0.23299511 | X81: -0.34300037 | Y81: 1.0535171 | Z81: -0.30137078 | AA81: 0.30385214 | AB81: 6.8002401 | AC81: 4.2522754 | AD81: 2.909567 | AE81: 1.9102221 | AF81: 1.7039971 | AG81: 3.5086447 | AH81: 3.1220144 | AI81: 2.5033165 | AJ81: 3.4642009 | AK81: 7.3646201 | AL81: 7.340055 | AM81: 7.453565 | AN81: 7.6873635 | AO81: 3.2415882 | AP81: 2.7721655 | AQ81: 2.9106725 | AR81: 3.1542569 | AS81: 2.9491127 | AT81: 4.3316005 | AU81: 4.2999567 | AV81: -0.61981064 | AW81: 0.181077 | AX81: 0.66257347 | AY81: 2.7366802 | AZ81: 11.180531 | BA81: 8.702677 | BB81: 7.7049467 | BC81: 5.5763435 | BD81: 0.91712616 | BE81: 2.4001071 | BF81: 1.8781016 | BG81: 1.5939308 | BH81: 1.4339385 | BI81: 1.2984632 | BJ81: 2.0983901 | BK81: 2.7173298 | BL81: 5.626021 | BM81: 2.2712451 | BN81: 1.7207055 | BO81: 1.9606763 | BP81: 4.0286004 | BQ81: 5.2139435 | BR81: 4.4864219 | BS81: 4.3735033 | BT81: -1.4590949 | BU81: 0.29587425 | BV81: -0.096090339 | BW81: -0.90739718 | BX81: 0.83882936 | BY81: -0.31121276 | BZ81: 0.28715524 | CA81: 1.6486195 | CB81: 2.8828639 | CC81: 5.1325691 | CD81: 6.3566855 | CE81: 6.1278666 | CF81: 6.3464589 | CG81: 5.0182539 | CH81: 4.3189497 | CI81: 3.1002323
B82: B | C82: Explotación de minas y canteras | H82: 4.1374937 | I82: 1.4906296 | J82: 2.211937 | K82: 2.2931097 | L82: -2.0812333 | M82: -0.44924562 | N82: -0.094920851 | O82: 1.3364696 | P82: 11.023014 | Q82: 10.675623 | R82: 10.814815 | S82: 9.379616 | T82: 7.9232326 | U82: 9.4235521 | V82: 9.5957837 | W82: 11.440147 | X82: 14.756583 | Y82: 15.144395 | Z82: 13.045565 | AA82: 10.871635 | AB82: 10.026771 | AC82: 11.222505 | AD82: 13.518167 | AE82: 14.435163 | AF82: 11.396295 | AG82: 8.448133 | AH82: 6.2340842 | AI82: 5.3690817 | AJ82: 2.9833365 | AK82: 3.8953817 | AL82: 4.7998405 | AM82: 5.3070033 | AN82: 4.1216319 | AO82: 0.11892507 | AP82: -0.72290746 | AQ82: -1.3485265 | AR82: -2.6786693 | AS82: 0.03170569 | AT82: -0.82130076 | AU82: -1.0574206 | AV82: -1.1503003 | AW82: -3.0954173 | AX82: -2.4424671 | AY82: -2.8849182 | AZ82: -8.1923138 | BA82: -6.4407574 | BB82: -6.4548926 | BC82: -5.7531403 | BD82: -4.6634958 | BE82: -3.9207986 | BF82: -2.5928792 | BG82: -1.6608552 | BH82: 4.7474036 | BI82: 2.5924945 | BJ82: 1.8128953 | BK82: 1.9245125 | BL82: -3.1892062 | BM82: -11.972853 | BN82: -14.06283 | BO82: -15.190076 | BP82: -14.041367 | BQ82: -5.4504695 | BR82: -2.9378154 | BS82: -0.20509499 | BT82: 2.1374201 | BU82: 2.7023255 | BV82: 4.1804027 | BW82: 1.4548405 | BX82: 3.2732596 | BY82: 3.3236782 | BZ82: 2.9044466 | CA82: 2.566768 | CB82: -0.75180085 | CC82: -1.323644 | CD82: -2.7976858 | CE82: -3.4120735 | CF82: -5.7218505 | CG82: -7.9737462 | CH82: -7.2859612 | CI82: -6.1873734
B83: C | C83: Industrias manufactureras | H83: 6.2936781 | I83: 4.8116069 | J83: 6.4510301 | K83: 7.2917206 | L83: 10.105894 | M83: 9.2725746 | N83: 7.8953398 | O83: 7.7637691 | P83: 4.2279149 | Q83: 3.7092376 | R83: 2.3573189 | S83: 0.35714286 | T83: -4.2957179 | U83: -5.4224499 | V83: -4.7444409 | W83: -3.6646995 | X83: 0.32007523 | Y83: 1.946413 | Z83: 1.6025243 | AA83: 1.8829469 | AB83: 6.1934431 | AC83: 5.4527388 | AD83: 6.2178831 | AE83: 5.5876336 | AF83: 3.1045826 | AG83: 2.122214 | AH83: 1.3613277 | AI83: 0.82996039 | AJ83: -4.2935532 | AK83: -0.25821722 | AL83: 0.60033333 | AM83: 1.5096032 | AN83: 6.8685047 | AO83: 3.724399 | AP83: 3.2618949 | AQ83: 2.8901673 | AR83: 0.69560251 | AS83: 0.84381674 | AT83: 1.340656 | AU83: 2.0034959 | AV83: 4.3339018 | AW83: 5.1949455 | AX83: 3.8557189 | AY83: 3.2238022 | AZ83: 0.63806316 | BA83: -2.0304366 | BB83: -1.7068136 | BC83: -1.816399 | BD83: -2.2824114 | BE83: 0.76693003 | BF83: 1.1815619 | BG83: 1.4752558 | BH83: 2.2780126 | BI83: 1.0313914 | BJ83: 1.1505452 | BK83: 1.2014382 | BL83: -1.2113841 | BM83: -14.564966 | BN83: -12.159047 | BO83: -9.248989 | BP83: 4.8583415 | BQ83: 16.196404 | BR83: 15.726175 | BS83: 13.593057 | BT83: 8.1152849 | BU83: 12.881119 | BV83: 10.214433 | BW83: 8.159453 | BX83: 3.0085414 | BY83: 0.7291663 | BZ83: -0.96445674 | CA83: -1.6208701 | CB83: -5.5264666 | CC83: -3.7867973 | CD83: -3.2662928 | CE83: -2.5648453 | CF83: 1.4253568 | CG83: 1.0981877 | CH83: 2.1405483 | CI83: 1.8500058
B84: D + E | C84: Suministro de electricidad, gas, vapor y aire acondicionado; Distribución de agua; evacuación y tratamiento de aguas residuales, gestión de desechos y actividades de saneamiento ambiental | H84: 5.185267 | I84: 4.8752581 | J84: 4.8799107 | K84: 5.3197752 | L84: 6.4491727 | M84: 5.2199998 | N84: 4.6160421 | O84: 4.2278571 | P84: -1.6001848 | Q84: -0.38038787 | R84: 0.23745516 | S84: 0.52654673 | T84: 0.47239073 | U84: 0.67721102 | V84: 1.4820212 | W84: 2.3958485 | X84: 8.2941089 | Y84: 7.0236377 | Z84: 5.6248283 | AA84: 3.8933359 | AB84: 2.4431337 | AC84: 2.4681817 | AD84: 2.7612076 | AE84: 3.0681559 | AF84: 2.1841586 | AG84: 2.2249156 | AH84: 2.3030269 | AI84: 2.1496815 | AJ84: 1.9706243 | AK84: 3.3359665 | AL84: 3.4849904 | AM84: 3.7065905 | AN84: 4.4935317 | AO84: 4.0838883 | AP84: 3.9674618 | AQ84: 3.4363257 | AR84: -0.65615047 | AS84: -1.4095611 | AT84: -1.0555167 | AU84: -0.70237759 | AV84: 1.1087325 | AW84: 0.11469703 | AX84: -0.20513024 | AY84: -0.0081304118 | AZ84: 0.50877746 | BA84: 1.8105191 | BB84: 2.5455188 | BC84: 2.8865309 | BD84: 2.0455755 | BE84: 2.3927902 | BF84: 2.595332 | BG84: 2.5487019 | BH84: 3.1324312 | BI84: 2.8966041 | BJ84: 2.7506007 | BK84: 2.520037 | BL84: 1.8655506 | BM84: -3.8052795 | BN84: -4.4512502 | BO84: -3.8299632 | BP84: -1.3722776 | BQ84: 3.7485585 | BR84: 5.404304 | BS84: 5.8310861 | BT84: 5.8674252 | BU84: 6.707576 | BV84: 5.4565225 | BW84: 4.6087374 | BX84: 2.3798917 | BY84: 2.4459379 | BZ84: 2.8828169 | CA84: 3.1559996 | CB84: 5.5690833 | CC84: 4.2830737 | CD84: 3.260798 | CE84: 2.4879368 | CF84: -1.3280109 | CG84: -0.22038966 | CH84: 0.55067674 | CI84: 1.1406519
B85: F | C85: Construcción | H85: 5.9065393 | I85: 8.2630118 | J85: 11.432388 | K85: 12.141036 | L85: 6.3975191 | M85: 12.39504 | N85: 9.7680702 | O85: 6.9404972 | P85: 1.4644507 | Q85: 9.3261417 | R85: 13.853207 | S85: 9.9085238 | T85: -3.3018022 | U85: 2.9062018 | V85: 0.55814698 | W85: 2.6139632 | X85: 5.1513572 | Y85: -2.784231 | Z85: -3.1856649 | AA85: -0.66474849 | AB85: 2.0899596 | AC85: 5.6763363 | AD85: 7.7708233 | AE85: 6.2125449 | AF85: 17.748966 | AG85: 16.200583 | AH85: 7.5885328 | AI85: 5.9126387 | AJ85: 1.7196591 | AK85: 3.7890737 | AL85: 11.106776 | AM85: 11.276109 | AN85: 14.456045 | AO85: 10.14043 | AP85: 10.16959 | AQ85: 8.9186332 | AR85: 5.8232148 | AS85: 7.8708423 | AT85: 5.714549 | AU85: 6.3001355 | AV85: 8.6691029 | AW85: 5.4349278 | AX85: 5.1297369 | AY85: 3.5887805 | AZ85: -4.3497052 | BA85: -2.6753154 | BB85: -2.4815409 | BC85: -2.0257796 | BD85: -1.0559548 | BE85: -3.957443 | BF85: -1.8654839 | BG85: -1.2748909 | BH85: 0.20010138 | BI85: -0.78089837 | BJ85: -3.5506993 | BK85: -3.891258 | BL85: -18.469766 | BM85: -31.120164 | BN85: -30.775104 | BO85: -29.581522 | BP85: -7.0506074 | BQ85: 5.741089 | BR85: 3.6964173 | BS85: 4.2684011 | BT85: 5.0696598 | BU85: 7.1826394 | BV85: 9.5178018 | BW85: 6.642462 | BX85: -1.8178933 | BY85: -1.5637136 | BZ85: -3.5776674 | CA85: -3.0915115 | CB85: -0.55599651 | CC85: -0.22791854 | CD85: 0.5191697 | CE85: 0.084881637 | CF85: -3.0118312 | CG85: -3.2926308 | CH85: -2.8206669 | CI85: -2.7679677
B86: G + H + I | C86: Comercio al por mayor y al por menor; reparación de vehículos automotores y motocicletas; Transporte y almacenamiento; Alojamiento y servicios de comida | H86: 5.8371951 | I86: 5.9590458 | J86: 7.1241128 | K86: 7.607665 | L86: 9.1121239 | M86: 8.5755256 | N86: 8.0537858 | O86: 8.0684464 | P86: 6.1830129 | Q86: 5.0930137 | R86: 4.0957059 | S86: 3.0228602 | T86: -1.6132897 | U86: -1.1349797 | V86: -0.67655944 | W86: -0.15730952 | X86: 4.5112692 | Y86: 4.6090639 | Z86: 4.8535769 | AA86: 5.3452072 | AB86: 6.5450059 | AC86: 7.2191374 | AD86: 7.3596494 | AE86: 6.8891841 | AF86: 6.2369019 | AG86: 5.1519758 | AH86: 4.2629831 | AI86: 3.8153012 | AJ86: 2.6802401 | AK86: 3.8868288 | AL86: 4.3345693 | AM86: 4.7684026 | AN86: 5.4903742 | AO86: 4.8265528 | AP86: 4.7530619 | AQ86: 4.7255671 | AR86: 3.5944178 | AS86: 3.206115 | AT86: 3.2824447 | AU86: 3.3312224 | AV86: 3.5761409 | AW86: 3.0153811 | AX86: 2.7248238 | AY86: 2.68554 | AZ86: 1.2234979 | BA86: 1.7627051 | BB86: 2.3446186 | BC86: 1.8595487 | BD86: 3.8195004 | BE86: 3.3863147 | BF86: 2.8238205 | BG86: 2.6727473 | BH86: 2.1821549 | BI86: 2.7887691 | BJ86: 3.5459147 | BK86: 3.7486764 | BL86: 3.0635694 | BM86: -15.139629 | BN86: -16.870969 | BO86: -13.68878 | BP86: -1.5193909 | BQ86: 15.337611 | BR86: 20.590687 | BS86: 20.40926 | BT86: 15.042673 | BU86: 19.05129 | BV86: 16.265438 | BW86: 11.884067 | BX86: -0.89563649 | BY86: -2.6731793 | BZ86: -3.8113245 | CA86: -3.6386227 | CB86: -0.97341137 | CC86: -0.51450731 | CD86: 0.018229085 | CE86: 1.2326474 | CF86: 3.68685 | CG86: 4.7551817 | CH86: 5.0634045 | CI86: 4.5987329
B87: J | C87: Información y comunicaciones | H87: 18.619618 | I87: 19.460912 | J87: 19.006499 | K87: 14.917518 | L87: 12.415222 | M87: 10.095051 | N87: 15.097011 | O87: 14.573792 | P87: 7.4410065 | Q87: 6.2497643 | R87: 4.1412243 | S87: 2.141877 | T87: -5.7017895 | U87: -7.1968946 | V87: -9.9667982 | W87: -8.4754673 | X87: 5.7371898 | Y87: 11.232637 | Z87: 15.453346 | AA87: 16.510307 | AB87: 16.042928 | AC87: 11.945111 | AD87: 11.302543 | AE87: 10.391104 | AF87: 2.9883274 | AG87: 1.9799504 | AH87: 0.73599264 | AI87: 1.3000546 | AJ87: 6.472062 | AK87: 7.7777845 | AL87: 9.1827075 | AM87: 8.8317414 | AN87: 9.2045383 | AO87: 9.2148639 | AP87: 6.9008383 | AQ87: 6.463228 | AR87: 0.38811082 | AS87: -0.21087975 | AT87: 1.2459763 | AU87: 1.2978777 | AV87: 0.33668166 | AW87: 0.59136058 | AX87: 0.098566717 | AY87: -0.65523142 | AZ87: -1.376399 | BA87: -0.65327564 | BB87: -1.4166582 | BC87: -0.19324483 | BD87: 0.75907569 | BE87: 1.7472405 | BF87: 3.4689027 | BG87: 3.5230238 | BH87: 3.3232456 | BI87: 3.0347418 | BJ87: 1.5465454 | BK87: 0.91888595 | BL87: 0.5819601 | BM87: -2.7456828 | BN87: -2.5396798 | BO87: -2.7718464 | BP87: 3.3629924 | BQ87: 7.5344443 | BR87: 9.7987001 | BS87: 12.750176 | BT87: 20.840362 | BU87: 18.68479 | BV87: 16.574786 | BW87: 12.326351 | BX87: 2.452899 | BY87: 1.6763809 | BZ87: 0.71967904 | CA87: 1.5377568 | CB87: -2.3007293 | CC87: -1.7051538 | CD87: -0.60777656 | CE87: -0.2094477 | CF87: 0.44453722 | CG87: 1.6922058 | CH87: 1.7664488 | CI87: 0.96882389
B88: K | C88: Actividades financieras y de seguros | H88: 10.297423 | I88: 7.1755009 | J88: 5.8043903 | K88: 6.5871369 | L88: 8.527183 | M88: 12.313713 | N88: 12.629522 | O88: 13.759124 | P88: 11.811387 | Q88: 8.9157081 | R88: 9.4650614 | S88: 10.137953 | T88: 7.1031107 | U88: 6.4319223 | V88: 5.6543081 | W88: 3.4809205 | X88: -3.0372893 | Y88: 1.1703289 | Z88: 3.0619246 | AA88: 4.6774572 | AB88: 13.363779 | AC88: 12.129882 | AD88: 11.151237 | AE88: 10.944783 | AF88: 8.6657461 | AG88: 9.004795 | AH88: 8.2865469 | AI88: 7.5624142 | AJ88: 9.892183 | AK88: 9.2929151 | AL88: 8.6757456 | AM88: 9.5170134 | AN88: 9.2053253 | AO88: 9.7832916 | AP88: 11.018762 | AQ88: 10.216049 | AR88: 11.029794 | AS88: 9.8896124 | AT88: 9.4005414 | AU88: 7.9560658 | AV88: 2.2769985 | AW88: 1.8624191 | AX88: 2.0300924 | AY88: 2.9686419 | AZ88: 2.3814009 | BA88: 4.852882 | BB88: 4.736388 | BC88: 5.3882327 | BD88: 3.6401709 | BE88: 3.9401064 | BF88: 4.1303106 | BG88: 3.7342966 | BH88: 6.7349646 | BI88: 5.8550876 | BJ88: 6.749888 | BK88: 6.2677625 | BL88: 2.3671005 | BM88: 1.7876062 | BN88: 1.8995353 | BO88: 2.2358752 | BP88: 5.0302886 | BQ88: 4.1702217 | BR88: 3.510274 | BS88: 3.6999505 | BT88: -3.1372439 | BU88: 4.0988702 | BV88: 5.9311546 | BW88: 6.6745449 | BX88: 23.861235 | BY88: 13.681108 | BZ88: 9.7804545 | CA88: 8.9369408 | CB88: -2.1994073 | CC88: -0.046764284 | CD88: 1.6183343 | CE88: 1.0736286 | CF88: 3.2794044 | CG88: 3.0397817 | CH88: 3.4832993 | CI88: 2.7636052
B89: L | C89: Actividades inmobiliarias | H89: 3.4946505 | I89: 3.6715761 | J89: 3.9062413 | K89: 4.0451496 | L89: 4.2477526 | M89: 4.0863269 | N89: 3.9131578 | O89: 3.7501196 | P89: 2.5860565 | Q89: 2.6355535 | R89: 2.7039779 | S89: 2.7773167 | T89: 3.6545857 | U89: 3.7243799 | V89: 3.762248 | W89: 3.830902 | X89: 3.872587 | Y89: 3.7635805 | Z89: 3.7087314 | AA89: 3.5703176 | AB89: 2.8861808 | AC89: 2.8276258 | AD89: 2.7882003 | AE89: 2.8298739 | AF89: 3.0299187 | AG89: 3.0684779 | AH89: 3.1430291 | AI89: 3.1657688 | AJ89: 3.1916155 | AK89: 3.2500793 | AL89: 3.2173468 | AM89: 3.2180437 | AN89: 3.2358826 | AO89: 3.1365616 | AP89: 3.1220263 | AQ89: 3.1070476 | AR89: 2.9765504 | AS89: 3.0250713 | AT89: 3.057503 | AU89: 3.1937219 | AV89: 3.4113426 | AW89: 3.6011599 | AX89: 3.6089275 | AY89: 3.5288221 | AZ89: 3.2517123 | BA89: 3.0329018 | BB89: 3.0015644 | BC89: 3.0516399 | BD89: 3.3091181 | BE89: 3.6179597 | BF89: 3.8975111 | BG89: 3.9653668 | BH89: 4.3743504 | BI89: 4.0582708 | BJ89: 3.641549 | BK89: 3.2472982 | BL89: 1.9758705 | BM89: 1.3170925 | BN89: 1.3311377 | BO89: 1.4431494 | BP89: 1.9144201 | BQ89: 2.568815 | BR89: 2.563371 | BS89: 2.4963633 | BT89: 2.2835024 | BU89: 2.1767719 | BV89: 2.1410424 | BW89: 2.04467 | BX89: 1.8035733 | BY89: 1.80072 | BZ89: 1.7850387 | CA89: 1.8504768 | CB89: 2.083867 | CC89: 2.178675 | CD89: 2.1915795 | CE89: 2.2091583 | CF89: 1.991974 | CG89: 1.9882231 | CH89: 2.0121367 | CI89: 1.9834299
B90: M + N | C90: Actividades profesionales, científicas y técnicas; Actividades de servicios administrativos y de apoyo | H90: 7.1089389 | I90: 6.9273519 | J90: 7.0989874 | K90: 7.030535 | L90: 7.0200382 | M90: 6.8176283 | N90: 7.0175535 | O90: 6.877073 | P90: 4.8990959 | Q90: 4.4433508 | R90: 3.9414092 | S90: 3.7676381 | T90: 2.6902998 | U90: 3.2765234 | V90: 3.1507063 | W90: 2.7990654 | X90: 2.2898056 | Y90: 2.4500534 | Z90: 2.6069102 | AA90: 3.0819583 | AB90: 5.7619351 | AC90: 6.0162139 | AD90: 6.6530668 | AE90: 7.0864753 | AF90: 6.1491191 | AG90: 5.7541097 | AH90: 5.1465402 | AI90: 4.8159282 | AJ90: 2.8928996 | AK90: 3.7280417 | AL90: 4.4692796 | AM90: 5.2762881 | AN90: 8.7237951 | AO90: 8.4149272 | AP90: 7.9868417 | AQ90: 7.2901312 | AR90: 2.0377799 | AS90: 1.101355 | AT90: 1.0735343 | AU90: -0.18782609 | AV90: -3.09334 | AW90: -2.68961 | AX90: -2.9901325 | AY90: -2.4341372 | AZ90: 0.27015069 | BA90: 1.0178748 | BB90: 1.3834667 | BC90: 1.4554871 | BD90: 3.3595174 | BE90: 3.8388134 | BF90: 3.933416 | BG90: 3.9711318 | BH90: 3.9295292 | BI90: 4.0074961 | BJ90: 3.8819223 | BK90: 3.4469915 | BL90: 1.2029103 | BM90: -5.8045427 | BN90: -6.623366 | BO90: -5.7903178 | BP90: 1.0807252 | BQ90: 7.3667101 | BR90: 9.2589798 | BS90: 9.733514 | BT90: 8.6057534 | BU90: 10.831751 | BV90: 9.5683123 | BW90: 7.8601168 | BX90: 3.4422298 | BY90: 2.405188 | BZ90: 1.9452721 | CA90: 1.9153995 | CB90: -0.41466838 | CC90: -0.39599786 | CD90: -0.42921654 | CE90: -0.41908493 | CF90: 1.1671912 | CG90: 1.3680363 | CH90: 1.3000009 | CI90: 1.3415756
B91: O + P + Q | C91: Administración pública y defensa; planes de seguridad social de afiliación obligatoria; Educación; Actividades de atención de la salud humana y de servicios sociales | H91: 3.6884002 | I91: 3.4755061 | J91: 4.0012936 | K91: 4.6177404 | L91: 3.4305124 | M91: 3.5808902 | N91: 3.9444192 | O91: 4.0889498 | P91: 3.8501329 | Q91: 3.9705841 | R91: 2.8921595 | S91: 2.132518 | T91: 1.4916598 | U91: 2.0364622 | V91: 2.6626032 | W91: 3.0492503 | X91: 5.0258205 | Y91: 4.7533376 | Z91: 4.331525 | AA91: 4.6346576 | AB91: 5.742181 | AC91: 5.4255586 | AD91: 5.5100096 | AE91: 5.7437736 | AF91: 5.0516249 | AG91: 5.2703494 | AH91: 5.5189524 | AI91: 5.5591868 | AJ91: 3.9258644 | AK91: 5.0811718 | AL91: 5.3734817 | AM91: 5.5078031 | AN91: 6.6419332 | AO91: 5.5089588 | AP91: 5.6421559 | AQ91: 5.845958 | AR91: 5.9336127 | AS91: 6.7660851 | AT91: 7.8625007 | AU91: 5.3276069 | AV91: 1.8565462 | AW91: 3.2363179 | AX91: 2.3844708 | AY91: 3.6769364 | AZ91: 3.2077997 | BA91: 3.3934686 | BB91: 3.3157157 | BC91: 3.4630544 | BD91: 3.9933331 | BE91: 4.6772041 | BF91: 4.7375628 | BG91: 4.736238 | BH91: 4.7735894 | BI91: 5.1853093 | BJ91: 5.251371 | BK91: 5.0962546 | BL91: 1.1326758 | BM91: -0.72240864 | BN91: -1.0963184 | BO91: 0.30906879 | BP91: 6.8389476 | BQ91: 8.5726269 | BR91: 9.2413139 | BS91: 8.4615269 | BT91: 3.4447726 | BU91: 4.5632252 | BV91: 2.6162906 | BW91: 1.1217303 | BX91: 0.43990745 | BY91: 2.7529815 | BZ91: 4.2687783 | CA91: 4.9337519 | CB91: 5.7805567 | CC91: 5.0200994 | CD91: 3.8154158 | CE91: 4.0635719 | CF91: 3.6154904 | CG91: 2.5832171 | CH91: 4.3659472 | CI91: 4.4888638
B92: R + S + T | C92: Actividades artísticas, de entretenimiento y recreación y otras actividades de servicios; Actividades de los hogares individuales en calidad de empleadores; actividades no diferenciadas de los hogares individuales como productores de bienes y servicios para uso propio | H92: 5.3950416 | I92: 5.9853203 | J92: 5.6979013 | K92: 5.07201 | L92: 5.3579122 | M92: 4.8816301 | N92: 4.605019 | O92: 5.2964839 | P92: 3.8617163 | Q92: 3.4576489 | R92: 3.5055963 | S92: 2.9925716 | T92: 1.383143 | U92: 1.9120324 | V92: 1.9235392 | W92: 2.3286166 | X92: 3.678271 | Y92: 2.6967253 | Z92: 2.6913249 | AA92: 2.4300195 | AB92: 3.7840696 | AC92: 5.2808674 | AD92: 6.3039627 | AE92: 6.0882102 | AF92: 3.5398669 | AG92: 2.5132552 | AH92: 3.2938181 | AI92: 3.0207561 | AJ92: 5.0357789 | AK92: 5.6147892 | AL92: 5.1224314 | AM92: 6.2421299 | AN92: 6.0245814 | AO92: 3.5508859 | AP92: 3.2289136 | AQ92: 2.7768371 | AR92: 2.181733 | AS92: 3.4375708 | AT92: 3.7180101 | AU92: 4.2394289 | AV92: 5.99627 | AW92: 6.4312656 | AX92: 6.0508411 | AY92: 5.5420925 | AZ92: 2.9706214 | BA92: 2.4155137 | BB92: 2.1466316 | BC92: 2.1064191 | BD92: -2.4420251 | BE92: -0.096490776 | BF92: 0.72140256 | BG92: 2.2927259 | BH92: 12.362025 | BI92: 13.800874 | BJ92: 13.609433 | BK92: 13.037037 | BL92: 3.7705103 | BM92: -15.651818 | BN92: -14.061681 | BO92: -11.787088 | BP92: 9.458152 | BQ92: 36.63024 | BR92: 35.612569 | BS92: 34.426072 | BT92: 30.373449 | BU92: 26.948981 | BV92: 26.44792 | BW92: 28.108956 | BX92: 15.13745 | BY92: 14.219945 | BZ92: 12.922924 | CA92: 10.377936 | CB92: 6.1710309 | CC92: 8.5509627 | CD92: 9.5542148 | CE92: 8.1919266 | CF92: 15.581151 | CG92: 11.52363 | CH92: 9.2883402 | CI92: 9.8935851
A93: B.1b | C93: Valor agregado bruto | H93: 5.56244 | I93: 5.0740652 | J93: 5.8741924 | K93: 6.1974423 | L93: 6.337461 | M93: 6.5041176 | N93: 6.3455175 | O93: 6.3080938 | P93: 4.7617094 | Q93: 4.6596426 | R93: 4.1887112 | S93: 3.0931911 | T93: 0.17553246 | U93: 0.56868123 | V93: 0.73314035 | W93: 1.415944 | X93: 4.0015153 | Y93: 4.2563172 | Z93: 4.057885 | AA93: 4.3336984 | AB93: 6.5291047 | AC93: 6.4793526 | AD93: 6.8558949 | AE93: 6.6168728 | AF93: 5.992753 | AG93: 5.420108 | AH93: 4.3025411 | AI93: 3.8546561 | AJ93: 2.4224931 | AK93: 3.999637 | AL93: 4.8665089 | AM93: 5.3135705 | AN93: 6.6547927 | AO93: 4.8945408 | AP93: 4.6658124 | AQ93: 4.4053999 | AR93: 2.8354347 | AS93: 3.2619074 | AT93: 3.4151344 | AU93: 3.0776134 | AV93: 2.4686567 | AW93: 2.40273 | AX93: 2.048094 | AY93: 2.1889197 | AZ93: 1.1868087 | BA93: 1.25609 | BB93: 1.4153417 | BC93: 1.3852015 | BD93: 1.58562 | BE93: 2.1185452 | BF93: 2.372461 | BG93: 2.5146821 | BH93: 3.5038833 | BI93: 3.259016 | BJ93: 3.1486597 | BK93: 3.0681473 | BL93: 0.12912182 | BM93: -8.4097754 | BN93: -8.6771078 | BO93: -7.2957332 | BP93: 1.3973481 | BQ93: 8.987436 | BR93: 10.286554 | BS93: 10.302562 | BT93: 7.2186328 | BU93: 9.3803023 | BV93: 8.2955841 | BW93: 6.4155383 | BX93: 2.6797542 | BY93: 1.6598848 | BZ93: 1.1758031 | CA93: 1.2203923 | CB93: 0.5872451 | CC93: 1.2153142 | CD93: 1.3549509 | CE93: 1.6005322 | CF93: 2.6321967 | CG93: 2.3487548 | CH93: 2.8060229 | CI93: 2.6596975
A94: D.21-D.31 | C94: Impuestos menos subvenciones sobre los productos | H94: 15.194095 | I94: 13.865156 | J94: 12.575978 | K94: 11.997648 | L94: 10.470311 | M94: 9.5745645 | N94: 11.328008 | O94: 10.888782 | P94: 9.1532671 | Q94: 7.9961548 | R94: 6.4274073 | S94: 5.089656 | T94: -0.26213163 | U94: -1.1028809 | V94: -2.2469685 | W94: -1.5963676 | X94: 2.673592 | Y94: 4.3242037 | Z94: 5.5259295 | AA94: 6.208917 | AB94: 9.6542758 | AC94: 10.041457 | AD94: 10.510035 | AE94: 10.335138 | AF94: 7.5748321 | AG94: 6.0634523 | AH94: 4.9289071 | AI94: 4.4874299 | AJ94: 1.9280067 | AK94: 2.7909689 | AL94: 2.9329108 | AM94: 3.3227162 | AN94: 6.0107081 | AO94: 5.7810301 | AP94: 5.8623378 | AQ94: 5.5054635 | AR94: 2.8181716 | AS94: 1.7812587 | AT94: 1.9335665 | AU94: 1.7147012 | AV94: 1.4505671 | AW94: 0.71114798 | AX94: 1.6259564 | AY94: 1.0870005 | AZ94: -0.14096541 | BA94: 0.26940234 | BB94: 0.64090852 | BC94: 1.0913215 | BD94: 2.3253164 | BE94: 3.136105 | BF94: 3.1345049 | BG94: 3.055178 | BH94: 3.1945521 | BI94: 3.3946926 | BJ94: 3.9438615 | BK94: 4.3553427 | BL94: 2.502217 | BM94: -7.5353927 | BN94: -7.7218115 | BO94: -6.1345703 | BP94: 2.4699992 | BQ94: 12.628984 | BR94: 14.796022 | BS94: 15.884429 | BT94: 17.089036 | BU94: 18.909306 | BV94: 18.592579 | BW94: 16.042419 | BX94: 3.9394115 | BY94: 0.81469371 | BZ94: -1.7972908 | CA94: -2.5140968 | CB94: -2.1660272 | CC94: -1.3860216 | CD94: -0.4311361 | CE94: 0.49963101 | CF94: 2.182459 | CG94: 2.3306576 | CH94: 2.4716622 | CI94: 2.4730157
A95: B.1b | C95: Producto Interno Bruto | H95: 6.3755741 | I95: 5.8398308 | J95: 6.463579 | K95: 6.7168687 | L95: 6.7128664 | M95: 6.7880534 | N95: 6.8111415 | O95: 6.7381947 | P95: 5.1743787 | Q95: 4.9771747 | R95: 4.4007395 | S95: 3.2834462 | T95: 0.14508701 | U95: 0.42348682 | V95: 0.46095765 | W95: 1.1396486 | X95: 3.8803502 | Y95: 4.2578886 | Z95: 4.1854153 | AA95: 4.494659 | AB95: 6.7991977 | AC95: 6.7907431 | AD95: 7.1785509 | AE95: 6.947892 | AF95: 6.1351561 | AG95: 5.4789255 | AH95: 4.3597383 | AI95: 3.9126358 | AJ95: 2.3818401 | AK95: 3.8955175 | AL95: 4.6939146 | AM95: 5.1339935 | AN95: 6.6000143 | AO95: 4.9707736 | AP95: 4.7693932 | AQ95: 4.49903 | AR95: 2.8280769 | AS95: 3.1285569 | AT95: 3.2819408 | AU95: 2.9559014 | AV95: 2.3747844 | AW95: 2.2466521 | AX95: 2.0092355 | AY95: 2.0873825 | AZ95: 1.0694632 | BA95: 1.1709404 | BB95: 1.3487501 | BC95: 1.3593609 | BD95: 1.6492417 | BE95: 2.2065152 | BF95: 2.4382593 | BG95: 2.5643243 | BH95: 3.4755274 | BI95: 3.2714499 | BJ95: 3.2215704 | BK95: 3.1868554 | BL95: 0.34608976 | BM95: -8.3304749 | BN95: -8.5890432 | BO95: -7.1859141 | BP95: 1.4997004 | BQ95: 9.3208753 | BR95: 10.693916 | BS95: 10.801198 | BT95: 8.1051367 | BU95: 10.248387 | BV95: 9.248534 | BW95: 7.3282773 | BX95: 2.8075119 | BY95: 1.581759 | BZ95: 0.88147833 | CA95: 0.84181956 | CB95: 0.31878093 | CC95: 0.96497071 | CD95: 1.183254 | CE95: 1.4933073 | CF95: 2.593029 | CG95: 2.351614 | CH95: 2.7779431 | CI95: 2.6420088
A97: Fuente: DANE, PIB_T
A98: prpreliminar
A99: pprovisional
A100: Actualizado el 16 de febrero de 2026

Sheet PIB oferta anual NORMAL
A1: Suma Agregada PIB por Oferta Anual
X3: PROYECCIÓN OFERTA ANUAL
A5: Secciones CIIU Rev. 4 A.C. 12 agrupaciones | B5: Concepto | C5: 2005 | D5: 2006 | E5: 2007 | F5: 2008 | G5: 2009 | H5: 2010 | I5: 2011 | J5: 2012 | K5: 2013 | L5: 2014 | M5: 2015 | N5: 2016 | O5: 2017 | P5: 2018 | Q5: 2019 | R5: 2020 | S5: 2021 | T5: 2022 | U5: 2023 | V5: 2024 | W5: 2025 | X5: 2026 | Y5: 2027 | Z5: 2028 | AA5: 2029 | AB5: 2030
A6: A | B6: Agricultura, ganadería, caza, silvicultura y pesca | C6: 37909 | D6: 38717 | E6: 40239 | F6: 39915 | G6: 39822 | H6: 39943 | I6: 40706 | J6: 41725 | K6: 44835 | L6: 46140 | M6: 48124 | N6: 49441 | O6: 52198 | P6: 53030 | Q6: 54471 | R6: 55539 | S6: 57968 | T6: 57442 | U6: 58389 | V6: 61967 | W6: 63888.121 | X6: =W6*(1+$X$20) -> 65216.919 | Y6: =X6*(1+$Y$20) -> 66778.492 | Z6: =Y6*(1+$Z$20) -> 68272.431 | AA6: =Z6*(1+$AA$20) -> 69853.479 | AB6: =AA6*(1+$AB$20) -> 71443.675
A7: B | B7: Explotación de minas y canteras | C7: 27430 | D7: 28059 | E7: 28434 | F7: 31101 | G7: 34659 | H7: 38427 | I7: 43974 | J7: 46335 | K7: 48794 | L7: 48136 | M7: 47627 | N7: 46253 | O7: 43592 | P7: 42868 | Q7: 43693 | R7: 37056 | S7: 36980 | T7: 37518 | U7: 38481 | V7: 37168 | W7: 34868.277 | X7: =35593.4966263493 -> 35593.497 | Y7: =X7*(1+$Y$20) -> 36445.757 | Z7: =Y7*(1+$Z$20) -> 37261.106 | AA7: =Z7*(1+$AA$20) -> 38123.996 | AB7: =AA7*(1+$AB$20) -> 38991.879
A8: C | B8: Industrias manufactureras | C8: 77252 | D8: 82885 | E8: 89320 | F8: 89639 | G8: 86354 | H8: 87980 | I8: 92896 | J8: 93667 | K8: 95081 | L8: 97829 | M8: 99789 | N8: 103006 | O8: 101135 | P8: 102627 | Q8: 103860 | R8: 94254 | S8: 107066 | T8: 115802 | U8: 113925 | V8: 111003 | W8: 113056.56 | X8: =W8*(1+$X$20) -> 115408.01 | Y8: =X8*(1+$Y$20) -> 118171.37 | Z8: =Y8*(1+$Z$20) -> 120815.05 | AA8: =Z8*(1+$AA$20) -> 123612.87 | AB8: =AA8*(1+$AB$20) -> 126426.89
A9: D + E | B9: Suministro de electricidad, gas, vapor y aire acondicionado; Distribución de agua; evacuación y tratamiento de aguas residuales, gestión de desechos y actividades de saneamiento ambiental | C9: 18685 | D9: 19679 | E9: 20511 | F9: 20619 | G9: 21113 | H9: 21935 | I9: 22608 | J9: 23094 | K9: 23950 | L9: 24773 | M9: 24599 | N9: 24597 | O9: 25307 | P9: 25952 | Q9: 26606 | R9: 25587 | S9: 27079 | T9: 28327 | U9: 29221 | V9: 29948 | W9: 30289.602 | X9: =W9*(1+$X$20) -> 30919.591 | Y9: =X9*(1+$Y$20) -> 31659.938 | Z9: =Y9*(1+$Z$20) -> 32368.221 | AA9: =Z9*(1+$AA$20) -> 33117.801 | AB9: =AA9*(1+$AB$20) -> 33871.72
A10: F | B10: Construcción | C10: 29808 | D10: 33427 | E10: 35747 | F10: 39289 | G10: 40316 | H10: 40048 | I10: 42536 | J10: 45051 | K10: 50131 | L10: 54602 | M10: 58042 | N10: 60125 | O10: 58907 | P10: 58156 | Q10: 55893 | R10: 39359 | S10: 41039 | T10: 43765 | U10: 42412 | V10: 42448 | W10: 41273.053 | X10: =W10*(1+$X$20) -> 42131.485 | Y10: =X10*(1+$Y$20) -> 43140.293 | Z10: =Y10*(1+$Z$20) -> 44105.408 | AA10: =Z10*(1+$AA$20) -> 45126.798 | AB10: =AA10*(1+$AB$20) -> 46154.098
A11: G + H + I | B11: Comercio al por mayor y al por menor; reparación de vehículos automotores y motocicletas; Transporte y almacenamiento; Alojamiento y servicios de comida | C11: 85427 | D11: 91926 | E11: 99343 | F11: 102346 | G11: 102185 | H11: 107647 | I11: 115063 | J11: 119453 | K11: 125149 | L11: 131063 | M11: 135429 | N11: 139066 | O11: 141652 | P11: 145438 | Q11: 150890 | R11: 130235 | S11: 156815 | T11: 175451 | U11: 169067 | V11: 171151 | W11: 179021.78 | X11: =W11*(1+$X$20) -> 182745.22 | Y11: =X11*(1+$Y$20) -> 187120.93 | Z11: =Y11*(1+$Z$20) -> 191307.11 | AA11: =Z11*(1+$AA$20) -> 195737.39 | AB11: =AA11*(1+$AB$20) -> 200193.3
A12: J | B12: Información y comunicaciones | C12: 12730 | D12: 14629 | E12: 16761 | F12: 17120 | G12: 15669 | H12: 18256 | I12: 20153 | J12: 20415 | K12: 22218 | L12: 23654 | M12: 23961 | N12: 23804 | O12: 23758 | P12: 24595 | Q12: 24821 | R12: 24133 | S12: 27210 | T12: 30564 | U12: 31034 | V12: 30969 | W12: 31269.035 | X12: =W12*(1+$X$20) -> 31919.395 | Y12: =X12*(1+$Y$20) -> 32683.682 | Z12: =Y12*(1+$Z$20) -> 33414.867 | AA12: =Z12*(1+$AA$20) -> 34188.686 | AB12: =AA12*(1+$AB$20) -> 34966.982
A13: K | B13: Actividades financieras y de seguros | C13: 15424 | D13: 16440 | E13: 18702 | F13: 20598 | G13: 21315 | H13: 22312 | I13: 24754 | J13: 26626 | K13: 29160 | L13: 32139 | M13: 34696 | N13: 35726 | O13: 37651 | P13: 39057 | Q13: 41505 | R13: 42433 | S13: 44003 | T13: 46940 | U13: 51135 | V13: 51684 | W13: 53112.342 | X13: =W13*(1+$X$20) -> 54217.017 | Y13: =X13*(1+$Y$20) -> 55515.204 | Z13: =Y13*(1+$Z$20) -> 56757.166 | AA13: =Z13*(1+$AA$20) -> 58071.544 | AB13: =AA13*(1+$AB$20) -> 59393.528
A14: L | B14: Actividades inmobiliarias | C14: 50233 | D14: 52265 | E14: 54225 | F14: 55731 | G14: 57866 | H14: 59932 | I14: 61628 | J14: 63579 | K14: 65625 | L14: 67664 | M14: 69825 | N14: 72289 | O14: 74495 | P14: 77449 | Q14: 79964 | R14: 81118 | S14: 83143 | T14: 84843 | U14: 86413 | V14: 88322 | W14: 90073.805 | X14: =W14*(1+$X$20) -> 91947.235 | Y14: =X14*(1+$Y$20) -> 94148.846 | Z14: =Y14*(1+$Z$20) -> 96255.103 | AA14: =Z14*(1+$AA$20) -> 98484.171 | AB14: =AA14*(1+$AB$20) -> 100726.14
A15: M + N | B15: Actividades profesionales, científicas y técnicas; Actividades de servicios administrativos y de apoyo | C15: 36057 | D15: 38592 | E15: 41246 | F15: 42800 | G15: 43998 | H15: 45354 | I15: 48568 | J15: 50907 | K15: 53593 | L15: 57500 | M15: 57392 | N15: 55995 | O15: 56810 | P15: 59066 | Q15: 61102 | R15: 57564 | S15: 63167 | T15: 68132 | U15: 69437 | V15: 69146 | W15: 70073.646 | X15: =W15*(1+$X$20) -> 71531.096 | Y15: =X15*(1+$Y$20) -> 73243.857 | Z15: =Y15*(1+$Z$20) -> 74882.436 | AA15: =Z15*(1+$AA$20) -> 76616.558 | AB15: =AA15*(1+$AB$20) -> 78360.714
A16: O + P + Q | B16: Administración pública y defensa; planes de seguridad social de afiliación obligatoria; Educación; Actividades de atención de la salud humana y de servicios sociales | C16: 71182 | D16: 74469 | E16: 77514 | F16: 79167 | G16: 81581 | H16: 85362 | I16: 90265 | J16: 95283 | K16: 100531 | L16: 106408 | M16: 112077 | N16: 116198 | O16: 120222 | P16: 125916 | Q16: 132333 | R16: 132742 | S16: 143974 | T16: 145589 | U16: 152772 | V16: 158980 | W16: 166116.4 | X16: =W16*(1+$X$20) -> 169571.42 | Y16: =X16*(1+$Y$20) -> 173631.69 | Z16: =Y16*(1+$Z$20) -> 177516.1 | AA16: =Z16*(1+$AA$20) -> 181627.01 | AB16: =AA16*(1+$AB$20) -> 185761.7
A17: R + S + T | B17: Actividades artísticas, de entretenimiento y recreación y otras actividades de servicios; Actividades de los hogares individuales en calidad de empleadores; actividades no diferenciadas de los hogares individuales como productores de bienes y servicios para uso propio | C17: 12776 | D17: 13424 | E17: 14135 | F17: 14558 | G17: 14897 | H17: 15259 | I17: 16188 | J17: 16677 | K17: 17718 | L17: 18210 | M17: 18982 | N17: 20034 | O17: 20456 | P17: 20925 | Q17: 23653 | R17: 20865 | S17: 28048 | T17: 35932 | U17: 39661 | V17: 42910 | W17: 47155.337 | X17: =W17*(1+$X$20) -> 48136.113 | Y17: =X17*(1+$Y$20) -> 49288.698 | Z17: =Y17*(1+$Z$20) -> 50391.363 | AA17: =Z17*(1+$AA$20) -> 51558.323 | AB17: =AA17*(1+$AB$20) -> 52732.035
B18: Impuestos menos subvenciones sobre los productos | C18: 42525 | D18: 47627 | E18: 52813 | F18: 55501 | G18: 54615 | H18: 58006 | I18: 64001 | J18: 66873 | K18: 69095 | L18: 72899 | M18: 74149 | N18: 74955 | O18: 75773 | P18: 78088 | Q18: 81489 | R18: 76490 | S18: 88640 | T18: 102860 | U18: 100274 | V18: 100775 | W18: 103267.18 | X18: =W18*(1+$X$20) -> 105415.02 | Y18: =X18*(1+$Y$20) -> 107939.11 | Z18: =Y18*(1+$Z$20) -> 110353.87 | AA18: =Z18*(1+$AA$20) -> 112909.44 | AB18: =AA18*(1+$AB$20) -> 115479.79
B19: PIB | C19: =SUM(C6:C18) -> 517438 | D19: =SUM(D6:D18) -> 552139 | E19: =SUM(E6:E18) -> 588990 | F19: =SUM(F6:F18) -> 608384 | G19: =SUM(G6:G18) -> 614390 | H19: =SUM(H6:H18) -> 640461 | I19: =SUM(I6:I18) -> 683340 | J19: =SUM(J6:J18) -> 709685 | ... AB19: =SUM(AB6:AB18) -> 1144502.4
B20: Tasas de Crecimiento | C20: 0 | D20: =IFERROR((D$19/C$19)-1,"") -> 0.067063107 | E20: =IFERROR((E$19/D$19)-1,"") -> 0.066742251 | F20: =IFERROR((F$19/E$19)-1,"") -> 0.032927554 | G20: =IFERROR((G$19/F$19)-1,"") -> 0.0098720545 | H20: =IFERROR((H$19/G$19)-1,"") -> 0.042433959 | I20: =IFERROR((I$19/H$19)-1,"") -> 0.066950212 | J20: =IFERROR((J$19/I$19)-1,"") -> 0.038553282 | K20: =IFERROR((K$19/J$19)-1,"") -> 0.051001501 | ... W20: =IFERROR((W$19/V$19)-1,"") -> 0.027089735 | X20: =AVERAGE(V20:W20) -> 0.020798836 | Y20: =AVERAGE(W20:X20) -> 0.023944285 | Z20: =AVERAGE(X20:Y20) -> 0.02237156 | AA20: =AVERAGE(Y20:Z20) -> 0.023157923 | AB20: =AVERAGE(Z20:AA20) -> 0.022764742
X21: Tasa de crecimiento Inercial

Sheet C1G
A3: Producto Interno Bruto (PIB)
A5: Series encadenadas de volumen con año de referencia 2015 | I5: Índice
A6: Datos originales | I6: Tasa de crecimiento anual
A7: Miles de millones de pesos | I7: Tasa de crecimiento año corrido
A8: 2005 - 2025pr cuarto trimestre
A10: Clasificación Cuentas Nacionales | B10: Concepto | C10: 2005 | G10: 2006 | K10: 2007 | O10: 2008 | S10: 2009 | W10: 2010 | AA10: 2011 | AE10: 2012 | AI10: 2013 | AM10: 2014 | AQ10: 2015 | AU10: 2016 | AY10: 2017 | BC10: 2018 | BG10: 2019 | BK10: 2020 | BO10: 2021 | BS10: 2022 | BW10: 2023 | CA10: 2024p | CE10: 2025pr
C11: I | D11: II | E11: III | F11: IV | G11: I | H11: II | I11: III | J11: IV | K11: I | L11: II | M11: III | N11: IV | O11: I | P11: II | Q11: III | R11: IV | S11: I | T11: II | U11: III | V11: IV | W11: I | X11: II | Y11: III | Z11: IV | AA11: I | AB11: II | AC11: III | AD11: IV | AE11: I | AF11: II | AG11: III | AH11: IV | AI11: I | AJ11: II | AK11: III | AL11: IV | AM11: I | AN11: II | AO11: III | AP11: IV | AQ11: I | AR11: II | AS11: III | AT11: IV | AU11: I | AV11: II | AW11: III | AX11: IV | AY11: I | AZ11: II | BA11: III | BB11: IV | BC11: I | BD11: II | BE11: III | BF11: IV | BG11: I | BH11: II | BI11: III | BJ11: IV | BK11: I | BL11: II | BM11: III | BN11: IV | BO11: I | BP11: II | BQ11: III | BR11: IV | BS11: I | BT11: II | BU11: III | BV11: IV | BW11: I | BX11: II | BY11: III | BZ11: IV | CA11: I | CB11: II | CC11: III | CD11: IV | CE11: I | CF11: II | CG11: III | CH11: IV
A13: P.8 | B13: Demanda interna1 | C13: 113928.9 | D13: 124084.41 | E13: 123351.17 | F13: 140033.52 | G13: 123815.12 | H13: 133231.53 | I13: 137786.66 | J13: 148804.68 | K13: 135409.59 | L13: 144784.42 | M13: 148604.92 | N13: 160090.07 | O13: 143788.11 | P13: 151865.49 | Q13: 156129.81 | R13: 168374.59 | S13: 145532.07 | T13: 153254.65 | U13: 154800.28 | V13: 168146 | W13: 151170.84 | X13: 162607.5 | Y13: 164875.49 | Z13: 180663.16 | AA13: 163099.4 | AB13: 176876.06 | AC13: 180404.74 | AD13: 194565.81 | AE13: 174812.47 | AF13: 188008.54 | AG13: 186033.64 | AH13: 201113.36 | AI13: 182393.4 | AJ13: 198564.87 | AK13: 200275.98 | AL13: 212902.74 | AM13: 195439.59 | AN13: 209079.4 | AO13: 209503.61 | AP13: 227658.4 | AQ13: 201365.26 | AR13: 212547.9 | AS13: 219441.82 | AT13: 228151.03 | AU13: 208074.34 | AV13: 213949.74 | AW13: 220373.31 | AX13: 229697.61 | AY13: 210291.93 | AZ13: 216680.18 | BA13: 223348.94 | BB13: 231576.96 | BC13: 213668.72 | BD13: 224260.03 | BE13: 231147.03 | BF13: 243365.22 | BG13: 223423.4 | BH13: 232655.89 | BI13: 242127.15 | BJ13: 250928.56 | BK13: 224619.24 | BL13: 190733.14 | BM13: 218543.84 | BN13: 243663.78 | BO13: 228863.05 | BP13: 236559.49 | BQ13: 254910.16 | BR13: 274583.3 | BS13: 258686.31 | BT13: 269145.74 | BU13: 280995.58 | BV13: 288085.36 | BW13: 262714.59 | BX13: 263719.92 | BY13: 265792.62 | BZ13: 278252.87 | CA13: 256425.61 | CB13: 267570.98 | CC13: 275251.02 | CD13: 288475.39 | CE13: 267840.88 | CF13: 278212.21 | CG13: 288773.29 | CH13: 295185.3
A14: P.3 | B14: Gasto de consumo final | C14: 96825.974 | D14: 100409.3 | E14: 102609.15 | F14: 119232.57 | G14: 102452.09 | H14: 106038.66 | I14: 109477.96 | J14: 126974.3 | K14: 108438.93 | L14: 111779.6 | M14: 116912.99 | N14: 135459.48 | O14: 114402.92 | P14: 116980.11 | Q14: 120931.49 | R14: 140192.48 | S14: 117214.41 | T14: 120058.62 | U14: 123358.45 | V14: 142784.52 | W14: 121815.43 | X14: 125685.49 | Y14: 130093.91 | Z14: 151407.16 | AA14: 127449.68 | AB14: 133770.09 | AC14: 137251.26 | AD14: 160521.97 | AE14: 136261.94 | AF14: 140708.43 | AG14: 144495.54 | AH14: 168228.09 | AI14: 142835.11 | AJ14: 149048.09 | AK14: 151944.03 | AL14: 177438.78 | AM14: 149686.07 | AN14: 154955.27 | AO14: 158197.49 | AP14: 185295.17 | AQ14: 155721.43 | AR14: 161711.33 | AS14: 166725.69 | AT14: 186042.55 | AU14: 158563.97 | AV14: 164095.96 | AW14: 166939.36 | AX14: 191501.71 | AY14: 160470.84 | AZ14: 168618.97 | BA14: 171932.09 | BB14: 195951.09 | BC14: 166269.07 | BD14: 175723.43 | BE14: 178796 | BF14: 203859.5 | BG14: 171813.54 | BH14: 183080.61 | BI14: 186937.14 | BJ14: 213924.71 | BK14: 178492.74 | BL14: 156964.65 | BM14: 172968.74 | BN14: 215481.87 | BO14: 184383.5 | BP14: 191510.34 | BQ14: 205151.35 | BR14: 242517.82 | BS14: 206010.52 | BT14: 221009.29 | BU14: 222958.16 | BV14: 247849.02 | BW14: 210298.41 | BX14: 222116.95 | BY14: 223416.64 | BZ14: 248089.99 | CA14: 210280.22 | CB14: 225183.15 | CC14: 224980.36 | CD14: 256724.26 | CE14: 218025.52 | CF14: 233652.07 | CG14: 237786.53 | CH14: 266461.13
A15: P.311 + P.313 + P.323 | B15: Gasto de consumo final individual de los hogares; gasto de consumo final de las ISFLH2 | C15: 82036.688 | D15: 84948.292 | E15: 86762.234 | F15: 94993.786 | G15: 86994.134 | H15: 90321.977 | I15: 92815.415 | J15: 100821.47 | K15: 92916.648 | L15: 95726.891 | M15: 99222.679 | N15: 107394.78 | O15: 97989.473 | P15: 99424.301 | Q15: 102764.67 | R15: 111347.55 | S15: 100026.39 | T15: 101870.58 | U15: 104015.22 | V15: 112643.8 | W15: 103799.36 | X15: 106508.91 | Y15: 109969.21 | Z15: 119426.52 | AA15: 108556.1 | AB15: 113235.78 | AC15: 115730.8 | AD15: 126368.32 | AE15: 116518.98 | AF15: 119286.48 | AG15: 122173.08 | AH15: 132047.45 | AI15: 121787.04 | AJ15: 125697.13 | AK15: 127427.94 | AL15: 137786.9 | AM15: 126810.99 | AN15: 130399.77 | AO15: 132771.01 | AP15: 144502.22 | AQ15: 131345.74 | AR15: 134566.1 | AS15: 137911.62 | AT15: 147189.54 | AU15: 134710.34 | AV15: 136275.33 | AW15: 138980.61 | AX15: 149772.72 | AY15: 135913.58 | AZ15: 139850.77 | BA15: 142791.44 | BB15: 152679.21 | BC15: 140483.36 | BD15: 144733.83 | BE15: 147349.31 | BF15: 157156.5 | BG15: 144587.36 | BH15: 149984.36 | BI15: 153725.84 | BJ15: 165430.45 | BK15: 151599.84 | BL15: 124339.01 | BM15: 140331.21 | BN15: 166726.94 | BO15: 154416.8 | BP15: 155973.11 | BQ15: 168170.24 | BR15: 190277.85 | BS15: 173355.6 | BT15: 181882.03 | BU15: 186525.82 | BV15: 199240.55 | BW15: 178431.02 | BX15: 183252.67 | BY15: 185662.96 | BZ15: 197460.35 | CA15: 179189.63 | CB15: 185291.26 | CC15: 189261.59 | CD15: 203280.52 | CE15: 185961.23 | CF15: 192014.7 | CG15: 196975.68 | CH15: 209564.53
A16: P.312 + P.322 | B16: Gasto de consumo final del gobierno general | C16: 14794.446 | D16: 15480.993 | E16: 15874.025 | F16: 24225.536 | G16: 15466.853 | H16: 15749.044 | I16: 16695.887 | J16: 26132.216 | K16: 15579.35 | L16: 16128.584 | M16: 17750.039 | N16: 27969.027 | O16: 16500.732 | P16: 17630.863 | Q16: 18252.41 | R16: 28679.995 | S16: 17189.977 | T16: 18204.911 | U16: 19363.433 | V16: 30166.679 | W16: 18048.824 | X16: 19218.287 | Y16: 20171.206 | Z16: 31924.683 | AA16: 18936.727 | AB16: 20583.608 | AC16: 21569.322 | AD16: 34061.343 | AE16: 19737.409 | AF16: 21432.211 | AG16: 22341.318 | AH16: 36214.062 | AI16: 21042.75 | AJ16: 23358.572 | AK16: 24528.877 | AL16: 39665.802 | AM16: 22883.845 | AN16: 24577.397 | AO16: 25455.194 | AP16: 40757.564 | AQ16: 24375.409 | AR16: 27145.2 | AS16: 28814.184 | AT16: 38853.207 | AU16: 23853.738 | AV16: 27820.673 | AW16: 27958.724 | AX16: 41728.865 | AY16: 24437.118 | AZ16: 28730 | BA16: 29095.947 | BB16: 43519.935 | BC16: 25738.385 | BD16: 30991.208 | BE16: 31447.17 | BF16: 46853.237 | BG16: 27196.72 | BH16: 33111.357 | BI16: 33220.085 | BJ16: 48623.839 | BK16: 26866.683 | BL16: 32677.636 | BM16: 32667.172 | BN16: 48859.51 | BO16: 30023.147 | BP16: 35584.196 | BQ16: 37034.31 | BR16: 52280.347 | BS16: 32405.161 | BT16: 39061.836 | BU16: 36216.021 | BV16: 48768.982 | BW16: 31239.05 | BX16: 38779.958 | BY16: 37519.966 | BZ16: 51339.027 | CA16: 30609.064 | CB16: 39851.134 | CC16: 35380.284 | CD16: 53970.518 | CE16: 31764.184 | CF16: 41583.14 | CG16: 40698.212 | CH16: 57180.695
A17: P.5 | B17: Formación bruta de capital | C17: 18548.464 | D17: 23912.502 | E17: 21772.334 | F17: 22486.7 | G17: 22240.984 | H17: 27234.14 | I17: 28214.251 | J17: 23715.625 | K17: 27087.063 | L17: 32620.846 | M17: 31425.569 | N17: 26290.522 | O17: 29447.374 | P17: 34605.521 | Q17: 34765.616 | R17: 29271.489 | S17: 28674.734 | T17: 33083.151 | U17: 31663.907 | V17: 26604.208 | W17: 29710.029 | X17: 36649.584 | Y17: 34768.272 | Z17: 30375.114 | AA17: 35503.928 | AB17: 42885.838 | AC17: 42623.777 | AD17: 34838.458 | AE17: 38420.059 | AF17: 47146.296 | AG17: 41460.761 | AH17: 33323.885 | AI17: 39587.915 | AJ17: 49537.532 | AK17: 48137.977 | AL17: 35605.576 | AM17: 45621.399 | AN17: 54366.003 | AO17: 51206.561 | AP17: 42339.038 | AQ17: 45629.521 | AR17: 50836.472 | AS17: 52724.857 | AT17: 42114.15 | AU17: 49513.564 | AV17: 49853.542 | AW17: 53431.836 | AX17: 38195.057 | AY17: 49865.417 | AZ17: 48068.737 | BA17: 51447.385 | BB17: 35446.461 | BC17: 47438.283 | BD17: 48548 | BE17: 52418.147 | BF17: 39203.571 | BG17: 51679.275 | BH17: 49562.686 | BI17: 55250.433 | BJ17: 36654.606 | BK17: 46075.354 | BL17: 33674.439 | BM17: 45531.961 | BN17: 27921.247 | BO17: 44240.555 | BP17: 44827.742 | BQ17: 49486.589 | BR17: 32368.114 | BS17: 52350.015 | BT17: 47973.173 | BU17: 57661.907 | BV17: 40358.904 | BW17: 52140.524 | BX17: 41553.742 | BY17: 42317.116 | BZ17: 30394.619 | CA17: 46049.785 | CB17: 42342.659 | CC17: 50160.977 | CD17: 31834.579 | CE17: 49687.499 | CF17: 44507.053 | CG17: 50879.048 | CH17: 28873.792
A18: P.51 | B18: Formación bruta de capital fijo | C18: 18507.162 | D18: 19918.576 | E18: 20553.359 | F18: 26958.903 | G18: 20661.048 | H18: 22856.2 | I18: 25926.201 | J18: 32626.551 | K18: 26638.797 | L18: 29355.031 | M18: 30867.009 | N18: 35512.163 | O18: 24056.647 | P18: 30171.637 | Q18: 30064.236 | R18: 34757.479 | S18: 25752.829 | T18: 30823.172 | U18: 32017.247 | V18: 35760.753 | W18: 25624.208 | X18: 33920.148 | Y18: 33380.259 | Z18: 40264.385 | AA18: 30263.715 | AB18: 36864.724 | AC18: 38555.824 | AD18: 43769.736 | AE18: 31661.212 | AF18: 39745.52 | AG18: 39330.248 | AH18: 43700.021 | AI18: 34741.942 | AJ18: 42393.653 | AK18: 40952.69 | AL18: 49444.714 | AM18: 38898.453 | AN18: 45795.094 | AO18: 46745.951 | AP18: 51517.502 | AQ18: 40790.507 | AR18: 48657.84 | AS18: 48478.49 | AT18: 50168.163 | AU18: 38485.368 | AV18: 47214.044 | AW18: 45284.074 | AX18: 51675.514 | AY18: 40404.479 | AZ18: 46582.572 | BA18: 47629.636 | BB18: 51429.313 | BC18: 39327.69 | BD18: 48458.461 | BE18: 48181.442 | BF18: 52007.407 | BG18: 44526.5 | BH18: 48942.697 | BI18: 48913.69 | BJ18: 49796.113 | BK18: 39636.464 | BL18: 27744.586 | BM18: 36407.213 | BN18: 42994.736 | BO18: 41623.676 | BP18: 39400.705 | BQ18: 41644.304 | BR18: 48621.315 | BS18: 47206.035 | BT18: 43656.038 | BU18: 47315.684 | BV18: 52807.242 | BW18: 44783.552 | BX18: 38053.901 | BY18: 39822.548 | BZ18: 43847.999 | CA18: 40362.981 | CB18: 38158.957 | CC18: 40774.236 | CD18: 48326.826 | CE18: 41144.243 | CF18: 38968.158 | CG18: 42833.056 | CH18: 46919.348
A19: P.6 | B19: Exportaciones | C19: 19831.478 | D19: 22333.865 | E19: 22882.818 | F19: 23076.84 | G19: 22337.196 | H19: 23616.113 | I19: 24648.785 | J19: 25910.905 | K19: 22749.44 | L19: 23879.216 | M19: 26699.485 | N19: 29187.86 | O19: 25886.593 | P19: 26784.471 | Q19: 26681.821 | R19: 25251.115 | S19: 24406.005 | T19: 24028.165 | U19: 24749.954 | V19: 25973.876 | W19: 24198.079 | X19: 25176.646 | Y19: 25210.557 | Z19: 26617.718 | AA19: 27426.425 | AB19: 28064.061 | AC19: 28190.065 | AD19: 29927.449 | AE19: 29769.725 | AF19: 28695.08 | AG19: 30038.437 | AH19: 30186.758 | AI19: 28895.47 | AJ19: 31197.575 | AK19: 30326.538 | AL19: 33821.416 | AM19: 30502.45 | AN19: 30298.846 | AO19: 31231.104 | AP19: 31849.6 | AQ19: 30585.323 | AR19: 32190.708 | AS19: 30319.263 | AT19: 32840.706 | AU19: 30067.975 | AV19: 30729.535 | AW19: 30634.088 | AX19: 34241.402 | AY19: 31008.905 | AZ19: 31689.325 | BA19: 31797.103 | BB19: 34406.667 | BC19: 30290.307 | BD19: 31637.21 | BE19: 32292.94 | BF19: 35509.543 | BG19: 32383.564 | BH19: 33754.201 | BI19: 33131.091 | BJ19: 34462.144 | BK19: 30089.282 | BL19: 23187.731 | BM19: 23824.354 | BN19: 26594.633 | BO19: 27041.913 | BP19: 26412.121 | BQ19: 30083.477 | BR19: 35333.488 | BS19: 31642.301 | BT19: 32988.543 | BU19: 34299.016 | BV19: 34753.141 | BW19: 32665.65 | BX19: 33508.39 | BY19: 34444.178 | BZ19: 37226.782 | CA19: 32589.737 | CB19: 33628.265 | CC19: 34113.571 | CD19: 38051.428 | CE19: 33651.524 | CF19: 33750.621 | CG19: 35035.367 | CH19: 38496.496
A20: P.7 | B20: Importaciones | C20: 17191.887 | D20: 19339.358 | E20: 20415.212 | F20: 21761.544 | G20: 19843.498 | H20: 22699.553 | I20: 24811.224 | J20: 25270.724 | K20: 22971.884 | L20: 25138.541 | M20: 27951.173 | N20: 29399.401 | O20: 26870.347 | P20: 27925.185 | Q20: 30610.74 | R20: 33249.728 | S20: 26942.143 | T20: 25672.504 | U20: 26739.45 | V20: 29040.903 | W20: 26872.721 | X20: 29019.313 | Y20: 30983.896 | Z20: 33258.07 | AA20: 32036.199 | AB20: 35552.833 | AC20: 37143.518 | AD20: 39703.45 | AE20: 36718.513 | AF20: 38996.592 | AG20: 40953.576 | AH20: 41308.319 | AI20: 39193.371 | AJ20: 42788.537 | AK20: 44415.28 | AL20: 45045.813 | AM20: 42509.443 | AN20: 45820.852 | AO20: 46418.099 | AP20: 49998.607 | AQ20: 43154.379 | AR20: 44377.699 | AS20: 48338.023 | AT20: 46879.898 | AU20: 42232.184 | AV20: 43640.088 | AW20: 44202.933 | AX20: 46203.795 | AY20: 43270.781 | AZ20: 44758.819 | BA20: 44860.126 | BB20: 45185.274 | BC20: 42666.012 | BD20: 46805.548 | BE20: 47121.114 | BF20: 51820.326 | BG20: 47737.017 | BH20: 51081.703 | BI20: 52287.79 | BJ20: 51143.49 | BK20: 45676.655 | BL20: 33917.385 | BM20: 38904.962 | BN20: 43113.998 | BO20: 43287.183 | BP20: 49494.877 | BQ20: 54303.199 | BR20: 57724.741 | BS20: 60097.176 | BT20: 62196.963 | BU20: 67259.286 | BV20: 64417.575 | BW20: 59110.861 | BX20: 57214.09 | BY20: 54913.957 | BZ20: 57259.092 | CA20: 52552.516 | CB20: 57422.494 | CC20: 59552.081 | CD20: 61629.909 | CE20: 59221.745 | CF20: 63408.013 | CG20: 65475.264 | CH20: 62513.81
A21: B.1b | B21: Producto Interno Bruto | C21: 121117.73 | D21: 125559.34 | E21: 129223.31 | F21: 138952.62 | G21: 128839.68 | H21: 132242.91 | I21: 139114.41 | J21: 149238 | K21: 137488.52 | L21: 141316.5 | M21: 148649.97 | N21: 159002.02 | O21: 144602.69 | P21: 148078.93 | Q21: 153584.53 | R21: 159446.84 | S21: 144812.49 | T21: 149108.6 | U21: 154402.16 | V21: 164292.74 | W21: 150431.72 | X21: 156004.2 | Y21: 160651.52 | Z21: 173063.55 | AA21: 160659.88 | AB21: 166585.33 | AC21: 173372.36 | AD21: 184010.44 | AE21: 170516.61 | AF21: 174658.12 | AG21: 177268.45 | AH21: 188971.82 | AI21: 174578.04 | AJ21: 184043.02 | AK21: 188345.14 | AL21: 200972.79 | AM21: 186100.22 | AN21: 190347.09 | AO21: 196605.87 | AP21: 208535.82 | AQ21: 191363.28 | AR21: 196861.4 | AS21: 203635.77 | AT21: 212831.55 | AU21: 195907.74 | AV21: 201038.99 | AW21: 206805.58 | AX21: 217736.68 | AY21: 198002.9 | AZ21: 203591.84 | BA21: 210300.68 | BB21: 220760.57 | BC21: 201268.45 | BD21: 209187.55 | BE21: 216359.03 | BF21: 227192.98 | BG21: 208263.59 | BH21: 215620.27 | BI21: 223124.46 | BJ21: 234215.69 | BK21: 208984.37 | BL21: 179587.95 | BM21: 202864.17 | BN21: 226463.51 | BO21: 212118.51 | BP21: 212672.15 | BQ21: 229893.55 | BR21: 251558.79 | BS21: 229311 | BT21: 239013.85 | BU21: 246908.06 | BV21: 257422.1 | BW21: 235748.94 | BX21: 239983.68 | BY21: 245804.91 | BZ21: 259305.47 | CA21: 236500.46 | CB21: 243822.84 | CC21: 249751.85 | CD21: 265414.85 | CE21: 242632.98 | CF21: 248985.66 | CG21: 258737.57 | CH21: 271434.71
A23: Fuente: DANE, PIB_T
A24: prpreliminar
A25: pprovisional
A26: 1Incluye el gasto de consumo final y la formación bruta de capital
A27: 2Instituciones sin fines de lucro que sirven a los hogares
A28: Actualizado el 16 de febrero de 2026
A31: Producto Interno Bruto (PIB)
A33: Tasa de crecimiento anual (%)
A34: Base 2015
A35: 2006 - 2025pr cuarto trimestre
A37: Clasificación Cuentas Nacionales | B37: Concepto | G37: 2006 | K37: 2007 | O37: 2008 | S37: 2009 | W37: 2010 | AA37: 2011 | AE37: 2012 | AI37: 2013 | AM37: 2014 | AQ37: 2015 | AU37: 2016 | AY37: 2017 | BC37: 2018 | BG37: 2019 | BK37: 2020 | BO37: 2021 | BS37: 2022 | BW37: 2023 | CA37: 2024p | CE37: 2025pr
G38: I | H38: II | I38: III | J38: IV | K38: I | L38: II | M38: III | N38: IV | O38: I | P38: II | Q38: III | R38: IV | S38: I | T38: II | U38: III | V38: IV | W38: I | X38: II | Y38: III | Z38: IV | AA38: I | AB38: II | AC38: III | AD38: IV | AE38: I | AF38: II | AG38: III | AH38: IV | AI38: I | AJ38: II | AK38: III | AL38: IV | AM38: I | AN38: II | AO38: III | AP38: IV | AQ38: I | AR38: II | AS38: III | AT38: IV | AU38: I | AV38: II | AW38: III | AX38: IV | AY38: I | AZ38: II | BA38: III | BB38: IV | BC38: I | BD38: II | BE38: III | BF38: IV | BG38: I | BH38: II | BI38: III | BJ38: IV | BK38: I | BL38: II | BM38: III | BN38: IV | BO38: I | BP38: II | BQ38: III | BR38: IV | BS38: I | BT38: II | BU38: III | BV38: IV | BW38: I | BX38: II | BY38: III | BZ38: IV | CA38: I | CB38: II | CC38: III | CD38: IV | CE38: I | CF38: II | CG38: III | CH38: IV
A40: P.8 | B40: Demanda interna1 | G40: 8.6775409 | H40: 7.371694 | I40: 11.702758 | J40: 6.263615 | K40: 9.3643368 | L40: 8.6712854 | M40: 7.8514546 | N40: 7.5840296 | O40: 6.1875367 | P40: 4.8907678 | Q40: 5.0636901 | R40: 5.1749115 | S40: 1.2128731 | T40: 0.91473015 | U40: -0.85155611 | V40: -0.13576498 | W40: 3.8745892 | X40: 6.1028207 | Y40: 6.5085202 | Z40: 7.4442248 | AA40: 7.8907761 | AB40: 8.7748427 | AC40: 9.4187743 | AD40: 7.6953398 | AE40: 7.1815532 | AF40: 6.2939429 | AG40: 3.1201497 | AH40: 3.3652131 | AI40: 4.3366121 | AJ40: 5.6148174 | AK40: 7.6557906 | AL40: 5.8620569 | AM40: 7.1527731 | AN40: 5.2952634 | AO40: 4.6074536 | AP40: 6.9307034 | AQ40: 3.0319681 | AR40: 1.6589354 | AS40: 4.7436947 | AT40: 0.21639007 | AU40: 3.3317972 | AV40: 0.65954305 | AW40: 0.42448113 | AX40: 0.67787732 | AY40: 1.0657688 | AZ40: 1.2762038 | BA40: 1.3502681 | BB40: 0.81818156 | BC40: 1.6057622 | BD40: 3.4981781 | BE40: 3.4914371 | BF40: 5.0904312 | BG40: 4.565329 | BH40: 3.7438036 | BI40: 4.7502786 | BJ40: 3.1078135 | BK40: 0.53523608 | BL40: -18.019208 | BM40: -9.7400517 | BN40: -2.89516 | BO40: 1.8893355 | BP40: 24.026424 | BQ40: 16.640283 | BR40: 12.689421 | BS40: 13.031051 | BT40: 13.775076 | BU40: 10.233183 | BV40: 4.9172935 | BW40: 1.5572047 | BX40: -2.0159436 | BY40: -5.41039 | BZ40: -3.4130482 | CA40: -2.3938449 | CB40: 1.4602852 | CC40: 3.5585626 | CD40: 3.6738236 | CE40: 4.4516886 | CF40: 3.9769772 | CG40: 4.912705 | CH40: 2.3259901
A41: P.3 | B41: Gasto de consumo final | G41: 5.8105418 | H41: 5.6064078 | I41: 6.6941452 | J41: 6.4929622 | K41: 5.8435519 | L41: 5.4140089 | M41: 6.791354 | N41: 6.6825973 | O41: 5.4998615 | P41: 4.652467 | Q41: 3.4371718 | R41: 3.4940336 | S41: 2.4575363 | T41: 2.6316506 | U41: 2.0068844 | V41: 1.8489178 | W41: 3.9253036 | X41: 4.6867734 | Y41: 5.4600736 | Z41: 6.0389185 | AA41: 4.6252328 | AB41: 6.4324033 | AC41: 5.5016812 | AD41: 6.0200603 | AE41: 6.9143011 | AF41: 5.1867686 | AG41: 5.2781169 | AH41: 4.8006626 | AI41: 4.8239214 | AJ41: 5.9269056 | AK41: 5.1548185 | AL41: 5.4751217 | AM41: 4.7964145 | AN41: 3.9632735 | AO41: 4.115637 | AP41: 4.4276614 | AQ41: 4.0320129 | AR41: 4.3600065 | AS41: 5.3908537 | AT41: 0.40334731 | AU41: 1.8254011 | AV41: 1.4746188 | AW41: 0.12815895 | AX41: 2.9343609 | AY41: 1.202587 | AZ41: 2.7563218 | BA41: 2.9907473 | BB41: 2.323417 | BC41: 3.6132582 | BD41: 4.2133196 | BE41: 3.9922201 | BF41: 4.0359103 | BG41: 3.3346406 | BH41: 4.1867975 | BI41: 4.5533105 | BJ41: 4.9373234 | BK41: 3.8874676 | BL41: -14.264735 | BM41: -7.472242 | BN41: 0.72790296 | BO41: 3.3002798 | BP41: 22.008579 | BQ41: 18.606024 | BR41: 12.546738 | BS41: 11.729371 | BT41: 15.403325 | BU41: 8.6798397 | BV41: 2.1982746 | BW41: 2.081394 | BX41: 0.5011808 | BY41: 0.20563699 | BZ41: 0.097223964 | CA41: -0.0086513543 | CB41: 1.3804444 | CC41: 0.69991289 | CD41: 3.4802979 | CE41: 3.6833211 | CF41: 3.7609009 | CG41: 5.6921241 | CH41: 3.7927324
A42: P.311 + P.313 + P.323 | B42: Gasto de consumo final individual de los hogares; gasto de consumo final de las ISFLH2 | G42: 6.0429622 | H42: 6.3258301 | I42: 6.9767469 | J42: 6.1348096 | K42: 6.8079463 | L42: 5.9840524 | M42: 6.9032319 | N42: 6.5197503 | O42: 5.4595443 | P42: 3.8624563 | Q42: 3.569744 | R42: 3.6805974 | S42: 2.0787144 | T42: 2.4604458 | U42: 1.2169061 | V42: 1.164146 | W42: 3.7719707 | X42: 4.553159 | Y42: 5.7241495 | Z42: 6.0213853 | AA42: 4.5826249 | AB42: 6.315779 | AC42: 5.2392775 | AD42: 5.8126162 | AE42: 7.335271 | AF42: 5.3434569 | AG42: 5.5666067 | AH42: 4.4941109 | AI42: 4.521201 | AJ42: 5.3741607 | AK42: 4.3011563 | AL42: 4.3464982 | AM42: 4.1251975 | AN42: 3.7412484 | AO42: 4.1930164 | AP42: 4.8737058 | AQ42: 3.575989 | AR42: 3.195039 | AS42: 3.8717888 | AT42: 1.8597057 | AU42: 2.5616367 | AV42: 1.2701817 | AW42: 0.77512191 | AX42: 1.7550039 | AY42: 0.89320573 | AZ42: 2.6236854 | BA42: 2.7419919 | BB42: 1.9405981 | BC42: 3.3622679 | BD42: 3.4916276 | BE42: 3.1919711 | BF42: 2.932483 | BG42: 2.9213404 | BH42: 3.6277101 | BI42: 4.3274941 | BJ42: 5.2647816 | BK42: 4.8499954 | BL42: -17.09868 | BM42: -8.7133251 | BN42: 0.78371182 | BO42: 1.8581553 | BP42: 25.44181 | BQ42: 19.838093 | BR42: 14.125437 | BS42: 12.264728 | BT42: 16.611148 | BU42: 10.914879 | BV42: 4.7103212 | BW42: 2.9277545 | BX42: 0.75358655 | BY42: -0.4625968 | BZ42: -0.893494 | CA42: 0.42515184 | CB42: 1.1124483 | CC42: 1.938261 | CD42: 2.947515 | CE42: 3.7790176 | CF42: 3.6285801 | CG42: 4.0758893 | CH42: 3.0913006
A43: P.312 + P.322 | B43: Gasto de consumo final del gobierno general | G43: 4.5449981 | H43: 1.7314849 | I43: 5.1774011 | J43: 7.8705366 | K43: 0.72734297 | L43: 2.4099263 | M43: 6.3138415 | N43: 7.0289131 | O43: 5.9141224 | P43: 9.3143883 | Q43: 2.8302539 | R43: 2.5419835 | S43: 4.1770545 | T43: 3.2559288 | U43: 6.0869956 | V43: 5.1836958 | W43: 4.9962104 | X43: 5.5664962 | Y43: 4.1716395 | Z43: 5.8276361 | AA43: 4.919448 | AB43: 7.1042798 | AC43: 6.9312482 | AD43: 6.6928159 | AE43: 4.2281991 | AF43: 4.1227131 | AG43: 3.5791366 | AH43: 6.3201233 | AI43: 6.6135354 | AJ43: 8.9881564 | AK43: 9.7915403 | AL43: 9.5314899 | AM43: 8.7493075 | AN43: 5.2178941 | AO43: 3.7764346 | AP43: 2.7524027 | AQ43: 6.5179794 | AR43: 10.447822 | AS43: 13.195697 | AT43: -4.6724023 | AU43: -2.1401539 | AV43: 2.4883697 | AW43: -2.9688841 | AX43: 7.4013403 | AY43: 2.4456562 | AZ43: 3.2685286 | BA43: 4.0675071 | BB43: 4.2921605 | BC43: 5.3249625 | BD43: 7.8705465 | BE43: 8.0809275 | BF43: 7.6592537 | BG43: 5.6659912 | BH43: 6.8411304 | BI43: 5.6377565 | BJ43: 3.7790378 | BK43: -1.2135191 | BL43: -1.3098861 | BM43: -1.6643936 | BN43: 0.48468288 | BO43: 11.748621 | BP43: 8.8946471 | BQ43: 13.368583 | BR43: 7.0013736 | BS43: 7.9339252 | BT43: 9.7729891 | BU43: -2.2095426 | BV43: -6.7164145 | BW43: -3.5985365 | BX43: -0.72161963 | BY43: 3.6004636 | BZ43: 5.2698348 | CA43: -2.0166613 | CB43: 2.7621899 | CC43: -5.7027809 | CD43: 5.125713 | CE43: 3.7737859 | CF43: 4.3461898 | CG43: 15.030767 | CH43: 5.9480188
A44: P.5 | B44: Formación bruta de capital | G44: 19.907411 | H44: 13.890803 | I44: 29.587626 | J44: 5.465122 | K44: 21.788961 | L44: 19.779239 | M44: 11.3819 | N44: 10.857387 | O44: 8.7137964 | P44: 6.0840705 | Q44: 10.628437 | R44: 11.338559 | S44: -2.6238016 | T44: -4.3992112 | U44: -8.9217718 | V44: -9.1122133 | W44: 3.6104794 | X44: 10.78021 | Y44: 9.8041143 | Z44: 14.174095 | AA44: 19.501491 | AB44: 17.015892 | AC44: 22.593887 | AD44: 14.69408 | AE44: 8.2135443 | AF44: 9.9344168 | AG44: -2.7285614 | AH44: -4.3474165 | AI44: 3.039705 | AJ44: 5.0719483 | AK44: 16.104905 | AL44: 6.8470161 | AM44: 15.240721 | AN44: 9.7470961 | AO44: 6.3745592 | AP44: 18.911256 | AQ44: 0.017803085 | AR44: -6.492165 | AS44: 2.9650433 | AT44: -0.53116023 | AU44: 8.512129 | AV44: -1.9335127 | AW44: 1.3408833 | AX44: -9.3058814 | AY44: 0.71061814 | AZ44: -3.5800977 | BA44: -3.7139861 | BB44: -7.1962083 | BC44: -4.8673685 | BD44: 0.99703677 | BE44: 1.8869012 | BF44: 10.599392 | BG44: 8.9400206 | BH44: 2.0900674 | BI44: 5.4032566 | BJ44: -6.5018698 | BK44: -10.843654 | BL44: -32.056873 | BM44: -17.589857 | BN44: -23.826089 | BO44: -3.9821698 | BP44: 33.120979 | BQ44: 8.6853888 | BR44: 15.926464 | BS44: 18.330377 | BT44: 7.016707 | BU44: 16.52027 | BV44: 24.687228 | BW44: -0.40017525 | BX44: -13.381295 | BY44: -26.61166 | BZ44: -24.689187 | CA44: -11.681392 | CB44: 1.8985483 | CC44: 18.535906 | CD44: 4.7375498 | CE44: 7.8995245 | CF44: 5.1116156 | CG44: 1.4315333 | CH44: -9.3005386
A45: P.51 | B45: Formación bruta de capital fijo | G45: 11.638126 | H45: 14.748163 | I45: 26.140941 | J45: 21.023287 | K45: 28.932455 | L45: 28.433559 | M45: 19.057202 | N45: 8.8443674 | O45: -9.6931927 | P45: 2.7818276 | Q45: -2.6007474 | R45: -2.1251409 | S45: 7.0507812 | T45: 2.1594283 | U45: 6.4961246 | V45: 2.8864963 | W45: -0.49944205 | X45: 10.047557 | Y45: 4.2571186 | Z45: 12.593785 | AA45: 18.105953 | AB45: 8.6809064 | AC45: 15.50487 | AD45: 8.7058351 | AE45: 4.6177297 | AF45: 7.8145049 | AG45: 2.0085768 | AH45: -0.15927808 | AI45: 9.7302993 | AJ45: 6.6627222 | AK45: 4.1251763 | AL45: 13.145746 | AM45: 11.963956 | AN45: 8.0234664 | AO45: 14.146228 | AP45: 4.1921326 | AQ45: 4.8640858 | AR45: 6.2512073 | AS45: 3.7062873 | AT45: -2.6191869 | AU45: -5.6511658 | AV45: -2.9672426 | AW45: -6.5893472 | AX45: 3.0045974 | AY45: 4.9865982 | AZ45: -1.3374667 | BA45: 5.1796622 | BB45: -0.47643572 | BC45: -2.6650221 | BD45: 4.0270184 | BE45: 1.1585357 | BF45: 1.1240539 | BG45: 13.219209 | BH45: 0.99928147 | BI45: 1.5197705 | BJ45: -4.2518818 | BK45: -10.982304 | BL45: -43.312102 | BM45: -25.568459 | BN45: -13.658449 | BO45: 5.0135957 | BP45: 42.012226 | BQ45: 14.384761 | BR45: 13.086669 | BS45: 13.4115 | BT45: 10.800144 | BU45: 13.618623 | BV45: 8.6092427 | BW45: -5.1317244 | BX45: -12.832446 | BY45: -15.836474 | BZ45: -16.965936 | CA45: -9.8709691 | CB45: 0.27607245 | CC45: 2.3898197 | CD45: 10.214439 | CE45: 1.9355908 | CF45: 2.1206072 | CG45: 5.0493173 | CH45: -2.9124162
A46: P.6 | B46: Exportaciones | G46: 12.635058 | H46: 5.7412728 | I46: 7.7174401 | J46: 12.280995 | K46: 1.8455467 | L46: 1.1140816 | M46: 8.3196774 | N46: 12.647009 | O46: 13.790024 | P46: 12.166459 | Q46: -0.066155602 | R46: -13.487611 | S46: -5.7195153 | T46: -10.290687 | U46: -7.2403875 | V46: 2.8622937 | W46: -0.8519465 | X46: 4.779728 | Y46: 1.8610252 | Z46: 2.4788072 | AA46: 13.34133 | AB46: 11.468627 | AC46: 11.818491 | AD46: 12.434317 | AE46: 8.5439494 | AF46: 2.2484948 | AG46: 6.5568217 | AH46: 0.86645856 | AI46: -2.9367239 | AJ46: 8.7209897 | AK46: 0.95910998 | AL46: 12.040571 | AM46: 5.5613579 | AN46: -2.8807681 | AO46: 2.9827536 | AP46: -5.8300829 | AQ46: 0.27169252 | AR46: 6.2440101 | AS46: -2.9196589 | AT46: 3.1118315 | AU46: -1.6914923 | AV46: -4.5391142 | AW46: 1.038367 | AX46: 4.265122 | AY46: 3.1293426 | AZ46: 3.1233455 | BA46: 3.796475 | BB46: 0.48264673 | BC46: -2.3173911 | BD46: -0.16445695 | BE46: 1.5593776 | BF46: 3.2054136 | BG46: 6.910648 | BH46: 6.6914615 | BI46: 2.5954622 | BJ46: -2.9496276 | BK46: -7.0847091 | BL46: -31.304163 | BM46: -28.090646 | BN46: -22.82943 | BO46: -10.127757 | BP46: 13.905588 | BQ46: 26.271955 | BR46: 32.859471 | BS46: 17.012064 | BT46: 24.899254 | BU46: 14.012804 | BV46: -1.6424858 | BW46: 3.2341177 | BX46: 1.5758432 | BY46: 0.42322526 | BZ46: 7.1177478 | CA46: -0.23239467 | CB46: 0.35774421 | CC46: -0.95983498 | CD46: 2.215196 | CE46: 3.258041 | CF46: 0.36385095 | CG46: 2.7021385 | CH46: 1.1696488
A47: P.7 | B47: Importaciones | G47: 15.423619 | H47: 17.374908 | I47: 21.533026 | J47: 16.125604 | K47: 15.765296 | L47: 10.744652 | M47: 12.655356 | N47: 16.337788 | O47: 16.970581 | P47: 11.085147 | Q47: 9.5150468 | R47: 13.096615 | S47: 0.26719708 | T47: -8.0668455 | U47: -12.646838 | V47: -12.658222 | W47: -0.25767188 | X47: 13.036553 | Y47: 15.873349 | Z47: 14.521472 | AA47: 19.214571 | AB47: 22.514384 | AC47: 19.880077 | AD47: 19.379898 | AE47: 14.615698 | AF47: 9.686312 | AG47: 10.257666 | AH47: 4.0421412 | AI47: 6.7400812 | AJ47: 9.7237858 | AK47: 8.4527507 | AL47: 9.0477989 | AM47: 8.4607985 | AN47: 7.086746 | AO47: 4.5093021 | AP47: 10.995015 | AQ47: 1.5171606 | AR47: -3.1495545 | AS47: 4.1361555 | AT47: -6.237591 | AU47: -2.1369694 | AV47: -1.6621209 | AW47: -8.5545288 | AX47: -1.4422022 | AY47: 2.4592549 | AZ47: 2.5635395 | BA47: 1.4867635 | BB47: -2.2044098 | BC47: -1.3976376 | BD47: 4.5727963 | BE47: 5.0400833 | BF47: 14.684101 | BG47: 11.88535 | BH47: 9.1360001 | BI47: 10.964672 | BJ47: -1.3061195 | BK47: -4.3160674 | BL47: -33.601695 | BM47: -25.594556 | BN47: -15.69993 | BO47: -5.2312769 | BP47: 45.927751 | BQ47: 39.579107 | BR47: 33.888631 | BS47: 38.83365 | BT47: 25.663435 | BU47: 23.858793 | BV47: 11.594394 | BW47: -1.6411994 | BX47: -8.0114413 | BY47: -18.354832 | BZ47: -11.112625 | CA47: -11.094991 | CB47: 0.36425261 | CC47: 8.4461655 | CD47: 7.6334033 | CE47: 12.6906 | CF47: 10.423649 | CG47: 9.946224 | CH47: 1.434207
A48: B.1b | B48: Producto Interno Bruto | G48: 6.3755741 | H48: 5.323039 | I48: 7.654265 | J48: 7.4020784 | K48: 6.7128664 | L48: 6.8613055 | M48: 6.8544721 | N48: 6.5425803 | O48: 5.1743787 | P48: 4.7853126 | Q48: 3.3195886 | R48: 0.27975742 | S48: 0.14508701 | T48: 0.69535103 | U48: 0.53236473 | V48: 3.039196 | W48: 3.8803502 | X48: 4.6245494 | Y48: 4.0474546 | Z48: 5.3385254 | AA48: 6.7991977 | AB48: 6.7825905 | AC48: 7.9182778 | AD48: 6.3253583 | AE48: 6.1351561 | AF48: 4.846037 | AG48: 2.247241 | AH48: 2.6962516 | AI48: 2.3818401 | AJ48: 5.3733024 | AK48: 6.2485426 | AL48: 6.3506629 | AM48: 6.6000143 | AN48: 3.4253216 | AO48: 4.3859522 | AP48: 3.7632113 | AQ48: 2.8280769 | AR48: 3.4223328 | AS48: 3.5756298 | AT48: 2.05995 | AU48: 2.3747844 | AV48: 2.1220985 | AW48: 1.5566087 | AX48: 2.3047006 | AY48: 1.0694632 | AZ48: 1.2698276 | BA48: 1.6900414 | BB48: 1.3887831 | BC48: 1.6492417 | BD48: 2.7484906 | BE48: 2.8808028 | BF48: 2.9137462 | BG48: 3.4755274 | BH48: 3.075098 | BI48: 3.1269436 | BJ48: 3.0910783 | BK48: 0.34608976 | BL48: -16.711007 | BM48: -9.080262 | BN48: -3.3098452 | BO48: 1.4997004 | BP48: 18.422284 | BQ48: 13.323882 | BR48: 11.081378 | BS48: 8.1051367 | BT48: 12.386057 | BU48: 7.4010353 | BV48: 2.3307905 | BW48: 2.8075119 | BX48: 0.40576595 | BY48: -0.44678468 | BZ48: 0.73162986 | CA48: 0.31878093 | CB48: 1.5997579 | CC48: 1.605721 | CD48: 2.3560545 | CE48: 2.593029 | CF48: 2.1174491 | CG48: 3.5978602 | CH48: 2.2680951
A50: Fuente: DANE, PIB_T
A51: prpreliminar
A52: pprovisional
A53: 1Incluye el gasto de consumo final y la formación bruta de capital
A54: 2Instituciones sin fines de lucro que sirven a los hogares
A55: Actualizado el 16 de febrero de 2026
A58: Producto Interno Bruto (PIB)
A60: Tasa de crecimiento año corrido (%)
A61: Base 2015
A62: 2006 - 2025pr cuarto trimestre
A64: Clasificación Cuentas Nacionales | B64: Concepto | G64: 2006 | K64: 2007 | O64: 2008 | S64: 2009 | W64: 2010 | AA64: 2011 | AE64: 2012 | AI64: 2013 | AM64: 2014 | AQ64: 2015 | AU64: 2016 | AY64: 2017 | BC64: 2018 | BG64: 2019 | BK64: 2020 | BO64: 2021 | BS64: 2022 | BW64: 2023 | CA64: 2024p | CE64: 2025pr
G65: I | H65: II | I65: III | J65: IV | K65: I | L65: II | M65: III | N65: IV | O65: I | P65: II | Q65: III | R65: IV | S65: I | T65: II | U65: III | V65: IV | W65: I | X65: II | Y65: III | Z65: IV | AA65: I | AB65: II | AC65: III | AD65: IV | AE65: I | AF65: II | AG65: III | AH65: IV | AI65: I | AJ65: II | AK65: III | AL65: IV | AM65: I | AN65: II | AO65: III | AP65: IV | AQ65: I | AR65: II | AS65: III | AT65: IV | AU65: I | AV65: II | AW65: III | AX65: IV | AY65: I | AZ65: II | BA65: III | BB65: IV | BC65: I | BD65: II | BE65: III | BF65: IV | BG65: I | BH65: II | BI65: III | BJ65: IV | BK65: I | BL65: II | BM65: III | BN65: IV | BO65: I | BP65: II | BQ65: III | BR65: IV | BS65: I | BT65: II | BU65: III | BV65: IV | BW65: I | BX65: II | BY65: III | BZ65: IV | CA65: I | CB65: II | CC65: III | CD65: IV | CE65: I | CF65: II | CG65: III | CH65: IV
A67: P.8 | B67: Demanda interna1 | G67: 8.6775409 | H67: 7.9967586 | I67: 9.2617956 | J67: 8.4244453 | K67: 9.3643368 | L67: 9.0051168 | M67: 8.6025184 | N67: 8.3237375 | O67: 6.1875367 | P67: 5.5174584 | Q67: 5.3602001 | R67: 5.3098292 | S67: 1.2128731 | T67: 1.0597289 | U67: 0.39921646 | V67: 0.25396754 | W67: 3.8745892 | X67: 5.0175009 | Y67: 5.5263563 | Z67: 6.0450386 | AA67: 7.8907761 | AB67: 8.3489207 | AC67: 8.7174389 | AD67: 8.4373678 | AE67: 7.1815532 | AF67: 6.719764 | AG67: 5.4718543 | AH67: 4.8985518 | AI67: 4.3366121 | AJ67: 4.9989594 | AK67: 5.8994892 | AL67: 5.8894513 | AM67: 7.1527731 | AN67: 6.1845931 | AO67: 5.6411579 | AP67: 5.9868763 | AQ67: 3.0319681 | AR67: 2.3223034 | AS67: 3.1484785 | AT67: 2.3554054 | AU67: 3.3317972 | AV67: 1.9595721 | AW67: 1.4277011 | AX67: 1.2291267 | AY67: 1.0657688 | AZ67: 1.1724511 | BA67: 1.2334509 | BB67: 1.1240748 | BC67: 1.6057622 | BD67: 2.5661271 | BE67: 2.8839194 | BF67: 3.4633257 | BG67: 4.565329 | BH67: 4.144632 | BI67: 4.353866 | BJ67: 4.0215203 | BK67: 0.53523608 | BL67: -8.9297865 | BM67: -9.2107739 | BN67: -7.5410769 | BO67: 1.8893355 | BP67: 12.054864 | BQ67: 13.635746 | BR67: 13.372989 | BS67: 13.031051 | BT67: 13.409215 | BU67: 12.285286 | BV67: 10.25182 | BW67: 1.5572047 | BX67: -0.26477189 | BY67: -2.052416 | BZ67: -2.4097627 | CA67: -2.3938449 | CB67: -0.46309972 | CC67: 0.88617014 | CD67: 1.6107727 | CE67: 4.4516886 | CF67: 4.2092844 | CG67: 4.4515337 | CH67: 3.8878176
A68: P.3 | B68: Gasto de consumo final | G68: 5.8105418 | H68: 5.7066205 | I68: 6.0445593 | J68: 6.1721354 | K68: 5.8435519 | L68: 5.6250858 | M68: 6.0266369 | N68: 6.2138296 | O68: 5.4998615 | P68: 5.0697368 | Q68: 4.5035837 | R68: 4.2142148 | S68: 2.4575363 | T68: 2.5455631 | U68: 2.3606624 | V68: 2.2149939 | W68: 3.9253036 | X68: 4.3106024 | Y68: 4.7037932 | Z68: 5.0824765 | AA68: 4.6252328 | AB68: 5.542947 | AC68: 5.5287296 | AD68: 5.6693547 | AE68: 6.9143011 | AF68: 6.0296354 | AG68: 5.7707788 | AH68: 5.4921976 | AI68: 4.8239214 | AJ68: 5.3842671 | AK68: 5.3056029 | AL68: 5.3539632 | AM68: 4.7964145 | AN68: 4.3709769 | AO68: 4.2835615 | AP68: 4.3247176 | AQ68: 4.0320129 | AR68: 4.1988463 | AS68: 4.6062723 | AT68: 3.4046972 | AU68: 1.8254011 | AV68: 1.6467003 | AW68: 1.1237727 | AX68: 1.6263778 | AY68: 1.202587 | AZ68: 1.9927738 | BA68: 2.3330542 | BB68: 2.3303445 | BC68: 3.6132582 | BD68: 3.9207175 | BE68: 3.9452545 | BF68: 3.9707421 | BG68: 3.3346406 | BH68: 3.772498 | BI68: 4.0405649 | BJ68: 4.2928429 | BK68: 3.8874676 | BL68: -5.4767791 | BM68: -6.1652335 | BN68: -4.2140585 | BO68: 3.3002798 | BP68: 12.054123 | BQ68: 14.283108 | BR68: 13.766252 | BS68: 11.729371 | BT68: 13.601177 | BU68: 11.863586 | BV68: 9.0174036 | BW68: 2.081394 | BX68: 1.2635355 | BY68: 0.90065073 | BZ68: 0.6788613 | CA68: -0.0086513543 | CB68: 0.70487951 | CC68: 0.70318758 | CD68: 1.4653919 | CE68: 3.6833211 | CF68: 3.7234385 | CG68: 4.3940718 | CH68: 4.2257511
A69: P.311 + P.313 + P.323 | B69: Gasto de consumo final individual de los hogares; gasto de consumo final de las ISFLH2 | G69: 6.0429622 | H69: 6.1868622 | I69: 6.4569427 | J69: 6.3691966 | K69: 6.8079463 | L69: 6.388268 | M69: 6.5652062 | N69: 6.5528517 | O69: 5.4595443 | P69: 4.6491043 | Q69: 4.2770668 | R69: 4.1150025 | S69: 2.0787144 | T69: 2.2709673 | U69: 1.9101144 | V69: 1.708276 | W69: 3.7719707 | X69: 4.1661326 | Y69: 4.6958842 | Z69: 5.0526094 | AA69: 4.5826249 | AB69: 5.4603667 | AC69: 5.3844544 | AD69: 5.500746 | AE69: 7.335271 | AF69: 6.3183509 | AG69: 6.0605906 | AH69: 5.6338666 | AI69: 4.521201 | AJ69: 4.9526862 | AK69: 4.7303281 | AL69: 4.6268973 | AM69: 4.1251975 | AN69: 3.9301899 | AO69: 4.0195213 | AP69: 4.2490818 | AQ69: 3.575989 | AR69: 3.3828564 | AS69: 3.5493156 | AT69: 3.0925154 | AU69: 2.5616367 | AV69: 1.908089 | AW69: 1.5211642 | AX69: 1.5836287 | AY69: 0.89320573 | AZ69: 1.7634425 | BA69: 2.0951756 | BB69: 2.0538144 | BC69: 3.3622679 | BD69: 3.4278712 | BE69: 3.3473932 | BF69: 3.2364964 | BG69: 2.9213404 | BH69: 3.2797886 | BI69: 3.6366786 | BJ69: 4.0705552 | BK69: 4.8499954 | BL69: -6.325409 | BM69: -7.14425 | BN69: -5.0072671 | BO69: 1.8581553 | BP69: 12.485033 | BQ69: 14.963865 | BR69: 14.724089 | BS69: 12.264728 | BT69: 14.448834 | BU69: 13.206971 | BV69: 10.789758 | BW69: 2.9277545 | BX69: 1.8145783 | BY69: 1.0305609 | BZ69: 0.5132226 | CA69: 0.42515184 | CB69: 0.77338126 | CC69: 1.1685148 | CD69: 1.6401564 | CE69: 3.7790176 | CF69: 3.7025396 | CG69: 3.8301454 | CH69: 3.6317462
A70: P.312 + P.322 | B70: Gasto de consumo final del gobierno general | G70: 4.5449981 | H70: 3.1063409 | I70: 3.8187232 | J70: 5.2134991 | K70: 0.72734297 | L70: 1.5762399 | M70: 3.2271586 | N70: 4.568905 | O70: 5.9141224 | P70: 7.6437044 | Q70: 5.9161987 | R70: 4.6973278 | S70: 4.1770545 | T70: 3.701242 | U70: 4.5325215 | V70: 4.7629034 | W70: 4.9962104 | X70: 5.2895297 | Y70: 4.8942255 | Z70: 5.2257875 | AA70: 4.919448 | AB70: 6.0461445 | AC70: 6.3569755 | AD70: 6.4769535 | AE70: 4.2281991 | AF70: 4.1732582 | AG70: 3.9634878 | AH70: 4.8070961 | AI70: 6.6135354 | AJ70: 7.8497231 | AK70: 8.5327984 | AL70: 8.8954625 | AM70: 8.7493075 | AN70: 6.8915075 | AO70: 5.7830058 | AP70: 4.676047 | AQ70: 6.5179794 | AR70: 8.5530149 | AS70: 10.173779 | AT70: 4.8507134 | AU70: -2.1401539 | AV70: 0.29852456 | AW70: -0.8734174 | AX70: 1.8240091 | AY70: 2.4456562 | AZ70: 2.8886775 | BA70: 3.3025576 | BB70: 3.6428207 | BC70: 5.3249625 | BD70: 6.7005237 | BE70: 7.1887642 | BF70: 7.3515499 | BG70: 5.6659912 | BH70: 6.3079663 | BI70: 6.0689441 | BJ70: 5.2743835 | BK70: -1.2135191 | BL70: -1.2664281 | BM70: -1.4077807 | BN70: -0.7604536 | BO70: 11.748621 | BP70: 10.182374 | BQ70: 11.311132 | BR70: 9.8184602 | BS70: 7.9339252 | BT70: 8.9313991 | BU70: 4.9116169 | BV70: 0.98759376 | BW70: -3.5985365 | BX70: -2.0260953 | BY70: -0.13376741 | BZ70: 1.5506353 | CA70: -2.0166613 | CB70: 0.63010069 | CC70: -1.5794192 | CD70: 0.58724304 | CE70: 3.7737859 | CF70: 4.0975282 | CG70: 7.7522837 | CH70: 7.142957
A71: P.5 | B71: Formación bruta de capital | G71: 19.907411 | H71: 16.519072 | I71: 20.948751 | J71: 16.93381 | K71: 21.788961 | L71: 20.682687 | M71: 17.304944 | N71: 15.797051 | O71: 8.7137964 | P71: 7.2770708 | Q71: 8.4327229 | R71: 9.083322 | S71: -2.6238016 | T71: -3.5829928 | U71: -5.4612435 | V71: -6.2955734 | W71: 3.6104794 | X71: 7.4512406 | Y71: 8.2487116 | Z71: 9.5620949 | AA71: 19.501491 | AB71: 18.128726 | AC71: 19.663871 | AD71: 18.515927 | AE71: 8.2135443 | AF71: 9.1550073 | AG71: 4.9693387 | AH71: 2.886713 | AI71: 3.039705 | AJ71: 4.1594529 | AK71: 8.0583647 | AL71: 7.8066242 | AM71: 15.240721 | AN71: 12.187265 | AO71: 10.148762 | AP71: 11.95356 | AQ71: 0.017803085 | AR71: -3.5218523 | AS71: -1.3248623 | AT71: -1.1512249 | AU71: 8.512129 | AV71: 3.0073956 | AW71: 2.4184411 | AX71: -0.16256763 | AY71: 0.71061814 | AZ71: -1.44208 | BA71: -2.2365365 | BB71: -3.2283737 | BC71: -4.8673685 | BD71: -1.9889594 | BE71: -0.65410309 | BF71: 1.5041011 | BG71: 8.9400206 | BH71: 5.4754471 | BI71: 5.4499486 | BJ71: 2.9524327 | BK71: -10.843654 | BL71: -21.228519 | BM71: -19.943871 | BN71: -20.680621 | BO71: -3.9821698 | BP71: 11.684676 | BQ71: 10.594626 | BR71: 11.566353 | BS71: 18.330377 | BT71: 12.636249 | BU71: 14.023475 | BV71: 16.042897 | BW71: -0.40017525 | BX71: -6.6075687 | BY71: -13.908726 | BZ71: -16.102327 | CA71: -11.681392 | CB71: -5.65864 | CC71: 1.8689905 | CD71: 2.3929426 | CE71: 7.8995245 | CF71: 6.5640316 | CG71: 4.7058954 | CH71: 2.088992
A72: P.51 | B72: Formación bruta de capital fijo | G72: 11.638126 | H72: 13.250262 | I72: 17.742476 | J72: 18.771673 | K72: 28.932455 | L72: 28.670424 | M72: 25.081398 | N72: 19.891251 | O72: -9.6931927 | P72: -3.1531039 | Q72: -2.9568176 | R72: -2.7154683 | S72: 7.0507812 | T72: 4.3293208 | U72: 5.102145 | V72: 4.4552709 | W72: -0.49944205 | X72: 5.2466688 | Y72: 4.8890493 | Z72: 7.1047172 | AA72: 18.105953 | AB72: 12.736863 | AC72: 13.731183 | AD72: 12.211969 | AE72: 4.6177297 | AF72: 6.3732932 | AG72: 4.7809536 | AH72: 3.3341363 | AI72: 9.7302993 | AJ72: 8.022863 | AK72: 6.6385288 | AL72: 8.4798332 | AM72: 11.963956 | AN72: 9.7982665 | AO72: 11.306127 | AP72: 9.2065444 | AQ72: 4.8640858 | AR72: 5.6141236 | AS72: 4.935609 | AT72: 2.8083101 | AU72: -5.6511658 | AV72: -4.1911734 | AW72: -5.0340829 | AX72: -2.890029 | AY72: 4.9865982 | AZ72: 1.5025057 | BA72: 2.7737852 | BB72: 1.8542749 | BC72: -2.6650221 | BD72: 0.91864302 | BE72: 1.0035211 | BF72: 1.0368404 | BG72: 13.219209 | BH72: 6.4737388 | BI72: 4.7182518 | BJ72: 2.2364676 | BK72: -10.982304 | BL72: -27.910956 | BM72: -27.106223 | BN72: -23.621728 | BO72: 5.0135957 | BP72: 20.248023 | BQ72: 18.191287 | BR72: 16.696075 | BS72: 13.4115 | BT72: 12.141644 | BU72: 12.643058 | BV72: 11.498044 | BW72: -5.1317244 | BX72: -8.8316507 | BY72: -11.230286 | BZ72: -12.81619 | CA72: -9.8709691 | CB72: -5.2096173 | CC72: -2.7423994 | CD72: 0.66963749 | CE72: 1.9355908 | CF72: 2.0255024 | CG72: 3.059012 | CH72: 1.3374095
A73: P.6 | B73: Exportaciones | G73: 12.635058 | H73: 8.9836024 | I73: 8.5381884 | J73: 9.5182979 | K73: 1.8455467 | L73: 1.4696355 | M73: 3.8611398 | N73: 6.2198875 | O73: 13.790024 | P73: 12.958573 | Q73: 8.2161431 | R73: 2.0367552 | S73: -5.7195153 | T73: -8.0440634 | U73: -7.7738333 | V73: -5.2063019 | W73: -0.8519465 | X73: 1.9419241 | Y73: 1.9145651 | Z73: 2.0623651 | AA73: 13.34133 | AB73: 12.386421 | AC73: 12.194455 | AD73: 12.257542 | AE73: 8.5439494 | AF73: 5.3600518 | AG73: 5.7632162 | AH73: 4.4732765 | AI73: -2.9367239 | AJ73: 2.7849924 | AK73: 2.1652789 | AL73: 4.6768894 | AM73: 5.5613579 | AN73: 1.1785901 | AO73: 1.7837028 | AP73: -0.28895453 | AQ73: 0.27169252 | AR73: 3.2478516 | AS73: 1.154913 | AT73: 1.6580294 | AU73: -1.6914923 | AV73: -3.1517147 | AW73: -1.7870894 | AX73: -0.20883623 | AY73: 3.1293426 | AZ73: 3.1263114 | BA73: 3.3508492 | BB73: 2.5693665 | BC73: -2.3173911 | BD73: -1.2292419 | BE73: -0.29088842 | BF73: 0.64234845 | BG73: 6.910648 | BH73: 6.7986712 | BI73: 5.3580713 | BJ73: 3.0840977 | BK73: -7.0847091 | BL73: -19.445398 | BM73: -22.330759 | BN73: -22.459265 | BO73: -10.127757 | BP73: 0.33226511 | BQ73: 8.3476397 | BR73: 14.634123 | BS73: 17.012064 | BT73: 20.909196 | BU73: 18.425672 | BV73: 12.460566 | BW73: 3.2341177 | BX73: 2.3877098 | BY73: 1.7066223 | BZ73: 3.1133353 | CA73: -0.23239467 | CB73: 0.066432542 | CC73: -0.28488496 | CD73: 0.39029345 | CE73: 3.258041 | CF73: 1.7882505 | CG73: 2.09898 | CH73: 1.8434401
A74: P.7 | B74: Importaciones | G74: 15.423619 | H74: 16.456616 | I74: 18.276501 | J74: 17.681811 | K74: 15.765296 | L74: 13.086447 | M74: 12.927646 | N74: 13.85803 | O74: 16.970581 | P74: 13.895338 | Q74: 12.285666 | R74: 12.511734 | S74: 0.26719708 | T74: -3.9800413 | U74: -7.0863362 | V74: -8.6476874 | W74: -0.25767188 | X74: 6.2290398 | Y74: 9.4788218 | Z74: 10.829835 | AA74: 19.214571 | AB74: 20.927844 | AC74: 20.554163 | AD74: 20.229078 | AE74: 14.615698 | AF74: 12.022768 | AG74: 11.396773 | AH74: 9.3750865 | AI74: 6.7400812 | AJ74: 8.2768196 | AK74: 8.3385758 | AL74: 8.5240256 | AM74: 8.4607985 | AN74: 7.743644 | AO74: 6.6071139 | AP74: 7.7600135 | AQ74: 1.5171606 | AR74: -0.90367202 | AS74: 0.83244673 | AT74: -1.0809377 | AU74: -2.1369694 | AV74: -1.896227 | AW74: -4.2650274 | AX74: -3.5409029 | AY74: 2.4592549 | AZ74: 2.5122521 | BA74: 2.1637644 | BB74: 1.0188395 | BC74: -1.3976376 | BD74: 1.638041 | BE74: 2.7864823 | BF74: 5.8054191 | BG74: 11.88535 | BH74: 10.447074 | BI74: 10.625632 | BJ74: 7.3439731 | BK74: -4.3160674 | BL74: -19.454492 | BM74: -21.579155 | BN74: -20.09246 | BO74: -5.2312769 | BP74: 16.569105 | BQ74: 24.123626 | BR74: 26.728667 | BS74: 38.83365 | BT74: 31.807958 | BU74: 28.873163 | BV74: 24.003222 | BW74: -1.6411994 | BX74: -4.8810088 | BY74: -9.6619286 | BZ74: -10.029885 | CA74: -11.094991 | CB74: -5.4587955 | CC74: -0.99966617 | CD74: 1.1636863 | CE74: 12.6906 | CF74: 11.506931 | CG74: 10.95868 | CH74: 8.4193133
A75: B.1b | B75: Producto Interno Bruto | G75: 6.3755741 | H75: 5.8398308 | I75: 6.463579 | J75: 6.7168687 | K75: 6.7128664 | L75: 6.7880534 | M75: 6.8111415 | N75: 6.7381947 | O75: 5.1743787 | P75: 4.9771747 | Q75: 4.4007395 | R75: 3.2834462 | S75: 0.14508701 | T75: 0.42348682 | U75: 0.46095765 | V75: 1.1396486 | W75: 3.8803502 | X75: 4.2578886 | Y75: 4.1854153 | Z75: 4.494659 | AA75: 6.7991977 | AB75: 6.7907431 | AC75: 7.1785509 | AD75: 6.947892 | AE75: 6.1351561 | AF75: 5.4789255 | AG75: 4.3597383 | AH75: 3.9126358 | AI75: 2.3818401 | AJ75: 3.8955175 | AK75: 4.6939146 | AL75: 5.1339935 | AM75: 6.6000143 | AN75: 4.9707736 | AO75: 4.7693932 | AP75: 4.49903 | AQ75: 2.8280769 | AR75: 3.1285569 | AS75: 3.2819408 | AT75: 2.9559014 | AU75: 2.3747844 | AV75: 2.2466521 | AW75: 2.0092355 | AX75: 2.0873825 | AY75: 1.0694632 | AZ75: 1.1709404 | BA75: 1.3487501 | BB75: 1.3593609 | BC75: 1.6492417 | BD75: 2.2065152 | BE75: 2.4382593 | BF75: 2.5643243 | BG75: 3.4755274 | BH75: 3.2714499 | BI75: 3.2215704 | BJ75: 3.1868554 | BK75: 0.34608976 | BL75: -8.3304749 | BM75: -8.5890432 | BN75: -7.1859141 | BO75: 1.4997004 | BP75: 9.3208753 | BQ75: 10.693916 | BR75: 10.801198 | BS75: 8.1051367 | BT75: 10.248387 | BU75: 9.248534 | BV75: 7.3282773 | BW75: 2.8075119 | BX75: 1.581759 | BY75: 0.88147833 | BZ75: 0.84181956 | CA75: 0.31878093 | CB75: 0.96497071 | CC75: 1.183254 | CD75: 1.4933073 | CE75: 2.593029 | CF75: 2.351614 | CG75: 2.7779431 | CH75: 2.6420088
A77: Fuente: DANE, PIB_T
A78: prpreliminar
A79: pprovisional
A80: 1Incluye el gasto de consumo final y la formación bruta de capital
A81: 2Instituciones sin fines de lucro que sirven a los hogares
A82: Actualizado el 16 de febrero de 2026

Sheet Proyección escenario demanda
A1: Suma Agregada Demanda anual
X3: PROYECCIÓN OFERTA ANUAL
B5: Concepto | C5: 2005 | D5: 2006 | E5: 2007 | F5: 2008 | G5: 2009 | H5: 2010 | I5: 2011 | J5: 2012 | K5: 2013 | L5: 2014 | M5: 2015 | N5: 2016 | O5: 2017 | P5: 2018 | Q5: 2019 | R5: 2020 | S5: 2021 | T5: 2022 | U5: 2023 | V5: 2024 | W5: 2025 | X5: 2026 | Y5: 2027 | Z5: 2028 | AA5: 2029 | AB5: 2030
A6: P.8 | B6: Demanda interna1 | C6: =SUM('C1G'!C13+'C1G'!D13+'C1G'!E13+'C1G'!F13) -> 501398 | D6: =SUM('C1G'!G13+'C1G'!H13+'C1G'!I13+'C1G'!J13) -> 543638 | E6: =SUM('C1G'!K13+'C1G'!L13+'C1G'!M13+'C1G'!N13) -> 588889 | F6: =SUM('C1G'!O13+'C1G'!P13+'C1G'!Q13+'C1G'!R13) -> 620158 | G6: =SUM('C1G'!S13+'C1G'!T13+'C1G'!U13+'C1G'!V13) -> 621733 | H6: =SUM('C1G'!W13+'C1G'!X13+'C1G'!Y13+'C1G'!Z13) -> 659317 | I6: =SUM('C1G'!AA13+'C1G'!AB13+'C1G'!AC13+'C1G'!AD13) -> 714946 | J6: =SUM('C1G'!AE13+'C1G'!AF13+'C1G'!AG13+'C1G'!AH13) -> 749968 | K6: =SUM('C1G'!AI13+'C1G'!AJ13+'C1G'!AK13+'C1G'!AL13) -> 794137 | L6: =SUM('C1G'!AM13+'C1G'!AN13+'C1G'!AO13+'C1G'!AP13) -> 841681 | M6: =SUM('C1G'!AQ13+'C1G'!AR13+'C1G'!AS13+'C1G'!AT13) -> 861506 | N6: =SUM('C1G'!AU13+'C1G'!AV13+'C1G'!AW13+'C1G'!AX13) -> 872095 | O6: =SUM('C1G'!AY13+'C1G'!AZ13+'C1G'!BA13+'C1G'!BB13) -> 881898 | P6: =SUM('C1G'!BC13+'C1G'!BD13+'C1G'!BE13+'C1G'!BF13) -> 912441 | Q6: =SUM('C1G'!BG13+'C1G'!BH13+'C1G'!BI13+'C1G'!BJ13) -> 949135 | R6: =SUM('C1G'!BK13+'C1G'!BL13+'C1G'!BM13+'C1G'!BN13) -> 877560 | S6: =SUM('C1G'!BO13:BR13) -> 994916 | T6: =SUM('C1G'!BS13:BV13) -> 1096913 | U6: =SUM('C1G'!BW13:'C1G'!BZ13) -> 1070480 | V6: =SUM('C1G'!CA13:'C1G'!CD13) -> 1087723 | W6: =SUM('C1G'!CE13:CH13) -> 1130011.7 | X6: =W6*(1+AVERAGE(W6/V6-1,(V6/U6-1))) -> 1161079 | Y6: =X6*(1+AVERAGE(X6/W6-1,(W6/V6-1))) -> 1199610.1 | Z6: =Y6*(1+AVERAGE(Y6/X6-1,(X6/W6-1))) -> 1236005.4 | AA6: =Z6*(1+AVERAGE(Z6/Y6-1,(Y6/X6-1))) -> 1275263.9 | AB6: =AA6*(1+AVERAGE(AA6/Z6-1,(Z6/Y6-1))) -> 1314861.9
A7: P.3 | B7: Gasto de consumo final | C7: =SUM('C1G'!C14+'C1G'!D14+'C1G'!E14+'C1G'!F14) -> 419077 | D7: =SUM('C1G'!G14+'C1G'!H14+'C1G'!I14+'C1G'!J14) -> 444943 | E7: =SUM('C1G'!K14+'C1G'!L14+'C1G'!M14+'C1G'!N14) -> 472591 | F7: =SUM('C1G'!O14+'C1G'!P14+'C1G'!Q14+'C1G'!R14) -> 492507 | G7: =SUM('C1G'!S14+'C1G'!T14+'C1G'!U14+'C1G'!V14) -> 503416 | H7: =SUM('C1G'!W14+'C1G'!X14+'C1G'!Y14+'C1G'!Z14) -> 529002 | I7: =SUM('C1G'!AA14+'C1G'!AB14+'C1G'!AC14+'C1G'!AD14) -> 558993 | J7: =SUM('C1G'!AE14+'C1G'!AF14+'C1G'!AG14+'C1G'!AH14) -> 589694 | K7: =SUM('C1G'!AI14+'C1G'!AJ14+'C1G'!AK14+'C1G'!AL14) -> 621266 | L7: =SUM('C1G'!AM14+'C1G'!AN14+'C1G'!AO14+'C1G'!AP14) -> 648134 | M7: =SUM('C1G'!AQ14+'C1G'!AR14+'C1G'!AS14+'C1G'!AT14) -> 670201 | N7: =SUM('C1G'!AU14+'C1G'!AV14+'C1G'!AW14+'C1G'!AX14) -> 681101 | O7: =SUM('C1G'!AY14+'C1G'!AZ14+'C1G'!BA14+'C1G'!BB14) -> 696973 | P7: =SUM('C1G'!BC14+'C1G'!BD14+'C1G'!BE14+'C1G'!BF14) -> 724648 | Q7: =SUM('C1G'!BG14+'C1G'!BH14+'C1G'!BI14+'C1G'!BJ14) -> 755756 | R7: =SUM('C1G'!BK14+'C1G'!BL14+'C1G'!BM14+'C1G'!BN14) -> 723908 | S7: =SUM('C1G'!BO14:BR14) -> 823563 | T7: =SUM('C1G'!BS14:BV14) -> 897827 | U7: =SUM('C1G'!BW14:'C1G'!BZ14) -> 903922 | V7: =SUM('C1G'!CA14:'C1G'!CD14) -> 917168 | W7: =SUM('C1G'!CE14:CH14) -> 955925.24 | X7: =W7*(1+AVERAGE(W7/V7-1,(V7/U7-1))) -> 983126.77 | Y7: =X7*(1+AVERAGE(X7/W7-1,(W7/V7-1))) -> 1017886.8 | Z7: =Y7*(1+AVERAGE(Y7/X7-1,(X7/W7-1))) -> 1050363.7 | AA7: =Z7*(1+AVERAGE(Z7/Y7-1,(Y7/X7-1))) -> 1085688.9 | AB7: =AA7*(1+AVERAGE(AA7/Z7-1,(Z7/Y7-1))) -> 1121265.6
A8: P.311 + P.313 + P.323 | B8: Gasto de consumo final individual de los hogares; gasto de consumo final de las ISFLH2 | C8: =SUM('C1G'!C15+'C1G'!D15+'C1G'!E15+'C1G'!F15) -> 348741 | D8: =SUM('C1G'!G15+'C1G'!H15+'C1G'!I15+'C1G'!J15) -> 370953 | E8: =SUM('C1G'!K15+'C1G'!L15+'C1G'!M15+'C1G'!N15) -> 395261 | F8: =SUM('C1G'!O15+'C1G'!P15+'C1G'!Q15+'C1G'!R15) -> 411526 | G8: =SUM('C1G'!S15+'C1G'!T15+'C1G'!U15+'C1G'!V15) -> 418556 | H8: =SUM('C1G'!W15+'C1G'!X15+'C1G'!Y15+'C1G'!Z15) -> 439704 | I8: =SUM('C1G'!AA15+'C1G'!AB15+'C1G'!AC15+'C1G'!AD15) -> 463891 | J8: =SUM('C1G'!AE15+'C1G'!AF15+'C1G'!AG15+'C1G'!AH15) -> 490026 | K8: =SUM('C1G'!AI15+'C1G'!AJ15+'C1G'!AK15+'C1G'!AL15) -> 512699 | L8: =SUM('C1G'!AM15+'C1G'!AN15+'C1G'!AO15+'C1G'!AP15) -> 534484 | M8: =SUM('C1G'!AQ15+'C1G'!AR15+'C1G'!AS15+'C1G'!AT15) -> 551013 | N8: =SUM('C1G'!AU15+'C1G'!AV15+'C1G'!AW15+'C1G'!AX15) -> 559739 | O8: =SUM('C1G'!AY15+'C1G'!AZ15+'C1G'!BA15+'C1G'!BB15) -> 571235 | P8: =SUM('C1G'!BC15+'C1G'!BD15+'C1G'!BE15+'C1G'!BF15) -> 589723 | Q8: =SUM('C1G'!BG15+'C1G'!BH15+'C1G'!BI15+'C1G'!BJ15) -> 613728 | R8: =SUM('C1G'!BK15+'C1G'!BL15+'C1G'!BM15+'C1G'!BN15) -> 582997 | S8: =SUM('C1G'!BO15:BR15) -> 668838 | T8: =SUM('C1G'!BS15:BV15) -> 741004 | U8: =SUM('C1G'!BW15:'C1G'!BZ15) -> 744807 | V8: =SUM('C1G'!CA15:'C1G'!CD15) -> 757023 | W8: =SUM('C1G'!CE15:CH15) -> 784516.15 | X8: =W8*(1+AVERAGE(W8/V8-1,(V8/U8-1))) -> 805195.62 | Y8: =X8*(1+AVERAGE(X8/W8-1,(W8/V8-1))) -> 830429.23 | Z8: =Y8*(1+AVERAGE(Y8/X8-1,(X8/W8-1))) -> 854386.28 | AA8: =Z8*(1+AVERAGE(Z8/Y8-1,(Y8/X8-1))) -> 880097.97 | AB8: =AA8*(1+AVERAGE(AA8/Z8-1,(Z8/Y8-1))) -> 906035.66
A9: P.312 + P.322 | B9: Gasto de consumo final del gobierno general | C9: =SUM('C1G'!C16+'C1G'!D16+'C1G'!E16+'C1G'!F16) -> 70375 | D9: =SUM('C1G'!G16+'C1G'!H16+'C1G'!I16+'C1G'!J16) -> 74044 | E9: =SUM('C1G'!K16+'C1G'!L16+'C1G'!M16+'C1G'!N16) -> 77427 | F9: =SUM('C1G'!O16+'C1G'!P16+'C1G'!Q16+'C1G'!R16) -> 81064 | G9: =SUM('C1G'!S16+'C1G'!T16+'C1G'!U16+'C1G'!V16) -> 84925 | H9: =SUM('C1G'!W16+'C1G'!X16+'C1G'!Y16+'C1G'!Z16) -> 89363 | I9: =SUM('C1G'!AA16+'C1G'!AB16+'C1G'!AC16+'C1G'!AD16) -> 95151 | J9: =SUM('C1G'!AE16+'C1G'!AF16+'C1G'!AG16+'C1G'!AH16) -> 99725 | K9: =SUM('C1G'!AI16+'C1G'!AJ16+'C1G'!AK16+'C1G'!AL16) -> 108596 | L9: =SUM('C1G'!AM16+'C1G'!AN16+'C1G'!AO16+'C1G'!AP16) -> 113674 | M9: =SUM('C1G'!AQ16+'C1G'!AR16+'C1G'!AS16+'C1G'!AT16) -> 119188 | N9: =SUM('C1G'!AU16+'C1G'!AV16+'C1G'!AW16+'C1G'!AX16) -> 121362 | O9: =SUM('C1G'!AY16+'C1G'!AZ16+'C1G'!BA16+'C1G'!BB16) -> 125783 | P9: =SUM('C1G'!BC16+'C1G'!BD16+'C1G'!BE16+'C1G'!BF16) -> 135030 | Q9: =SUM('C1G'!BG16+'C1G'!BH16+'C1G'!BI16+'C1G'!BJ16) -> 142152 | R9: =SUM('C1G'!BK16+'C1G'!BL16+'C1G'!BM16+'C1G'!BN16) -> 141071 | S9: =SUM('C1G'!BO16:BR16) -> 154922 | T9: =SUM('C1G'!BS16:BV16) -> 156452 | U9: =SUM('C1G'!BW16:'C1G'!BZ16) -> 158878 | V9: =SUM('C1G'!CA16:'C1G'!CD16) -> 159811 | W9: =SUM('C1G'!CE16:CH16) -> 171226.23 | X9: =W9*(1+AVERAGE(W9/V9-1,(V9/U9-1))) -> 177844.3 | Y9: =X9*(1+AVERAGE(X9/W9-1,(W9/V9-1))) -> 187632.9 | Z9: =Y9*(1+AVERAGE(Y9/X9-1,(X9/W9-1))) -> 196422.68 | AA9: =Z9*(1+AVERAGE(Z9/Y9-1,(Y9/X9-1))) -> 206429.03 | AB9: =AA9*(1+AVERAGE(AA9/Z9-1,(Z9/Y9-1))) -> 216522.24
A10: P.5 | B10: Formación bruta de capital | C10: =SUM('C1G'!C17+'C1G'!D17+'C1G'!E17+'C1G'!F17) -> 86720 | D10: =SUM('C1G'!G17+'C1G'!H17+'C1G'!I17+'C1G'!J17) -> 101405 | E10: =SUM('C1G'!K17+'C1G'!L17+'C1G'!M17+'C1G'!N17) -> 117424 | F10: =SUM('C1G'!O17+'C1G'!P17+'C1G'!Q17+'C1G'!R17) -> 128090 | G10: =SUM('C1G'!S17+'C1G'!T17+'C1G'!U17+'C1G'!V17) -> 120026 | H10: =SUM('C1G'!W17+'C1G'!X17+'C1G'!Y17+'C1G'!Z17) -> 131503 | I10: =SUM('C1G'!AA17+'C1G'!AB17+'C1G'!AC17+'C1G'!AD17) -> 155852 | J10: =SUM('C1G'!AE17+'C1G'!AF17+'C1G'!AG17+'C1G'!AH17) -> 160351 | K10: =SUM('C1G'!AI17+'C1G'!AJ17+'C1G'!AK17+'C1G'!AL17) -> 172869 | L10: =SUM('C1G'!AM17+'C1G'!AN17+'C1G'!AO17+'C1G'!AP17) -> 193533 | M10: =SUM('C1G'!AQ17+'C1G'!AR17+'C1G'!AS17+'C1G'!AT17) -> 191305 | N10: =SUM('C1G'!AU17+'C1G'!AV17+'C1G'!AW17+'C1G'!AX17) -> 190994 | O10: =SUM('C1G'!AY17+'C1G'!AZ17+'C1G'!BA17+'C1G'!BB17) -> 184828 | P10: =SUM('C1G'!BC17+'C1G'!BD17+'C1G'!BE17+'C1G'!BF17) -> 187608 | Q10: =SUM('C1G'!BG17+'C1G'!BH17+'C1G'!BI17+'C1G'!BJ17) -> 193147 | R10: =SUM('C1G'!BK17+'C1G'!BL17+'C1G'!BM17+'C1G'!BN17) -> 153203 | S10: =SUM('C1G'!BO17:BR17) -> 170923 | T10: =SUM('C1G'!BS17:BV17) -> 198344 | U10: =SUM('C1G'!BW17:'C1G'!BZ17) -> 166406 | V10: =SUM('C1G'!CA17:'C1G'!CD17) -> 170388 | W10: =SUM('C1G'!CE17:CH17) -> 173947.39 | X10: =W10*(1+AVERAGE(W10/V10-1,(V10/U10-1))) -> 177845.5 | Y10: =X10*(1+AVERAGE(X10/W10-1,(W10/V10-1))) -> 181695.81 | Z10: =Y10*(1+AVERAGE(Y10/X10-1,(X10/W10-1))) -> 185698.53 | AA10: =Z10*(1+AVERAGE(Z10/Y10-1,(Y10/X10-1))) -> 189754.14 | AB10: =AA10*(1+AVERAGE(AA10/Z10-1,(Z10/Y10-1))) -> 193916.35
A11: P.51 | B11: Formación bruta de capital fijo | C11: =SUM('C1G'!C18+'C1G'!D18+'C1G'!E18+'C1G'!F18) -> 85938 | D11: =SUM('C1G'!G18+'C1G'!H18+'C1G'!I18+'C1G'!J18) -> 102070 | E11: =SUM('C1G'!K18+'C1G'!L18+'C1G'!M18+'C1G'!N18) -> 122373 | F11: =SUM('C1G'!O18+'C1G'!P18+'C1G'!Q18+'C1G'!R18) -> 119050 | G11: =SUM('C1G'!S18+'C1G'!T18+'C1G'!U18+'C1G'!V18) -> 124354 | H11: =SUM('C1G'!W18+'C1G'!X18+'C1G'!Y18+'C1G'!Z18) -> 133189 | I11: =SUM('C1G'!AA18+'C1G'!AB18+'C1G'!AC18+'C1G'!AD18) -> 149454 | J11: =SUM('C1G'!AE18+'C1G'!AF18+'C1G'!AG18+'C1G'!AH18) -> 154437 | K11: =SUM('C1G'!AI18+'C1G'!AJ18+'C1G'!AK18+'C1G'!AL18) -> 167533 | L11: =SUM('C1G'!AM18+'C1G'!AN18+'C1G'!AO18+'C1G'!AP18) -> 182957 | M11: =SUM('C1G'!AQ18+'C1G'!AR18+'C1G'!AS18+'C1G'!AT18) -> 188095 | N11: =SUM('C1G'!AU18+'C1G'!AV18+'C1G'!AW18+'C1G'!AX18) -> 182659 | O11: =SUM('C1G'!AY18+'C1G'!AZ18+'C1G'!BA18+'C1G'!BB18) -> 186046 | P11: =SUM('C1G'!BC18+'C1G'!BD18+'C1G'!BE18+'C1G'!BF18) -> 187975 | Q11: =SUM('C1G'!BG18+'C1G'!BH18+'C1G'!BI18+'C1G'!BJ18) -> 192179 | R11: =SUM('C1G'!BK18+'C1G'!BL18+'C1G'!BM18+'C1G'!BN18) -> 146783 | S11: =SUM('C1G'!BO18:BR18) -> 171290 | T11: =SUM('C1G'!BS18:BV18) -> 190985 | U11: =SUM('C1G'!BW18:'C1G'!BZ18) -> 166508 | V11: =SUM('C1G'!CA18:'C1G'!CD18) -> 167623 | W11: =SUM('C1G'!CE18:CH18) -> 169864.81 | X11: =W11*(1+AVERAGE(W11/V11-1,(V11/U11-1))) -> 171569.44 | Y11: =X11*(1+AVERAGE(X11/W11-1,(W11/V11-1))) -> 173577.6 | Z11: =Y11*(1+AVERAGE(Y11/X11-1,(X11/W11-1))) -> 175464.38 | AA11: =Z11*(1+AVERAGE(Z11/Y11-1,(Y11/X11-1))) -> 177444.9 | AB11: =AA11*(1+AVERAGE(AA11/Z11-1,(Z11/Y11-1))) -> 179410.75
A12: P.6 | B12: Exportaciones | C12: =SUM('C1G'!C19+'C1G'!D19+'C1G'!E19+'C1G'!F19) -> 88125 | D12: =SUM('C1G'!G19+'C1G'!H19+'C1G'!I19+'C1G'!J19) -> 96513 | E12: =SUM('C1G'!K19+'C1G'!L19+'C1G'!M19+'C1G'!N19) -> 102516 | F12: =SUM('C1G'!O19+'C1G'!P19+'C1G'!Q19+'C1G'!R19) -> 104604 | G12: =SUM('C1G'!S19+'C1G'!T19+'C1G'!U19+'C1G'!V19) -> 99158 | H12: =SUM('C1G'!W19+'C1G'!X19+'C1G'!Y19+'C1G'!Z19) -> 101203 | I12: =SUM('C1G'!AA19+'C1G'!AB19+'C1G'!AC19+'C1G'!AD19) -> 113608 | J12: =SUM('C1G'!AE19+'C1G'!AF19+'C1G'!AG19+'C1G'!AH19) -> 118690 | K12: =SUM('C1G'!AI19+'C1G'!AJ19+'C1G'!AK19+'C1G'!AL19) -> 124241 | L12: =SUM('C1G'!AM19+'C1G'!AN19+'C1G'!AO19+'C1G'!AP19) -> 123882 | M12: =SUM('C1G'!AQ19+'C1G'!AR19+'C1G'!AS19+'C1G'!AT19) -> 125936 | N12: =SUM('C1G'!AU19+'C1G'!AV19+'C1G'!AW19+'C1G'!AX19) -> 125673 | O12: =SUM('C1G'!AY19+'C1G'!AZ19+'C1G'!BA19+'C1G'!BB19) -> 128902 | P12: =SUM('C1G'!BC19+'C1G'!BD19+'C1G'!BE19+'C1G'!BF19) -> 129730 | Q12: =SUM('C1G'!BG19+'C1G'!BH19+'C1G'!BI19+'C1G'!BJ19) -> 133731 | R12: =SUM('C1G'!BK19+'C1G'!BL19+'C1G'!BM19+'C1G'!BN19) -> 103696 | S12: =SUM('C1G'!BO19:BR19) -> 118871 | T12: =SUM('C1G'!BS19:BV19) -> 133683 | U12: =SUM('C1G'!BW19:'C1G'!BZ19) -> 137845 | V12: =SUM('C1G'!CA19:'C1G'!CD19) -> 138383 | W12: =SUM('C1G'!CE19:CH19) -> 140934.01 | X12: =W12*(1+AVERAGE(W12/V12-1,(V12/U12-1))) -> 142508.05 | Y12: =X12*(1+AVERAGE(X12/W12-1,(W12/V12-1))) -> 144617.39 | Z12: =Y12*(1+AVERAGE(Y12/X12-1,(X12/W12-1))) -> 146495.26 | AA12: =Z12*(1+AVERAGE(Z12/Y12-1,(Y12/X12-1))) -> 148530.57 | AB12: =AA12*(1+AVERAGE(AA12/Z12-1,(Z12/Y12-1))) -> 150526.7
A13: P.7 | B13: Importaciones | C13: =SUM('C1G'!C20+'C1G'!D20+'C1G'!E20+'C1G'!F20) -> 78708 | D13: =SUM('C1G'!G20+'C1G'!H20+'C1G'!I20+'C1G'!J20) -> 92625 | E13: =SUM('C1G'!K20+'C1G'!L20+'C1G'!M20+'C1G'!N20) -> 105461 | F13: =SUM('C1G'!O20+'C1G'!P20+'C1G'!Q20+'C1G'!R20) -> 118656 | G13: =SUM('C1G'!S20+'C1G'!T20+'C1G'!U20+'C1G'!V20) -> 108395 | H13: =SUM('C1G'!W20+'C1G'!X20+'C1G'!Y20+'C1G'!Z20) -> 120134 | I13: =SUM('C1G'!AA20+'C1G'!AB20+'C1G'!AC20+'C1G'!AD20) -> 144436 | J13: =SUM('C1G'!AE20+'C1G'!AF20+'C1G'!AG20+'C1G'!AH20) -> 157977 | K13: =SUM('C1G'!AI20+'C1G'!AJ20+'C1G'!AK20+'C1G'!AL20) -> 171443 | L13: =SUM('C1G'!AM20+'C1G'!AN20+'C1G'!AO20+'C1G'!AP20) -> 184747 | M13: =SUM('C1G'!AQ20+'C1G'!AR20+'C1G'!AS20+'C1G'!AT20) -> 182750 | N13: =SUM('C1G'!AU20+'C1G'!AV20+'C1G'!AW20+'C1G'!AX20) -> 176279 | O13: =SUM('C1G'!AY20+'C1G'!AZ20+'C1G'!BA20+'C1G'!BB20) -> 178075 | P13: =SUM('C1G'!BC20+'C1G'!BD20+'C1G'!BE20+'C1G'!BF20) -> 188413 | Q13: =SUM('C1G'!BG20+'C1G'!BH20+'C1G'!BI20+'C1G'!BJ20) -> 202250 | R13: =SUM('C1G'!BK20+'C1G'!BL20+'C1G'!BM20+'C1G'!BN20) -> 161613 | S13: =SUM('C1G'!BO20:BR20) -> 204810 | T13: =SUM('C1G'!BS20:BV20) -> 253971 | U13: =SUM('C1G'!BW20:'C1G'!BZ20) -> 228498 | V13: =SUM('C1G'!CA20:'C1G'!CD20) -> 231157 | W13: =SUM('C1G'!CE20:CH20) -> 250618.83 | X13: =W13*(1+AVERAGE(W13/V13-1,(V13/U13-1))) -> 262627.23 | Y13: =X13*(1+AVERAGE(X13/W13-1,(W13/V13-1))) -> 279974.83 | Z13: =Y13*(1+AVERAGE(Y13/X13-1,(X13/W13-1))) -> 295929.06 | AA13: =Z13*(1+AVERAGE(Z13/Y13-1,(Y13/X13-1))) -> 314134.41 | AB13: =AA13*(1+AVERAGE(AA13/Z13-1,(Z13/Y13-1))) -> 332747.48
A14: B.1b | B14: Producto Interno Bruto | C14: =SUM('C1G'!C21+'C1G'!D21+'C1G'!E21+'C1G'!F21) -> 514853 | D14: =SUM('C1G'!G21+'C1G'!H21+'C1G'!I21+'C1G'!J21) -> 549435 | E14: =SUM('C1G'!K21+'C1G'!L21+'C1G'!M21+'C1G'!N21) -> 586457 | F14: =SUM('C1G'!O21+'C1G'!P21+'C1G'!Q21+'C1G'!R21) -> 605713 | G14: =SUM('C1G'!S21+'C1G'!T21+'C1G'!U21+'C1G'!V21) -> 612616 | H14: =SUM('C1G'!W21+'C1G'!X21+'C1G'!Y21+'C1G'!Z21) -> 640151 | I14: =SUM('C1G'!AA21+'C1G'!AB21+'C1G'!AC21+'C1G'!AD21) -> 684628 | J14: =SUM('C1G'!AE21+'C1G'!AF21+'C1G'!AG21+'C1G'!AH21) -> 711415 | K14: =SUM('C1G'!AI21+'C1G'!AJ21+'C1G'!AK21+'C1G'!AL21) -> 747939 | L14: =SUM('C1G'!AM21+'C1G'!AN21+'C1G'!AO21+'C1G'!AP21) -> 781589 | M14: =SUM('C1G'!AQ21+'C1G'!AR21+'C1G'!AS21+'C1G'!AT21) -> 804692 | N14: =SUM('C1G'!AU21+'C1G'!AV21+'C1G'!AW21+'C1G'!AX21) -> 821489 | O14: =SUM('C1G'!AY21+'C1G'!AZ21+'C1G'!BA21+'C1G'!BB21) -> 832656 | P14: =SUM('C1G'!BC21+'C1G'!BD21+'C1G'!BE21+'C1G'!BF21) -> 854008 | Q14: =SUM('C1G'!BG21+'C1G'!BH21+'C1G'!BI21+'C1G'!BJ21) -> 881224 | R14: =SUM('C1G'!BK21+'C1G'!BL21+'C1G'!BM21+'C1G'!BN21) -> 817900 | S14: =SUM('C1G'!BO21:BR21) -> 906243 | T14: =SUM('C1G'!BS21:BV21) -> 972655 | U14: =SUM('C1G'!BW21:'C1G'!BZ21) -> 980843 | V14: =SUM('C1G'!CA21:'C1G'!CD21) -> 995490 | W14: =SUM('C1G'!CE21:CH21) -> 1021790.9 | X14: =W14*(1+AVERAGE(W14/V14-1,(V14/U14-1))) -> 1042918.1 | Y14: =X14*(1+AVERAGE(X14/W14-1,(W14/V14-1))) -> 1067477.1 | Z14: =Y14*(1+AVERAGE(Y14/X14-1,(X14/W14-1))) -> 1091081.6 | AA14: =Z14*(1+AVERAGE(Z14/Y14-1,(Y14/X14-1))) -> 1115991.4 | AB14: =AA14*(1+AVERAGE(AA14/Z14-1,(Z14/Y14-1))) -> 1141069.3
